Workbook

Sheet General Information
A1: BOSE QuietComfort | C1: Group 2
A4: DETAILED INFORMATION
A6: Goal of Forecasting
A23: Reference Planning Period
A36: Trend and Seasonality
A50: Forecast
A75: Supply Plan
A85: Inventory Management

Sheet Raw Black and outliers handling
A1: Black QC Headphones: Raw Data and Outliers Handling
B3: Date | C3: Date Cleaned | D3: Orders | F3: Date | G3: Combined Daily order | H3: Quarters | I3: Moving Average on Months | J3: Lower Bound Computed on Moving Average | K3: Upper Bound Computed on Moving Average | L3: Presumed Outliers | M3: Period for moving average | N3: Lower Bound Computed on the whole series of data | O3: Upper Bound Computed on the whole series of data | Q3: Bose Quiet Comfort Black
B4: 45562.73 | C4: =INT(B4) -> 45562 | D4: 13614 | F4: 45562 | G4: =SUMIF(C:C, F4, D:D) -> 25910 | H4: =ROUNDUP(MONTH(Table3[[#This Row],[Date]])/3, 0) -> 3 | L4: #N/A | M4: 22 | N4: =$V$46 -> 45729.883 | O4: =$U$46 -> 5411.2257
B5: 45562.342 | C5: =INT(B5) -> 45562 | D5: 12296 | F5: =WORKDAY(F4,-1) -> 45561 | G5: =SUMIF(C:C, F5, D:D) -> 36491 | H5: =ROUNDUP(MONTH(Table3[[#This Row],[Date]])/3, 0) -> 3 | L5: =Table3[[#This Row],[Combined Daily order]] -> 36491 | N5: =$V$46 -> 45729.883 | O5: =$U$46 -> 5411.2257
B6: 45561.927 | C6: =INT(B6) -> 45561 | D6: 13540 | F6: =WORKDAY(F5,-1) -> 45560 | G6: =SUMIF(C:C, F6, D:D) -> 26068 | H6: =ROUNDUP(MONTH(Table3[[#This Row],[Date]])/3, 0) -> 3 | L6: #N/A | N6: =$V$46 -> 45729.883 | O6: =$U$46 -> 5411.2257
B7: 45561.508 | C7: =INT(B7) -> 45561 | D7: 11675 | F7: =WORKDAY(F6,-1) -> 45559 | G7: =SUMIF(C:C, F7, D:D) -> 40865 | H7: =ROUNDUP(MONTH(Table3[[#This Row],[Date]])/3, 0) -> 3 | L7: =Table3[[#This Row],[Combined Daily order]] -> 40865 | N7: =$V$46 -> 45729.883 | O7: =$U$46 -> 5411.2257
B8: 45561.088 | C8: =INT(B8) -> 45561 | D8: 11276 | F8: =WORKDAY(F7,-1) -> 45558 | G8: =SUMIF(C:C, F8, D:D) -> 27032 | H8: =ROUNDUP(MONTH(Table3[[#This Row],[Date]])/3, 0) -> 3 | L8: #N/A | N8: =$V$46 -> 45729.883 | O8: =$U$46 -> 5411.2257
B9: 45560.712 | C9: =INT(B9) -> 45560 | D9: 12662 | F9: =WORKDAY(F8,-1) -> 45555 | G9: =SUMIF(C:C, F9, D:D) -> 25465 | H9: =ROUNDUP(MONTH(Table3[[#This Row],[Date]])/3, 0) -> 3 | L9: #N/A | N9: =$V$46 -> 45729.883 | O9: =$U$46 -> 5411.2257
B10: 45560.315 | C10: =INT(B10) -> 45560 | D10: 13406 | F10: =WORKDAY(F9,-1) -> 45554 | G10: =SUMIF(C:C, F10, D:D) -> 36114 | H10: =ROUNDUP(MONTH(Table3[[#This Row],[Date]])/3, 0) -> 3 | L10: =Table3[[#This Row],[Combined Daily order]] -> 36114 | N10: =$V$46 -> 45729.883 | O10: =$U$46 -> 5411.2257
B11: 45559.924 | C11: =INT(B11) -> 45559 | D11: 14628 | F11: =WORKDAY(F10,-1) -> 45553 | G11: =SUMIF(C:C, F11, D:D) -> 25049 | H11: =ROUNDUP(MONTH(Table3[[#This Row],[Date]])/3, 0) -> 3 | L11: #N/A | N11: =$V$46 -> 45729.883 | O11: =$U$46 -> 5411.2257
B12: 45559.553 | C12: =INT(B12) -> 45559 | D12: 12678 | F12: =WORKDAY(F11,-1) -> 45552 | G12: =SUMIF(C:C, F12, D:D) -> 36767 | H12: =ROUNDUP(MONTH(Table3[[#This Row],[Date]])/3, 0) -> 3 | L12: =Table3[[#This Row],[Combined Daily order]] -> 36767 | N12: =$V$46 -> 45729.883 | O12: =$U$46 -> 5411.2257
B13: 45559.149 | C13: =INT(B13) -> 45559 | D13: 13559 | F13: =WORKDAY(F12,-1) -> 45551 | G13: =SUMIF(C:C, F13, D:D) -> 27301 | H13: =ROUNDUP(MONTH(Table3[[#This Row],[Date]])/3, 0) -> 3 | L13: #N/A | N13: =$V$46 -> 45729.883 | O13: =$U$46 -> 5411.2257
B14: 45558.735 | C14: =INT(B14) -> 45558 | D14: 13248 | F14: =WORKDAY(F13,-1) -> 45548 | G14: =SUMIF(C:C, F14, D:D) -> 35320 | H14: =ROUNDUP(MONTH(Table3[[#This Row],[Date]])/3, 0) -> 3 | L14: #N/A | N14: =$V$46 -> 45729.883 | O14: =$U$46 -> 5411.2257
B15: 45558.346 | C15: =INT(B15) -> 45558 | D15: 13784 | F15: =WORKDAY(F14,-1) -> 45547 | G15: =SUMIF(C:C, F15, D:D) -> 25240 | H15: =ROUNDUP(MONTH(Table3[[#This Row],[Date]])/3, 0) -> 3 | I15: {=(SUM(OFFSET(G15, -$M$4/2+1, 0, $M$4-1, 1)) + (INDIRECT("G" & ROW(G15) - $M$4/2) + INDIRECT("G" & ROW(G15) + $M$4/2))/2) / $M$4} -> 31088.341 | J15: =Table3[[#This Row],[Moving Average on Months]] - 1.96*STDEV(OFFSET(Table3[[#This Row],[Combined Daily order]], -$M$4/2, 0, $M$4+1, 1)) -> 17937.05 | K15: =Table3[[#This Row],[Moving Average on Months]] + 1.96*STDEV(OFFSET(Table3[[#This Row],[Combined Daily order]], -$M$4/2, 0, $M$4+1, 1)) -> 44239.632 | L15: #N/A | N15: =$V$46 -> 45729.883 | O15: =$U$46 -> 5411.2257
B16: 45555.654 | C16: =INT(B16) -> 45555 | D16: 12449 | F16: =WORKDAY(F15,-1) -> 45546 | G16: =SUMIF(C:C, F16, D:D) -> 39060 | H16: =ROUNDUP(MONTH(Table3[[#This Row],[Date]])/3, 0) -> 3 | I16: {=(SUM(OFFSET(G16, -$M$4/2+1, 0, $M$4-1, 1)) + (INDIRECT("G" & ROW(G16) - $M$4/2) + INDIRECT("G" & ROW(G16) + $M$4/2))/2) / $M$4} -> 30999.636 | J16: =Table3[[#This Row],[Moving Average on Months]] - 1.96*STDEV(OFFSET(Table3[[#This Row],[Combined Daily order]], -$M$4/2, 0, $M$4+1, 1)) -> 17844.926 | K16: =Table3[[#This Row],[Moving Average on Months]] + 1.96*STDEV(OFFSET(Table3[[#This Row],[Combined Daily order]], -$M$4/2, 0, $M$4+1, 1)) -> 44154.346 | L16: =Table3[[#This Row],[Combined Daily order]] -> 39060 | N16: =$V$46 -> 45729.883 | O16: =$U$46 -> 5411.2257
B17: 45555.224 | C17: =INT(B17) -> 45555 | D17: 13016 | F17: =WORKDAY(F16,-1) -> 45545 | G17: =SUMIF(C:C, F17, D:D) -> 24227 | H17: =ROUNDUP(MONTH(Table3[[#This Row],[Date]])/3, 0) -> 3 | I17: {=(SUM(OFFSET(G17, -$M$4/2+1, 0, $M$4-1, 1)) + (INDIRECT("G" & ROW(G17) - $M$4/2) + INDIRECT("G" & ROW(G17) + $M$4/2))/2) / $M$4} -> 30948.932 | J17: =Table3[[#This Row],[Moving Average on Months]] - 1.96*STDEV(OFFSET(Table3[[#This Row],[Combined Daily order]], -$M$4/2, 0, $M$4+1, 1)) -> 17691.219 | K17: =Table3[[#This Row],[Moving Average on Months]] + 1.96*STDEV(OFFSET(Table3[[#This Row],[Combined Daily order]], -$M$4/2, 0, $M$4+1, 1)) -> 44206.644 | L17: #N/A | N17: =$V$46 -> 45729.883 | O17: =$U$46 -> 5411.2257
B18: 45554.82 | C18: =INT(B18) -> 45554 | D18: 12256 | F18: =WORKDAY(F17,-1) -> 45544 | G18: =SUMIF(C:C, F18, D:D) -> 26751 | H18: =ROUNDUP(MONTH(Table3[[#This Row],[Date]])/3, 0) -> 3 | I18: {=(SUM(OFFSET(G18, -$M$4/2+1, 0, $M$4-1, 1)) + (INDIRECT("G" & ROW(G18) - $M$4/2) + INDIRECT("G" & ROW(G18) + $M$4/2))/2) / $M$4} -> 30737 | J18: =Table3[[#This Row],[Moving Average on Months]] - 1.96*STDEV(OFFSET(Table3[[#This Row],[Combined Daily order]], -$M$4/2, 0, $M$4+1, 1)) -> 17586.795 | K18: =Table3[[#This Row],[Moving Average on Months]] + 1.96*STDEV(OFFSET(Table3[[#This Row],[Combined Daily order]], -$M$4/2, 0, $M$4+1, 1)) -> 43887.205 | L18: #N/A | N18: =$V$46 -> 45729.883 | O18: =$U$46 -> 5411.2257
B19: 45554.406 | C19: =INT(B19) -> 45554 | D19: 11650 | F19: =WORKDAY(F18,-1) -> 45541 | G19: =SUMIF(C:C, F19, D:D) -> 42169 | H19: =ROUNDUP(MONTH(Table3[[#This Row],[Date]])/3, 0) -> 3 | I19: {=(SUM(OFFSET(G19, -$M$4/2+1, 0, $M$4-1, 1)) + (INDIRECT("G" & ROW(G19) - $M$4/2) + INDIRECT("G" & ROW(G19) + $M$4/2))/2) / $M$4} -> 30509 | J19: =Table3[[#This Row],[Moving Average on Months]] - 1.96*STDEV(OFFSET(Table3[[#This Row],[Combined Daily order]], -$M$4/2, 0, $M$4+1, 1)) -> 17800.096 | K19: =Table3[[#This Row],[Moving Average on Months]] + 1.96*STDEV(OFFSET(Table3[[#This Row],[Combined Daily order]], -$M$4/2, 0, $M$4+1, 1)) -> 43217.904 | L19: =Table3[[#This Row],[Combined Daily order]] -> 42169 | N19: =$V$46 -> 45729.883 | O19: =$U$46 -> 5411.2257
B20: 45554.012 | C20: =INT(B20) -> 45554 | D20: 12208 | F20: =WORKDAY(F19,-1) -> 45540 | G20: =SUMIF(C:C, F20, D:D) -> 24206 | H20: =ROUNDUP(MONTH(Table3[[#This Row],[Date]])/3, 0) -> 3 | I20: {=(SUM(OFFSET(G20, -$M$4/2+1, 0, $M$4-1, 1)) + (INDIRECT("G" & ROW(G20) - $M$4/2) + INDIRECT("G" & ROW(G20) + $M$4/2))/2) / $M$4} -> 30645.773 | J20: =Table3[[#This Row],[Moving Average on Months]] - 1.96*STDEV(OFFSET(Table3[[#This Row],[Combined Daily order]], -$M$4/2, 0, $M$4+1, 1)) -> 17926.703 | K20: =Table3[[#This Row],[Moving Average on Months]] + 1.96*STDEV(OFFSET(Table3[[#This Row],[Combined Daily order]], -$M$4/2, 0, $M$4+1, 1)) -> 43364.842 | L20: #N/A | N20: =$V$46 -> 45729.883 | O20: =$U$46 -> 5411.2257
B21: 45553.63 | C21: =INT(B21) -> 45553 | D21: 11847 | F21: =WORKDAY(F20,-1) -> 45539 | G21: =SUMIF(C:C, F21, D:D) -> 39550 | H21: =ROUNDUP(MONTH(Table3[[#This Row],[Date]])/3, 0) -> 3 | I21: {=(SUM(OFFSET(G21, -$M$4/2+1, 0, $M$4-1, 1)) + (INDIRECT("G" & ROW(G21) - $M$4/2) + INDIRECT("G" & ROW(G21) + $M$4/2))/2) / $M$4} -> 30566.091 | J21: =Table3[[#This Row],[Moving Average on Months]] - 1.96*STDEV(OFFSET(Table3[[#This Row],[Combined Daily order]], -$M$4/2, 0, $M$4+1, 1)) -> 17728.781 | K21: =Table3[[#This Row],[Moving Average on Months]] + 1.96*STDEV(OFFSET(Table3[[#This Row],[Combined Daily order]], -$M$4/2, 0, $M$4+1, 1)) -> 43403.401 | L21: =Table3[[#This Row],[Combined Daily order]] -> 39550 | N21: =$V$46 -> 45729.883 | O21: =$U$46 -> 5411.2257
B22: 45553.239 | C22: =INT(B22) -> 45553 | D22: 13202 | F22: =WORKDAY(F21,-1) -> 45538 | G22: =SUMIF(C:C, F22, D:D) -> 24805 | H22: =ROUNDUP(MONTH(Table3[[#This Row],[Date]])/3, 0) -> 3 | I22: {=(SUM(OFFSET(G22, -$M$4/2+1, 0, $M$4-1, 1)) + (INDIRECT("G" & ROW(G22) - $M$4/2) + INDIRECT("G" & ROW(G22) + $M$4/2))/2) / $M$4} -> 30450.273 | J22: =Table3[[#This Row],[Moving Average on Months]] - 1.96*STDEV(OFFSET(Table3[[#This Row],[Combined Daily order]], -$M$4/2, 0, $M$4+1, 1)) -> 17814.31 | K22: =Table3[[#This Row],[Moving Average on Months]] + 1.96*STDEV(OFFSET(Table3[[#This Row],[Combined Daily order]], -$M$4/2, 0, $M$4+1, 1)) -> 43086.235 | L22: #N/A | N22: =$V$46 -> 45729.883 | O22: =$U$46 -> 5411.2257
B23: 45552.866 | C23: =INT(B23) -> 45552 | D23: 11602 | F23: =WORKDAY(F22,-1) -> 45537 | G23: =SUMIF(C:C, F23, D:D) -> 38326 | H23: =ROUNDUP(MONTH(Table3[[#This Row],[Date]])/3, 0) -> 3 | I23: {=(SUM(OFFSET(G23, -$M$4/2+1, 0, $M$4-1, 1)) + (INDIRECT("G" & ROW(G23) - $M$4/2) + INDIRECT("G" & ROW(G23) + $M$4/2))/2) / $M$4} -> 30244.091 | J23: =Table3[[#This Row],[Moving Average on Months]] - 1.96*STDEV(OFFSET(Table3[[#This Row],[Combined Daily order]], -$M$4/2, 0, $M$4+1, 1)) -> 17166.305 | K23: =Table3[[#This Row],[Moving Average on Months]] + 1.96*STDEV(OFFSET(Table3[[#This Row],[Combined Daily order]], -$M$4/2, 0, $M$4+1, 1)) -> 43321.877 | L23: =Table3[[#This Row],[Combined Daily order]] -> 38326 | N23: =$V$46 -> 45729.883 | O23: =$U$46 -> 5411.2257
B24: 45552.473 | C24: =INT(B24) -> 45552 | D24: 12174 | F24: =WORKDAY(F23,-1) -> 45534 | G24: =SUMIF(C:C, F24, D:D) -> 23906 | H24: =ROUNDUP(MONTH(Table3[[#This Row],[Date]])/3, 0) -> 3 | I24: {=(SUM(OFFSET(G24, -$M$4/2+1, 0, $M$4-1, 1)) + (INDIRECT("G" & ROW(G24) - $M$4/2) + INDIRECT("G" & ROW(G24) + $M$4/2))/2) / $M$4} -> 30009.841 | J24: =Table3[[#This Row],[Moving Average on Months]] - 1.96*STDEV(OFFSET(Table3[[#This Row],[Combined Daily order]], -$M$4/2, 0, $M$4+1, 1)) -> 17171.087 | K24: =Table3[[#This Row],[Moving Average on Months]] + 1.96*STDEV(OFFSET(Table3[[#This Row],[Combined Daily order]], -$M$4/2, 0, $M$4+1, 1)) -> 42848.595 | L24: #N/A | N24: =$V$46 -> 45729.883 | O24: =$U$46 -> 5411.2257
B25: 45552.086 | C25: =INT(B25) -> 45552 | D25: 12991 | F25: =WORKDAY(F24,-1) -> 45533 | G25: =SUMIF(C:C, F25, D:D) -> 35106 | H25: =ROUNDUP(MONTH(Table3[[#This Row],[Date]])/3, 0) -> 3 | I25: {=(SUM(OFFSET(G25, -$M$4/2+1, 0, $M$4-1, 1)) + (INDIRECT("G" & ROW(G25) - $M$4/2) + INDIRECT("G" & ROW(G25) + $M$4/2))/2) / $M$4} -> 29833.114 | J25: =Table3[[#This Row],[Moving Average on Months]] - 1.96*STDEV(OFFSET(Table3[[#This Row],[Combined Daily order]], -$M$4/2, 0, $M$4+1, 1)) -> 16594.682 | K25: =Table3[[#This Row],[Moving Average on Months]] + 1.96*STDEV(OFFSET(Table3[[#This Row],[Combined Daily order]], -$M$4/2, 0, $M$4+1, 1)) -> 43071.545 | L25: #N/A | N25: =$V$46 -> 45729.883 | O25: =$U$46 -> 5411.2257
B26: 45551.666 | C26: =INT(B26) -> 45551 | D26: 13471 | F26: =WORKDAY(F25,-1) -> 45532 | G26: =SUMIF(C:C, F26, D:D) -> 22341 | H26: =ROUNDUP(MONTH(Table3[[#This Row],[Date]])/3, 0) -> 3 | I26: {=(SUM(OFFSET(G26, -$M$4/2+1, 0, $M$4-1, 1)) + (INDIRECT("G" & ROW(G26) - $M$4/2) + INDIRECT("G" & ROW(G26) + $M$4/2))/2) / $M$4} -> 29676.523 | J26: =Table3[[#This Row],[Moving Average on Months]] - 1.96*STDEV(OFFSET(Table3[[#This Row],[Combined Daily order]], -$M$4/2, 0, $M$4+1, 1)) -> 16614.859 | K26: =Table3[[#This Row],[Moving Average on Months]] + 1.96*STDEV(OFFSET(Table3[[#This Row],[Combined Daily order]], -$M$4/2, 0, $M$4+1, 1)) -> 42738.186 | L26: #N/A | N26: =$V$46 -> 45729.883 | O26: =$U$46 -> 5411.2257
B27: 45551.29 | C27: =INT(B27) -> 45551 | D27: 13830 | F27: =WORKDAY(F26,-1) -> 45531 | G27: =SUMIF(C:C, F27, D:D) -> 36157 | H27: =ROUNDUP(MONTH(Table3[[#This Row],[Date]])/3, 0) -> 3 | I27: {=(SUM(OFFSET(G27, -$M$4/2+1, 0, $M$4-1, 1)) + (INDIRECT("G" & ROW(G27) - $M$4/2) + INDIRECT("G" & ROW(G27) + $M$4/2))/2) / $M$4} -> 29394.318 | J27: =Table3[[#This Row],[Moving Average on Months]] - 1.96*STDEV(OFFSET(Table3[[#This Row],[Combined Daily order]], -$M$4/2, 0, $M$4+1, 1)) -> 15853.399 | K27: =Table3[[#This Row],[Moving Average on Months]] + 1.96*STDEV(OFFSET(Table3[[#This Row],[Combined Daily order]], -$M$4/2, 0, $M$4+1, 1)) -> 42935.237 | L27: =Table3[[#This Row],[Combined Daily order]] -> 36157 | N27: =$V$46 -> 45729.883 | O27: =$U$46 -> 5411.2257
B28: 45548.815 | C28: =INT(B28) -> 45548 | D28: 11982 | F28: =WORKDAY(F27,-1) -> 45530 | G28: =SUMIF(C:C, F28, D:D) -> 24171 | H28: =ROUNDUP(MONTH(Table3[[#This Row],[Date]])/3, 0) -> 3 | I28: {=(SUM(OFFSET(G28, -$M$4/2+1, 0, $M$4-1, 1)) + (INDIRECT("G" & ROW(G28) - $M$4/2) + INDIRECT("G" & ROW(G28) + $M$4/2))/2) / $M$4} -> 29161.795 | J28: =Table3[[#This Row],[Moving Average on Months]] - 1.96*STDEV(OFFSET(Table3[[#This Row],[Combined Daily order]], -$M$4/2, 0, $M$4+1, 1)) -> 16155.034 | K28: =Table3[[#This Row],[Moving Average on Months]] + 1.96*STDEV(OFFSET(Table3[[#This Row],[Combined Daily order]], -$M$4/2, 0, $M$4+1, 1)) -> 42168.557 | L28: #N/A | N28: =$V$46 -> 45729.883 | O28: =$U$46 -> 5411.2257
B29: 45548.404 | C29: =INT(B29) -> 45548 | D29: 11995 | F29: =WORKDAY(F28,-1) -> 45527 | G29: =SUMIF(C:C, F29, D:D) -> 33437 | H29: =ROUNDUP(MONTH(Table3[[#This Row],[Date]])/3, 0) -> 3 | I29: {=(SUM(OFFSET(G29, -$M$4/2+1, 0, $M$4-1, 1)) + (INDIRECT("G" & ROW(G29) - $M$4/2) + INDIRECT("G" & ROW(G29) + $M$4/2))/2) / $M$4} -> 29454.023 | J29: =Table3[[#This Row],[Moving Average on Months]] - 1.96*STDEV(OFFSET(Table3[[#This Row],[Combined Daily order]], -$M$4/2, 0, $M$4+1, 1)) -> 16605.449 | K29: =Table3[[#This Row],[Moving Average on Months]] + 1.96*STDEV(OFFSET(Table3[[#This Row],[Combined Daily order]], -$M$4/2, 0, $M$4+1, 1)) -> 42302.597 | L29: #N/A | N29: =$V$46 -> 45729.883 | O29: =$U$46 -> 5411.2257
B30: 45548.029 | C30: =INT(B30) -> 45548 | D30: 11343 | F30: =WORKDAY(F29,-1) -> 45526 | G30: =SUMIF(C:C, F30, D:D) -> 24428 | H30: =ROUNDUP(MONTH(Table3[[#This Row],[Date]])/3, 0) -> 3 | I30: {=(SUM(OFFSET(G30, -$M$4/2+1, 0, $M$4-1, 1)) + (INDIRECT("G" & ROW(G30) - $M$4/2) + INDIRECT("G" & ROW(G30) + $M$4/2))/2) / $M$4} -> 29023.841 | J30: =Table3[[#This Row],[Moving Average on Months]] - 1.96*STDEV(OFFSET(Table3[[#This Row],[Combined Daily order]], -$M$4/2, 0, $M$4+1, 1)) -> 15552.505 | K30: =Table3[[#This Row],[Moving Average on Months]] + 1.96*STDEV(OFFSET(Table3[[#This Row],[Combined Daily order]], -$M$4/2, 0, $M$4+1, 1)) -> 42495.177 | L30: #N/A | N30: =$V$46 -> 45729.883 | O30: =$U$46 -> 5411.2257
B31: 45547.613 | C31: =INT(B31) -> 45547 | D31: 11358 | F31: =WORKDAY(F30,-1) -> 45525 | G31: =SUMIF(C:C, F31, D:D) -> 34087 | H31: =ROUNDUP(MONTH(Table3[[#This Row],[Date]])/3, 0) -> 3 | I31: {=(SUM(OFFSET(G31, -$M$4/2+1, 0, $M$4-1, 1)) + (INDIRECT("G" & ROW(G31) - $M$4/2) + INDIRECT("G" & ROW(G31) + $M$4/2))/2) / $M$4} -> 28594.318 | J31: =Table3[[#This Row],[Moving Average on Months]] - 1.96*STDEV(OFFSET(Table3[[#This Row],[Combined Daily order]], -$M$4/2, 0, $M$4+1, 1)) -> 16334.784 | K31: =Table3[[#This Row],[Moving Average on Months]] + 1.96*STDEV(OFFSET(Table3[[#This Row],[Combined Daily order]], -$M$4/2, 0, $M$4+1, 1)) -> 40853.853 | L31: #N/A | N31: =$V$46 -> 45729.883 | O31: =$U$46 -> 5411.2257
B32: 45547.189 | C32: =INT(B32) -> 45547 | D32: 13882 | F32: =WORKDAY(F31,-1) -> 45524 | G32: =SUMIF(C:C, F32, D:D) -> 23986 | H32: =ROUNDUP(MONTH(Table3[[#This Row],[Date]])/3, 0) -> 3 | I32: {=(SUM(OFFSET(G32, -$M$4/2+1, 0, $M$4-1, 1)) + (INDIRECT("G" & ROW(G32) - $M$4/2) + INDIRECT("G" & ROW(G32) + $M$4/2))/2) / $M$4} -> 28238.023 | J32: =Table3[[#This Row],[Moving Average on Months]] - 1.96*STDEV(OFFSET(Table3[[#This Row],[Combined Daily order]], -$M$4/2, 0, $M$4+1, 1)) -> 15590.131 | K32: =Table3[[#This Row],[Moving Average on Months]] + 1.96*STDEV(OFFSET(Table3[[#This Row],[Combined Daily order]], -$M$4/2, 0, $M$4+1, 1)) -> 40885.914 | L32: #N/A | N32: =$V$46 -> 45729.883 | O32: =$U$46 -> 5411.2257
B33: 45546.774 | C33: =INT(B33) -> 45546 | D33: 14222 | F33: =WORKDAY(F32,-1) -> 45523 | G33: =SUMIF(C:C, F33, D:D) -> 32081 | H33: =ROUNDUP(MONTH(Table3[[#This Row],[Date]])/3, 0) -> 3 | I33: {=(SUM(OFFSET(G33, -$M$4/2+1, 0, $M$4-1, 1)) + (INDIRECT("G" & ROW(G33) - $M$4/2) + INDIRECT("G" & ROW(G33) + $M$4/2))/2) / $M$4} -> 27643.091 | J33: =Table3[[#This Row],[Moving Average on Months]] - 1.96*STDEV(OFFSET(Table3[[#This Row],[Combined Daily order]], -$M$4/2, 0, $M$4+1, 1)) -> 15320.659 | K33: =Table3[[#This Row],[Moving Average on Months]] + 1.96*STDEV(OFFSET(Table3[[#This Row],[Combined Daily order]], -$M$4/2, 0, $M$4+1, 1)) -> 39965.522 | L33: #N/A | N33: =$V$46 -> 45729.883 | O33: =$U$46 -> 5411.2257
B34: 45546.379 | C34: =INT(B34) -> 45546 | D34: 12161 | F34: =WORKDAY(F33,-1) -> 45520 | G34: =SUMIF(C:C, F34, D:D) -> 20663 | H34: =ROUNDUP(MONTH(Table3[[#This Row],[Date]])/3, 0) -> 3 | I34: {=(SUM(OFFSET(G34, -$M$4/2+1, 0, $M$4-1, 1)) + (INDIRECT("G" & ROW(G34) - $M$4/2) + INDIRECT("G" & ROW(G34) + $M$4/2))/2) / $M$4} -> 27235.591 | J34: =Table3[[#This Row],[Moving Average on Months]] - 1.96*STDEV(OFFSET(Table3[[#This Row],[Combined Daily order]], -$M$4/2, 0, $M$4+1, 1)) -> 14959.73 | K34: =Table3[[#This Row],[Moving Average on Months]] + 1.96*STDEV(OFFSET(Table3[[#This Row],[Combined Daily order]], -$M$4/2, 0, $M$4+1, 1)) -> 39511.451 | L34: #N/A | N34: =$V$46 -> 45729.883 | O34: =$U$46 -> 5411.2257
B35: 45546.002 | C35: =INT(B35) -> 45546 | D35: 12677 | F35: =WORKDAY(F34,-1) -> 45519 | G35: =SUMIF(C:C, F35, D:D) -> 33098 | H35: =ROUNDUP(MONTH(Table3[[#This Row],[Date]])/3, 0) -> 3 | I35: {=(SUM(OFFSET(G35, -$M$4/2+1, 0, $M$4-1, 1)) + (INDIRECT("G" & ROW(G35) - $M$4/2) + INDIRECT("G" & ROW(G35) + $M$4/2))/2) / $M$4} -> 26853.682 | J35: =Table3[[#This Row],[Moving Average on Months]] - 1.96*STDEV(OFFSET(Table3[[#This Row],[Combined Daily order]], -$M$4/2, 0, $M$4+1, 1)) -> 14977.885 | K35: =Table3[[#This Row],[Moving Average on Months]] + 1.96*STDEV(OFFSET(Table3[[#This Row],[Combined Daily order]], -$M$4/2, 0, $M$4+1, 1)) -> 38729.479 | L35: #N/A | N35: =$V$46 -> 45729.883 | O35: =$U$46 -> 5411.2257
B36: 45545.6 | C36: =INT(B36) -> 45545 | D36: 13017 | F36: =WORKDAY(F35,-1) -> 45518 | G36: =SUMIF(C:C, F36, D:D) -> 21747 | H36: =ROUNDUP(MONTH(Table3[[#This Row],[Date]])/3, 0) -> 3 | I36: {=(SUM(OFFSET(G36, -$M$4/2+1, 0, $M$4-1, 1)) + (INDIRECT("G" & ROW(G36) - $M$4/2) + INDIRECT("G" & ROW(G36) + $M$4/2))/2) / $M$4} -> 26554.545 | J36: =Table3[[#This Row],[Moving Average on Months]] - 1.96*STDEV(OFFSET(Table3[[#This Row],[Combined Daily order]], -$M$4/2, 0, $M$4+1, 1)) -> 14732.761 | K36: =Table3[[#This Row],[Moving Average on Months]] + 1.96*STDEV(OFFSET(Table3[[#This Row],[Combined Daily order]], -$M$4/2, 0, $M$4+1, 1)) -> 38376.33 | L36: #N/A | N36: =$V$46 -> 45729.883 | O36: =$U$46 -> 5411.2257
B37: 45545.196 | C37: =INT(B37) -> 45545 | D37: 11210 | F37: =WORKDAY(F36,-1) -> 45517 | G37: =SUMIF(C:C, F37, D:D) -> 31923 | H37: =ROUNDUP(MONTH(Table3[[#This Row],[Date]])/3, 0) -> 3 | I37: {=(SUM(OFFSET(G37, -$M$4/2+1, 0, $M$4-1, 1)) + (INDIRECT("G" & ROW(G37) - $M$4/2) + INDIRECT("G" & ROW(G37) + $M$4/2))/2) / $M$4} -> 26246.864 | J37: =Table3[[#This Row],[Moving Average on Months]] - 1.96*STDEV(OFFSET(Table3[[#This Row],[Combined Daily order]], -$M$4/2, 0, $M$4+1, 1)) -> 14290.05 | K37: =Table3[[#This Row],[Moving Average on Months]] + 1.96*STDEV(OFFSET(Table3[[#This Row],[Combined Daily order]], -$M$4/2, 0, $M$4+1, 1)) -> 38203.677 | L37: #N/A | N37: =$V$46 -> 45729.883 | O37: =$U$46 -> 5411.2257
B38: 45544.797 | C38: =INT(B38) -> 45544 | D38: 13133 | F38: =WORKDAY(F37,-1) -> 45516 | G38: =SUMIF(C:C, F38, D:D) -> 19960 | H38: =ROUNDUP(MONTH(Table3[[#This Row],[Date]])/3, 0) -> 3 | I38: {=(SUM(OFFSET(G38, -$M$4/2+1, 0, $M$4-1, 1)) + (INDIRECT("G" & ROW(G38) - $M$4/2) + INDIRECT("G" & ROW(G38) + $M$4/2))/2) / $M$4} -> 25870.068 | J38: =Table3[[#This Row],[Moving Average on Months]] - 1.96*STDEV(OFFSET(Table3[[#This Row],[Combined Daily order]], -$M$4/2, 0, $M$4+1, 1)) -> 14008.656 | K38: =Table3[[#This Row],[Moving Average on Months]] + 1.96*STDEV(OFFSET(Table3[[#This Row],[Combined Daily order]], -$M$4/2, 0, $M$4+1, 1)) -> 37731.48 | L38: #N/A | N38: =$V$46 -> 45729.883 | O38: =$U$46 -> 5411.2257
B39: 45544.421 | C39: =INT(B39) -> 45544 | D39: 13618 | F39: =WORKDAY(F38,-1) -> 45513 | G39: =SUMIF(C:C, F39, D:D) -> 33096 | H39: =ROUNDUP(MONTH(Table3[[#This Row],[Date]])/3, 0) -> 3 | I39: {=(SUM(OFFSET(G39, -$M$4/2+1, 0, $M$4-1, 1)) + (INDIRECT("G" & ROW(G39) - $M$4/2) + INDIRECT("G" & ROW(G39) + $M$4/2))/2) / $M$4} -> 25463.114 | J39: =Table3[[#This Row],[Moving Average on Months]] - 1.96*STDEV(OFFSET(Table3[[#This Row],[Combined Daily order]], -$M$4/2, 0, $M$4+1, 1)) -> 13875.993 | K39: =Table3[[#This Row],[Moving Average on Months]] + 1.96*STDEV(OFFSET(Table3[[#This Row],[Combined Daily order]], -$M$4/2, 0, $M$4+1, 1)) -> 37050.235 | L39: #N/A | N39: =$V$46 -> 45729.883 | O39: =$U$46 -> 5411.2257
... B42: 45541.132 | C42: =INT(B42) -> 45541 | D42: 11090 | F42: =WORKDAY(F41,-1) -> 45510 | G42: =SUMIF(C:C, F42, D:D) -> 28224 | H42: =ROUNDUP(MONTH(Table3[[#This Row],[Date]])/3, 0) -> 3 | I42: {=(SUM(OFFSET(G42, -$M$4/2+1, 0, $M$4-1, 1)) + (INDIRECT("G" & ROW(G42) - $M$4/2) + INDIRECT("G" & ROW(G42) + $M$4/2))/2) / $M$4} -> 24149.773 | J42: =Table3[[#This Row],[Moving Average on Months]] - 1.96*STDEV(OFFSET(Table3[[#This Row],[Combined Daily order]], -$M$4/2, 0, $M$4+1, 1)) -> 12362.005 | K42: =Table3[[#This Row],[Moving Average on Months]] + 1.96*STDEV(OFFSET(Table3[[#This Row],[Combined Daily order]], -$M$4/2, 0, $M$4+1, 1)) -> 35937.541 | L42: #N/A | N42: =$V$46 -> 45729.883 | O42: =$U$46 -> 5411.2257
B43: 45540.747 | C43: =INT(B43) -> 45540 | D43: 12739 | F43: =WORKDAY(F42,-1) -> 45509 | G43: =SUMIF(C:C, F43, D:D) -> 19855 | H43: =ROUNDUP(MONTH(Table3[[#This Row],[Date]])/3, 0) -> 3 | I43: {=(SUM(OFFSET(G43, -$M$4/2+1, 0, $M$4-1, 1)) + (INDIRECT("G" & ROW(G43) - $M$4/2) + INDIRECT("G" & ROW(G43) + $M$4/2))/2) / $M$4} -> 23651.409 | J43: =Table3[[#This Row],[Moving Average on Months]] - 1.96*STDEV(OFFSET(Table3[[#This Row],[Combined Daily order]], -$M$4/2, 0, $M$4+1, 1)) -> 11903.073 | K43: =Table3[[#This Row],[Moving Average on Months]] + 1.96*STDEV(OFFSET(Table3[[#This Row],[Combined Daily order]], -$M$4/2, 0, $M$4+1, 1)) -> 35399.745 | L43: #N/A | N43: =$V$46 -> 45729.883 | O43: =$U$46 -> 5411.2257 | Q43: Confidence Interval computed on the whole series of data
B44: 45540.348 | C44: =INT(B44) -> 45540 | D44: 11467 | F44: =WORKDAY(F43,-1) -> 45506 | G44: =SUMIF(C:C, F44, D:D) -> 18323 | H44: =ROUNDUP(MONTH(Table3[[#This Row],[Date]])/3, 0) -> 3 | I44: {=(SUM(OFFSET(G44, -$M$4/2+1, 0, $M$4-1, 1)) + (INDIRECT("G" & ROW(G44) - $M$4/2) + INDIRECT("G" & ROW(G44) + $M$4/2))/2) / $M$4} -> 23193.068 | J44: =Table3[[#This Row],[Moving Average on Months]] - 1.96*STDEV(OFFSET(Table3[[#This Row],[Combined Daily order]], -$M$4/2, 0, $M$4+1, 1)) -> 11431.603 | K44: =Table3[[#This Row],[Moving Average on Months]] + 1.96*STDEV(OFFSET(Table3[[#This Row],[Combined Daily order]], -$M$4/2, 0, $M$4+1, 1)) -> 34954.533 | L44: #N/A | N44: =$V$46 -> 45729.883 | O44: =$U$46 -> 5411.2257
B45: 45539.922 | C45: =INT(B45) -> 45539 | D45: 12283 | F45: =WORKDAY(F44,-1) -> 45505 | G45: =SUMIF(C:C, F45, D:D) -> 26878 | H45: =ROUNDUP(MONTH(Table3[[#This Row],[Date]])/3, 0) -> 3 | I45: {=(SUM(OFFSET(G45, -$M$4/2+1, 0, $M$4-1, 1)) + (INDIRECT("G" & ROW(G45) - $M$4/2) + INDIRECT("G" & ROW(G45) + $M$4/2))/2) / $M$4} -> 22821.841 | J45: =Table3[[#This Row],[Moving Average on Months]] - 1.96*STDEV(OFFSET(Table3[[#This Row],[Combined Daily order]], -$M$4/2, 0, $M$4+1, 1)) -> 11137.369 | K45: =Table3[[#This Row],[Moving Average on Months]] + 1.96*STDEV(OFFSET(Table3[[#This Row],[Combined Daily order]], -$M$4/2, 0, $M$4+1, 1)) -> 34506.313 | L45: #N/A | N45: =$V$46 -> 45729.883 | O45: =$U$46 -> 5411.2257 | Q45: Average | R45: Standard Deviation | S45: Confidence Level | T45: Z-Score | U45: CI1 | V45: CI2
B46: 45539.549 | C46: =INT(B46) -> 45539 | D46: 13922 | F46: =WORKDAY(F45,-1) -> 45504 | G46: =SUMIF(C:C, F46, D:D) -> 18550 | H46: =ROUNDUP(MONTH(Table3[[#This Row],[Date]])/3, 0) -> 3 | I46: {=(SUM(OFFSET(G46, -$M$4/2+1, 0, $M$4-1, 1)) + (INDIRECT("G" & ROW(G46) - $M$4/2) + INDIRECT("G" & ROW(G46) + $M$4/2))/2) / $M$4} -> 22398.886 | J46: =Table3[[#This Row],[Moving Average on Months]] - 1.96*STDEV(OFFSET(Table3[[#This Row],[Combined Daily order]], -$M$4/2, 0, $M$4+1, 1)) -> 10715.273 | K46: =Table3[[#This Row],[Moving Average on Months]] + 1.96*STDEV(OFFSET(Table3[[#This Row],[Combined Daily order]], -$M$4/2, 0, $M$4+1, 1)) -> 34082.499 | L46: #N/A | N46: =$V$46 -> 45729.883 | O46: =$U$46 -> 5411.2257 | Q46: =AVERAGE(G4:G806) -> 25570.554 | R46: =STDEV(G4:G806) -> 10285.372 | S46: 0.95 | T46: 1.96 | U46: =Q46 - T46*R46 -> 5411.2257 | V46: =Q46 + T46*R46 -> 45729.883
B47: 45539.127 | C47: =INT(B47) -> 45539 | D47: 13345 | F47: =WORKDAY(F46,-1) -> 45503 | G47: =SUMIF(C:C, F47, D:D) -> 27300 | H47: =ROUNDUP(MONTH(Table3[[#This Row],[Date]])/3, 0) -> 3 | I47: {=(SUM(OFFSET(G47, -$M$4/2+1, 0, $M$4-1, 1)) + (INDIRECT("G" & ROW(G47) - $M$4/2) + INDIRECT("G" & ROW(G47) + $M$4/2))/2) / $M$4} -> 21925.773 | J47: =Table3[[#This Row],[Moving Average on Months]] - 1.96*STDEV(OFFSET(Table3[[#This Row],[Combined Daily order]], -$M$4/2, 0, $M$4+1, 1)) -> 10557.054 | K47: =Table3[[#This Row],[Moving Average on Months]] + 1.96*STDEV(OFFSET(Table3[[#This Row],[Combined Daily order]], -$M$4/2, 0, $M$4+1, 1)) -> 33294.491 | L47: #N/A | N47: =$V$46 -> 45729.883 | O47: =$U$46 -> 5411.2257
B48: 45538.737 | C48: =INT(B48) -> 45538 | D48: 11564 | F48: =WORKDAY(F47,-1) -> 45502 | G48: =SUMIF(C:C, F48, D:D) -> 16609 | H48: =ROUNDUP(MONTH(Table3[[#This Row],[Date]])/3, 0) -> 3 | I48: {=(SUM(OFFSET(G48, -$M$4/2+1, 0, $M$4-1, 1)) + (INDIRECT("G" & ROW(G48) - $M$4/2) + INDIRECT("G" & ROW(G48) + $M$4/2))/2) / $M$4} -> 21481.25 | J48: =Table3[[#This Row],[Moving Average on Months]] - 1.96*STDEV(OFFSET(Table3[[#This Row],[Combined Daily order]], -$M$4/2, 0, $M$4+1, 1)) -> 10105.785 | K48: =Table3[[#This Row],[Moving Average on Months]] + 1.96*STDEV(OFFSET(Table3[[#This Row],[Combined Daily order]], -$M$4/2, 0, $M$4+1, 1)) -> 32856.715 | L48: #N/A | N48: =$V$46 -> 45729.883 | O48: =$U$46 -> 5411.2257
B49: 45538.317 | C49: =INT(B49) -> 45538 | D49: 13241 | F49: =WORKDAY(F48,-1) -> 45499 | G49: =SUMIF(C:C, F49, D:D) -> 25310 | H49: =ROUNDUP(MONTH(Table3[[#This Row],[Date]])/3, 0) -> 3 | I49: {=(SUM(OFFSET(G49, -$M$4/2+1, 0, $M$4-1, 1)) + (INDIRECT("G" & ROW(G49) - $M$4/2) + INDIRECT("G" & ROW(G49) + $M$4/2))/2) / $M$4} -> 21115.295 | J49: =Table3[[#This Row],[Moving Average on Months]] - 1.96*STDEV(OFFSET(Table3[[#This Row],[Combined Daily order]], -$M$4/2, 0, $M$4+1, 1)) -> 10309.558 | K49: =Table3[[#This Row],[Moving Average on Months]] + 1.96*STDEV(OFFSET(Table3[[#This Row],[Combined Daily order]], -$M$4/2, 0, $M$4+1, 1)) -> 31921.032 | L49: #N/A | N49: =$V$46 -> 45729.883 | O49: =$U$46 -> 5411.2257
B50: 45537.888 | C50: =INT(B50) -> 45537 | D50: 10788 | F50: =WORKDAY(F49,-1) -> 45498 | G50: =SUMIF(C:C, F50, D:D) -> 17112 | H50: =ROUNDUP(MONTH(Table3[[#This Row],[Date]])/3, 0) -> 3 | I50: {=(SUM(OFFSET(G50, -$M$4/2+1, 0, $M$4-1, 1)) + (INDIRECT("G" & ROW(G50) - $M$4/2) + INDIRECT("G" & ROW(G50) + $M$4/2))/2) / $M$4} -> 20749.205 | J50: =Table3[[#This Row],[Moving Average on Months]] - 1.96*STDEV(OFFSET(Table3[[#This Row],[Combined Daily order]], -$M$4/2, 0, $M$4+1, 1)) -> 9945.0364 | K50: =Table3[[#This Row],[Moving Average on Months]] + 1.96*STDEV(OFFSET(Table3[[#This Row],[Combined Daily order]], -$M$4/2, 0, $M$4+1, 1)) -> 31553.373 | L50: #N/A | N50: =$V$46 -> 45729.883 | O50: =$U$46 -> 5411.2257
B51: 45537.51 | C51: =INT(B51) -> 45537 | D51: 13885 | F51: =WORKDAY(F50,-1) -> 45497 | G51: =SUMIF(C:C, F51, D:D) -> 23316 | H51: =ROUNDUP(MONTH(Table3[[#This Row],[Date]])/3, 0) -> 3 | I51: {=(SUM(OFFSET(G51, -$M$4/2+1, 0, $M$4-1, 1)) + (INDIRECT("G" & ROW(G51) - $M$4/2) + INDIRECT("G" & ROW(G51) + $M$4/2))/2) / $M$4} -> 20127.068 | J51: =Table3[[#This Row],[Moving Average on Months]] - 1.96*STDEV(OFFSET(Table3[[#This Row],[Combined Daily order]], -$M$4/2, 0, $M$4+1, 1)) -> 10320.019 | K51: =Table3[[#This Row],[Moving Average on Months]] + 1.96*STDEV(OFFSET(Table3[[#This Row],[Combined Daily order]], -$M$4/2, 0, $M$4+1, 1)) -> 29934.118 | L51: #N/A | N51: =$V$46 -> 45729.883 | O51: =$U$46 -> 5411.2257 | Q51: Confidence Interval computed on each year
B52: 45537.139 | C52: =INT(B52) -> 45537 | D52: 13653 | F52: =WORKDAY(F51,-1) -> 45496 | G52: =SUMIF(C:C, F52, D:D) -> 15130 | H52: =ROUNDUP(MONTH(Table3[[#This Row],[Date]])/3, 0) -> 3 | I52: {=(SUM(OFFSET(G52, -$M$4/2+1, 0, $M$4-1, 1)) + (INDIRECT("G" & ROW(G52) - $M$4/2) + INDIRECT("G" & ROW(G52) + $M$4/2))/2) / $M$4} -> 19807.591 | J52: =Table3[[#This Row],[Moving Average on Months]] - 1.96*STDEV(OFFSET(Table3[[#This Row],[Combined Daily order]], -$M$4/2, 0, $M$4+1, 1)) -> 11061.473 | K52: =Table3[[#This Row],[Moving Average on Months]] + 1.96*STDEV(OFFSET(Table3[[#This Row],[Combined Daily order]], -$M$4/2, 0, $M$4+1, 1)) -> 28553.709 | L52: #N/A | N52: =$V$46 -> 45729.883 | O52: =$U$46 -> 5411.2257
B53: 45534.823 | C53: =INT(B53) -> 45534 | D53: 12492 | F53: =WORKDAY(F52,-1) -> 45495 | G53: =SUMIF(C:C, F53, D:D) -> 22197 | H53: =ROUNDUP(MONTH(Table3[[#This Row],[Date]])/3, 0) -> 3 | I53: {=(SUM(OFFSET(G53, -$M$4/2+1, 0, $M$4-1, 1)) + (INDIRECT("G" & ROW(G53) - $M$4/2) + INDIRECT("G" & ROW(G53) + $M$4/2))/2) / $M$4} -> 19533.273 | J53: =Table3[[#This Row],[Moving Average on Months]] - 1.96*STDEV(OFFSET(Table3[[#This Row],[Combined Daily order]], -$M$4/2, 0, $M$4+1, 1)) -> 10467.824 | K53: =Table3[[#This Row],[Moving Average on Months]] + 1.96*STDEV(OFFSET(Table3[[#This Row],[Combined Daily order]], -$M$4/2, 0, $M$4+1, 1)) -> 28598.722 | L53: #N/A | N53: =$V$46 -> 45729.883 | O53: =$U$46 -> 5411.2257 | Q53: Year 2021 | S53: Year 2022 | U53: Year 2023 | W53: Year 2024
B54: 45534.422 | C54: =INT(B54) -> 45534 | D54: 11414 | F54: =WORKDAY(F53,-1) -> 45492 | G54: =SUMIF(C:C, F54, D:D) -> 13948 | H54: =ROUNDUP(MONTH(Table3[[#This Row],[Date]])/3, 0) -> 3 | I54: {=(SUM(OFFSET(G54, -$M$4/2+1, 0, $M$4-1, 1)) + (INDIRECT("G" & ROW(G54) - $M$4/2) + INDIRECT("G" & ROW(G54) + $M$4/2))/2) / $M$4} -> 19277.682 | J54: =Table3[[#This Row],[Moving Average on Months]] - 1.96*STDEV(OFFSET(Table3[[#This Row],[Combined Daily order]], -$M$4/2, 0, $M$4+1, 1)) -> 10862.503 | K54: =Table3[[#This Row],[Moving Average on Months]] + 1.96*STDEV(OFFSET(Table3[[#This Row],[Combined Daily order]], -$M$4/2, 0, $M$4+1, 1)) -> 27692.861 | L54: #N/A | N54: =$V$46 -> 45729.883 | O54: =$U$46 -> 5411.2257 | Q54: IC1 | R54: IC2 | S54: IC1 | T54: IC2 | U54: IC1 | V54: IC2 | W54: IC1 | X54: IC2
B55: 45533.998 | C55: =INT(B55) -> 45533 | D55: 10435 | F55: =WORKDAY(F54,-1) -> 45491 | G55: =SUMIF(C:C, F55, D:D) -> 21952 | H55: =ROUNDUP(MONTH(Table3[[#This Row],[Date]])/3, 0) -> 3 | I55: {=(SUM(OFFSET(G55, -$M$4/2+1, 0, $M$4-1, 1)) + (INDIRECT("G" & ROW(G55) - $M$4/2) + INDIRECT("G" & ROW(G55) + $M$4/2))/2) / $M$4} -> 19290.545 | J55: =Table3[[#This Row],[Moving Average on Months]] - 1.96*STDEV(OFFSET(Table3[[#This Row],[Combined Daily order]], -$M$4/2, 0, $M$4+1, 1)) -> 10760.968 | K55: =Table3[[#This Row],[Moving Average on Months]] + 1.96*STDEV(OFFSET(Table3[[#This Row],[Combined Daily order]], -$M$4/2, 0, $M$4+1, 1)) -> 27820.123 | L55: #N/A | N55: =$V$46 -> 45729.883 | O55: =$U$46 -> 5411.2257 | Q55: =AVERAGE(G719:G806) - T46*STDEV(G719:G806) -> 10960.024 | R55: =AVERAGE(G719:G806) + T46*STDEV(G719:G806) -> 55660.544 | S55: =AVERAGE(G459:G718) - T46*STDEV(G459:G718) -> 4875.834 | T55: =AVERAGE(G459:G718) + T46*STDEV(G459:G718) -> 41714.966 | U55: =AVERAGE(G199:G458) - T46*STDEV(G199:G458) -> 3648.1793 | V55: =AVERAGE(G199:G458) + T46*STDEV(G199:G458) -> 49524.498 | W55: =AVERAGE(G4:G198) - T46*STDEV(G4:G198) -> 11444.933 | X55: =AVERAGE(G4:G198) + T46*STDEV(G4:G198) -> 36068.892
B56: 45533.592 | C56: =INT(B56) -> 45533 | D56: 11233 | F56: =WORKDAY(F55,-1) -> 45490 | G56: =SUMIF(C:C, F56, D:D) -> 14458 | H56: =ROUNDUP(MONTH(Table3[[#This Row],[Date]])/3, 0) -> 3 | I56: {=(SUM(OFFSET(G56, -$M$4/2+1, 0, $M$4-1, 1)) + (INDIRECT("G" & ROW(G56) - $M$4/2) + INDIRECT("G" & ROW(G56) + $M$4/2))/2) / $M$4} -> 19139.773 | J56: =Table3[[#This Row],[Moving Average on Months]] - 1.96*STDEV(OFFSET(Table3[[#This Row],[Combined Daily order]], -$M$4/2, 0, $M$4+1, 1)) -> 10503.787 | K56: =Table3[[#This Row],[Moving Average on Months]] + 1.96*STDEV(OFFSET(Table3[[#This Row],[Combined Daily order]], -$M$4/2, 0, $M$4+1, 1)) -> 27775.758 | L56: #N/A | N56: =$V$46 -> 45729.883 | O56: =$U$46 -> 5411.2257
B57: 45533.199 | C57: =INT(B57) -> 45533 | D57: 13438 | F57: =WORKDAY(F56,-1) -> 45489 | G57: =SUMIF(C:C, F57, D:D) -> 20693 | H57: =ROUNDUP(MONTH(Table3[[#This Row],[Date]])/3, 0) -> 3 | I57: {=(SUM(OFFSET(G57, -$M$4/2+1, 0, $M$4-1, 1)) + (INDIRECT("G" & ROW(G57) - $M$4/2) + INDIRECT("G" & ROW(G57) + $M$4/2))/2) / $M$4} -> 19124.841 | J57: =Table3[[#This Row],[Moving Average on Months]] - 1.96*STDEV(OFFSET(Table3[[#This Row],[Combined Daily order]], -$M$4/2, 0, $M$4+1, 1)) -> 11007.289 | K57: =Table3[[#This Row],[Moving Average on Months]] + 1.96*STDEV(OFFSET(Table3[[#This Row],[Combined Daily order]], -$M$4/2, 0, $M$4+1, 1)) -> 27242.393 | L57: #N/A | N57: =$V$46 -> 45729.883 | O57: =$U$46 -> 5411.2257
B58: 45532.778 | C58: =INT(B58) -> 45532 | D58: 11231 | F58: =WORKDAY(F57,-1) -> 45488 | G58: =SUMIF(C:C, F58, D:D) -> 13335 | H58: =ROUNDUP(MONTH(Table3[[#This Row],[Date]])/3, 0) -> 3 | I58: {=(SUM(OFFSET(G58, -$M$4/2+1, 0, $M$4-1, 1)) + (INDIRECT("G" & ROW(G58) - $M$4/2) + INDIRECT("G" & ROW(G58) + $M$4/2))/2) / $M$4} -> 18969.523 | J58: =Table3[[#This Row],[Moving Average on Months]] - 1.96*STDEV(OFFSET(Table3[[#This Row],[Combined Daily order]], -$M$4/2, 0, $M$4+1, 1)) -> 10802.375 | K58: =Table3[[#This Row],[Moving Average on Months]] + 1.96*STDEV(OFFSET(Table3[[#This Row],[Combined Daily order]], -$M$4/2, 0, $M$4+1, 1)) -> 27136.671 | L58: #N/A | N58: =$V$46 -> 45729.883 | O58: =$U$46 -> 5411.2257
B59: 45532.407 | C59: =INT(B59) -> 45532 | D59: 11110 | F59: =WORKDAY(F58,-1) -> 45485 | G59: =SUMIF(C:C, F59, D:D) -> 20776 | H59: =ROUNDUP(MONTH(Table3[[#This Row],[Date]])/3, 0) -> 3 | I59: {=(SUM(OFFSET(G59, -$M$4/2+1, 0, $M$4-1, 1)) + (INDIRECT("G" & ROW(G59) - $M$4/2) + INDIRECT("G" & ROW(G59) + $M$4/2))/2) / $M$4} -> 18897.295 | J59: =Table3[[#This Row],[Moving Average on Months]] - 1.96*STDEV(OFFSET(Table3[[#This Row],[Combined Daily order]], -$M$4/2, 0, $M$4+1, 1)) -> 11231.372 | K59: =Table3[[#This Row],[Moving Average on Months]] + 1.96*STDEV(OFFSET(Table3[[#This Row],[Combined Daily order]], -$M$4/2, 0, $M$4+1, 1)) -> 26563.219 | L59: #N/A | N59: =$V$46 -> 45729.883 | O59: =$U$46 -> 5411.2257 | R59: Confidence Interval computed on each quarter of each year
B60: 45531.993 | C60: =INT(B60) -> 45531 | D60: 12450 | F60: =WORKDAY(F59,-1) -> 45484 | G60: =SUMIF(C:C, F60, D:D) -> 15005 | H60: =ROUNDUP(MONTH(Table3[[#This Row],[Date]])/3, 0) -> 3 | I60: {=(SUM(OFFSET(G60, -$M$4/2+1, 0, $M$4-1, 1)) + (INDIRECT("G" & ROW(G60) - $M$4/2) + INDIRECT("G" & ROW(G60) + $M$4/2))/2) / $M$4} -> 18873.159 | J60: =Table3[[#This Row],[Moving Average on Months]] - 1.96*STDEV(OFFSET(Table3[[#This Row],[Combined Daily order]], -$M$4/2, 0, $M$4+1, 1)) -> 11228.136 | K60: =Table3[[#This Row],[Moving Average on Months]] + 1.96*STDEV(OFFSET(Table3[[#This Row],[Combined Daily order]], -$M$4/2, 0, $M$4+1, 1)) -> 26518.182 | L60: #N/A | N60: =$V$46 -> 45729.883 | O60: =$U$46 -> 5411.2257
B61: 45531.567 | C61: =INT(B61) -> 45531 | D61: 11731 | F61: =WORKDAY(F60,-1) -> 45483 | G61: =SUMIF(C:C, F61, D:D) -> 21943 | H61: =ROUNDUP(MONTH(Table3[[#This Row],[Date]])/3, 0) -> 3 | I61: {=(SUM(OFFSET(G61, -$M$4/2+1, 0, $M$4-1, 1)) + (INDIRECT("G" & ROW(G61) - $M$4/2) + INDIRECT("G" & ROW(G61) + $M$4/2))/2) / $M$4} -> 18843.341 | J61: =Table3[[#This Row],[Moving Average on Months]] - 1.96*STDEV(OFFSET(Table3[[#This Row],[Combined Daily order]], -$M$4/2, 0, $M$4+1, 1)) -> 11362.404 | K61: =Table3[[#This Row],[Moving Average on Months]] + 1.96*STDEV(OFFSET(Table3[[#This Row],[Combined Daily order]], -$M$4/2, 0, $M$4+1, 1)) -> 26324.278 | L61: #N/A | N61: =$V$46 -> 45729.883 | O61: =$U$46 -> 5411.2257 | R61: Year 2021 | T61: Year 2022 | V61: Year 2023 | X61: Year 2024
B62: 45531.154 | C62: =INT(B62) -> 45531 | D62: 11976 | F62: =WORKDAY(F61,-1) -> 45482 | G62: =SUMIF(C:C, F62, D:D) -> 14519 | H62: =ROUNDUP(MONTH(Table3[[#This Row],[Date]])/3, 0) -> 3 | I62: {=(SUM(OFFSET(G62, -$M$4/2+1, 0, $M$4-1, 1)) + (INDIRECT("G" & ROW(G62) - $M$4/2) + INDIRECT("G" & ROW(G62) + $M$4/2))/2) / $M$4} -> 18875.705 | J62: =Table3[[#This Row],[Moving Average on Months]] - 1.96*STDEV(OFFSET(Table3[[#This Row],[Combined Daily order]], -$M$4/2, 0, $M$4+1, 1)) -> 11417.976 | K62: =Table3[[#This Row],[Moving Average on Months]] + 1.96*STDEV(OFFSET(Table3[[#This Row],[Combined Daily order]], -$M$4/2, 0, $M$4+1, 1)) -> 26333.433 | L62: #N/A | N62: =$V$46 -> 45729.883 | O62: =$U$46 -> 5411.2257 | R62: IC1 | S62: IC2 | T62: IC1 | U62: IC2 | V62: IC1 | W62: IC2 | X62: IC1 | Y62: IC2
B63: 45530.748 | C63: =INT(B63) -> 45530 | D63: 11706 | F63: =WORKDAY(F62,-1) -> 45481 | G63: =SUMIF(C:C, F63, D:D) -> 21416 | H63: =ROUNDUP(MONTH(Table3[[#This Row],[Date]])/3, 0) -> 3 | I63: {=(SUM(OFFSET(G63, -$M$4/2+1, 0, $M$4-1, 1)) + (INDIRECT("G" & ROW(G63) - $M$4/2) + INDIRECT("G" & ROW(G63) + $M$4/2))/2) / $M$4} -> 18989.386 | J63: =Table3[[#This Row],[Moving Average on Months]] - 1.96*STDEV(OFFSET(Table3[[#This Row],[Combined Daily order]], -$M$4/2, 0, $M$4+1, 1)) -> 11234.932 | K63: =Table3[[#This Row],[Moving Average on Months]] + 1.96*STDEV(OFFSET(Table3[[#This Row],[Combined Daily order]], -$M$4/2, 0, $M$4+1, 1)) -> 26743.841 | L63: #N/A | N63: =$V$46 -> 45729.883 | O63: =$U$46 -> 5411.2257 | Q63: 1st Quarter | T63: =GETPIVOTDATA("Average of Orders aggregated",$Q$71,"Quarters (Date)",1,"Years (Date)",2022)-$T$46*GETPIVOTDATA("StdDev of Orders aggregated",$Q$71,"Quarters (Date)",1,"Years (Date)",2022) -> 10561.603 | U63: =GETPIVOTDATA("Average of Orders aggregated",$Q$71,"Quarters (Date)",1,"Years (Date)",2022)+$T$46*GETPIVOTDATA("StdDev of Orders aggregated",$Q$71,"Quarters (Date)",1,"Years (Date)",2022) -> 28255.835 | V63: =GETPIVOTDATA("Average of Orders aggregated",$Q$71,"Quarters (Date)",1,"Years (Date)",2023)-$T$46*GETPIVOTDATA("StdDev of Orders aggregated",$Q$71,"Quarters (Date)",1,"Years (Date)",2023) -> 8875.2587 | W63: =GETPIVOTDATA("Average of Orders aggregated",$Q$71,"Quarters (Date)",1,"Years (Date)",2023)+$T$46*GETPIVOTDATA("StdDev of Orders aggregated",$Q$71,"Quarters (Date)",1,"Years (Date)",2023) -> 31806.003 | X63: =GETPIVOTDATA("Average of Orders aggregated",$Q$71,"Quarters (Date)",1,"Years (Date)",2024)-$T$46*GETPIVOTDATA("StdDev of Orders aggregated",$Q$71,"Quarters (Date)",1,"Years (Date)",2024) -> 11344.741 | Y63: =GETPIVOTDATA("Average of Orders aggregated",$Q$71,"Quarters (Date)",1,"Years (Date)",2024)+$T$46*GETPIVOTDATA("StdDev of Orders aggregated",$Q$71,"Quarters (Date)",1,"Years (Date)",2024) -> 34171.074
B64: 45530.347 | C64: =INT(B64) -> 45530 | D64: 12465 | F64: =WORKDAY(F63,-1) -> 45478 | G64: =SUMIF(C:C, F64, D:D) -> 13990 | H64: =ROUNDUP(MONTH(Table3[[#This Row],[Date]])/3, 0) -> 3 | I64: {=(SUM(OFFSET(G64, -$M$4/2+1, 0, $M$4-1, 1)) + (INDIRECT("G" & ROW(G64) - $M$4/2) + INDIRECT("G" & ROW(G64) + $M$4/2))/2) / $M$4} -> 19141.114 | J64: =Table3[[#This Row],[Moving Average on Months]] - 1.96*STDEV(OFFSET(Table3[[#This Row],[Combined Daily order]], -$M$4/2, 0, $M$4+1, 1)) -> 11560.935 | K64: =Table3[[#This Row],[Moving Average on Months]] + 1.96*STDEV(OFFSET(Table3[[#This Row],[Combined Daily order]], -$M$4/2, 0, $M$4+1, 1)) -> 26721.293 | L64: #N/A | N64: =$V$46 -> 45729.883 | O64: =$U$46 -> 5411.2257 | Q64: 2nd Quarter | T64: =GETPIVOTDATA("Average of Orders aggregated",$Q$71,"Quarters (Date)",2,"Years (Date)",2022)-$T$46*GETPIVOTDATA("StdDev of Orders aggregated",$Q$71,"Quarters (Date)",2,"Years (Date)",2022) -> 10175.172 | U64: =GETPIVOTDATA("Average of Orders aggregated",$Q$71,"Quarters (Date)",2,"Years (Date)",2022)+$T$46*GETPIVOTDATA("StdDev of Orders aggregated",$Q$71,"Quarters (Date)",2,"Years (Date)",2022) -> 26649.935 | V64: =GETPIVOTDATA("Average of Orders aggregated",$Q$71,"Quarters (Date)",2,"Years (Date)",2023)-$T$46*GETPIVOTDATA("StdDev of Orders aggregated",$Q$71,"Quarters (Date)",2,"Years (Date)",2023) -> 11717.818 | W64: =GETPIVOTDATA("Average of Orders aggregated",$Q$71,"Quarters (Date)",2,"Years (Date)",2023)+$T$46*GETPIVOTDATA("StdDev of Orders aggregated",$Q$71,"Quarters (Date)",2,"Years (Date)",2023) -> 30597.598 | X64: =GETPIVOTDATA("Average of Orders aggregated",$Q$71,"Quarters (Date)",2,"Years (Date)",2024)-$T$46*GETPIVOTDATA("StdDev of Orders aggregated",$Q$71,"Quarters (Date)",2,"Years (Date)",2024) -> 13294.282 | Y64: =GETPIVOTDATA("Average of Orders aggregated",$Q$71,"Quarters (Date)",2,"Years (Date)",2024)+$T$46*GETPIVOTDATA("StdDev of Orders aggregated",$Q$71,"Quarters (Date)",2,"Years (Date)",2024) -> 32616.026
B65: 45527.956 | C65: =INT(B65) -> 45527 | D65: 10878 | F65: =WORKDAY(F64,-1) -> 45477 | G65: =SUMIF(C:C, F65, D:D) -> 22843 | H65: =ROUNDUP(MONTH(Table3[[#This Row],[Date]])/3, 0) -> 3 | I65: {=(SUM(OFFSET(G65, -$M$4/2+1, 0, $M$4-1, 1)) + (INDIRECT("G" & ROW(G65) - $M$4/2) + INDIRECT("G" & ROW(G65) + $M$4/2))/2) / $M$4} -> 19309.114 | J65: =Table3[[#This Row],[Moving Average on Months]] - 1.96*STDEV(OFFSET(Table3[[#This Row],[Combined Daily order]], -$M$4/2, 0, $M$4+1, 1)) -> 11427.164 | K65: =Table3[[#This Row],[Moving Average on Months]] + 1.96*STDEV(OFFSET(Table3[[#This Row],[Combined Daily order]], -$M$4/2, 0, $M$4+1, 1)) -> 27191.063 | L65: #N/A | N65: =$V$46 -> 45729.883 | O65: =$U$46 -> 5411.2257 | Q65: 3rd Quarter | R65: =GETPIVOTDATA("Average of Orders aggregated",$Q$71,"Quarters (Date)",3,"Years (Date)",2021) - 'Raw Black and outliers handling'!$T$46*GETPIVOTDATA("StdDev of Orders aggregated",$Q$71,"Quarters (Date)",3,"Years (Date)",2021) -> 15005.388 | S65: =GETPIVOTDATA("Average of Orders aggregated",$Q$71,"Quarters (Date)",3,"Years (Date)",2021) + 'Raw Black and outliers handling'!$T$46*GETPIVOTDATA("StdDev of Orders aggregated",$Q$71,"Quarters (Date)",3,"Years (Date)",2021) -> 34816.793 | T65: =GETPIVOTDATA("Average of Orders aggregated",$Q$71,"Quarters (Date)",3,"Years (Date)",2022) - 'Raw Black and outliers handling'!$T$46*GETPIVOTDATA("StdDev of Orders aggregated",$Q$71,"Quarters (Date)",3,"Years (Date)",2022) -> 8832.9992 | U65: =GETPIVOTDATA("Average of Orders aggregated",$Q$71,"Quarters (Date)",3,"Years (Date)",2022) + 'Raw Black and outliers handling'!$T$46*GETPIVOTDATA("StdDev of Orders aggregated",$Q$71,"Quarters (Date)",3,"Years (Date)",2022) -> 32212.698 | V65: =GETPIVOTDATA("Average of Orders aggregated",$Q$71,"Quarters (Date)",3,"Years (Date)",2023) - 'Raw Black and outliers handling'!$T$46*GETPIVOTDATA("StdDev of Orders aggregated",$Q$71,"Quarters (Date)",3,"Years (Date)",2023) -> 8885.6819 | W65: =GETPIVOTDATA("Average of Orders aggregated",$Q$71,"Quarters (Date)",3,"Years (Date)",2023) + 'Raw Black and outliers handling'!$T$46*GETPIVOTDATA("StdDev of Orders aggregated",$Q$71,"Quarters (Date)",3,"Years (Date)",2023) -> 38846.349 | X65: =GETPIVOTDATA("Average of Orders aggregated",$Q$71,"Quarters (Date)",3,"Years (Date)",2024) - 'Raw Black and outliers handling'!$T$46*GETPIVOTDATA("StdDev of Orders aggregated",$Q$71,"Quarters (Date)",3,"Years (Date)",2024) -> 10832.025 | Y65: =GETPIVOTDATA("Average of Orders aggregated",$Q$71,"Quarters (Date)",3,"Years (Date)",2024) + 'Raw Black and outliers handling'!$T$46*GETPIVOTDATA("StdDev of Orders aggregated",$Q$71,"Quarters (Date)",3,"Years (Date)",2024) -> 40283.329
B66: 45527.556 | C66: =INT(B66) -> 45527 | D66: 10524 | F66: =WORKDAY(F65,-1) -> 45476 | G66: =SUMIF(C:C, F66, D:D) -> 15901 | H66: =ROUNDUP(MONTH(Table3[[#This Row],[Date]])/3, 0) -> 3 | I66: {=(SUM(OFFSET(G66, -$M$4/2+1, 0, $M$4-1, 1)) + (INDIRECT("G" & ROW(G66) - $M$4/2) + INDIRECT("G" & ROW(G66) + $M$4/2))/2) / $M$4} -> 19476.023 | J66: =Table3[[#This Row],[Moving Average on Months]] - 1.96*STDEV(OFFSET(Table3[[#This Row],[Combined Daily order]], -$M$4/2, 0, $M$4+1, 1)) -> 11910.086 | K66: =Table3[[#This Row],[Moving Average on Months]] + 1.96*STDEV(OFFSET(Table3[[#This Row],[Combined Daily order]], -$M$4/2, 0, $M$4+1, 1)) -> 27041.959 | L66: #N/A | N66: =$V$46 -> 45729.883 | O66: =$U$46 -> 5411.2257 | Q66: 4th Quarter | R66: =GETPIVOTDATA("Average of Orders aggregated",$Q$71,"Quarters (Date)",4,"Years (Date)",2021)-$T$46*GETPIVOTDATA("StdDev of Orders aggregated",$Q$71,"Quarters (Date)",4,"Years (Date)",2021) -> 13425.142 | S66: =GETPIVOTDATA("Average of Orders aggregated",$Q$71,"Quarters (Date)",4,"Years (Date)",2021)+$T$46*GETPIVOTDATA("StdDev of Orders aggregated",$Q$71,"Quarters (Date)",4,"Years (Date)",2021) -> 58794.888 | T66: =GETPIVOTDATA("Average of Orders aggregated",$Q$71,"Quarters (Date)",4,"Years (Date)",2022)-$T$46*GETPIVOTDATA("StdDev of Orders aggregated",$Q$71,"Quarters (Date)",4,"Years (Date)",2022) -> 15082.164 | U66: =GETPIVOTDATA("Average of Orders aggregated",$Q$71,"Quarters (Date)",4,"Years (Date)",2022)+$T$46*GETPIVOTDATA("StdDev of Orders aggregated",$Q$71,"Quarters (Date)",4,"Years (Date)",2022) -> 54558.512 | V66: =GETPIVOTDATA("Average of Orders aggregated",$Q$71,"Quarters (Date)",4,"Years (Date)",2023)-$T$46*GETPIVOTDATA("StdDev of Orders aggregated",$Q$71,"Quarters (Date)",4,"Years (Date)",2023) -> 16901.324 | W66: =GETPIVOTDATA("Average of Orders aggregated",$Q$71,"Quarters (Date)",4,"Years (Date)",2023)+$T$46*GETPIVOTDATA("StdDev of Orders aggregated",$Q$71,"Quarters (Date)",4,"Years (Date)",2023) -> 65060.676
B67: 45527.148 | C67: =INT(B67) -> 45527 | D67: 12035 | F67: =WORKDAY(F66,-1) -> 45475 | G67: =SUMIF(C:C, F67, D:D) -> 22666 | H67: =ROUNDUP(MONTH(Table3[[#This Row],[Date]])/3, 0) -> 3 | I67: {=(SUM(OFFSET(G67, -$M$4/2+1, 0, $M$4-1, 1)) + (INDIRECT("G" & ROW(G67) - $M$4/2) + INDIRECT("G" & ROW(G67) + $M$4/2))/2) / $M$4} -> 19681.659 | J67: =Table3[[#This Row],[Moving Average on Months]] - 1.96*STDEV(OFFSET(Table3[[#This Row],[Combined Daily order]], -$M$4/2, 0, $M$4+1, 1)) -> 11501.547 | K67: =Table3[[#This Row],[Moving Average on Months]] + 1.96*STDEV(OFFSET(Table3[[#This Row],[Combined Daily order]], -$M$4/2, 0, $M$4+1, 1)) -> 27861.771 | L67: #N/A | N67: =$V$46 -> 45729.883 | O67: =$U$46 -> 5411.2257
B68: 45526.727 | C68: =INT(B68) -> 45526 | D68: 12431 | F68: =WORKDAY(F67,-1) -> 45474 | G68: =SUMIF(C:C, F68, D:D) -> 22105 | H68: =ROUNDUP(MONTH(Table3[[#This Row],[Date]])/3, 0) -> 3 | I68: {=(SUM(OFFSET(G68, -$M$4/2+1, 0, $M$4-1, 1)) + (INDIRECT("G" & ROW(G68) - $M$4/2) + INDIRECT("G" & ROW(G68) + $M$4/2))/2) / $M$4} -> 19910.727 | J68: =Table3[[#This Row],[Moving Average on Months]] - 1.96*STDEV(OFFSET(Table3[[#This Row],[Combined Daily order]], -$M$4/2, 0, $M$4+1, 1)) -> 11998.091 | K68: =Table3[[#This Row],[Moving Average on Months]] + 1.96*STDEV(OFFSET(Table3[[#This Row],[Combined Daily order]], -$M$4/2, 0, $M$4+1, 1)) -> 27823.364 | L68: #N/A | N68: =$V$46 -> 45729.883 | O68: =$U$46 -> 5411.2257
B69: 45526.299 | C69: =INT(B69) -> 45526 | D69: 11997 | F69: =WORKDAY(F68,-1) -> 45471 | G69: =SUMIF(C:C, F69, D:D) -> 16911 | H69: =ROUNDUP(MONTH(Table3[[#This Row],[Date]])/3, 0) -> 2 | I69: {=(SUM(OFFSET(G69, -$M$4/2+1, 0, $M$4-1, 1)) + (INDIRECT("G" & ROW(G69) - $M$4/2) + INDIRECT("G" & ROW(G69) + $M$4/2))/2) / $M$4} -> 20126.545 | J69: =Table3[[#This Row],[Moving Average on Months]] - 1.96*STDEV(OFFSET(Table3[[#This Row],[Combined Daily order]], -$M$4/2, 0, $M$4+1, 1)) -> 11866 | K69: =Table3[[#This Row],[Moving Average on Months]] + 1.96*STDEV(OFFSET(Table3[[#This Row],[Combined Daily order]], -$M$4/2, 0, $M$4+1, 1)) -> 28387.091 | L69: #N/A | N69: =$V$46 -> 45729.883 | O69: =$U$46 -> 5411.2257
B70: 45525.899 | C70: =INT(B70) -> 45525 | D70: 10089 | F70: =WORKDAY(F69,-1) -> 45470 | G70: =SUMIF(C:C, F70, D:D) -> 23820 | H70: =ROUNDUP(MONTH(Table3[[#This Row],[Date]])/3, 0) -> 2 | I70: {=(SUM(OFFSET(G70, -$M$4/2+1, 0, $M$4-1, 1)) + (INDIRECT("G" & ROW(G70) - $M$4/2) + INDIRECT("G" & ROW(G70) + $M$4/2))/2) / $M$4} -> 20319.045 | J70: =Table3[[#This Row],[Moving Average on Months]] - 1.96*STDEV(OFFSET(Table3[[#This Row],[Combined Daily order]], -$M$4/2, 0, $M$4+1, 1)) -> 12446.835 | K70: =Table3[[#This Row],[Moving Average on Months]] + 1.96*STDEV(OFFSET(Table3[[#This Row],[Combined Daily order]], -$M$4/2, 0, $M$4+1, 1)) -> 28191.256 | L70: #N/A | N70: =$V$46 -> 45729.883 | O70: =$U$46 -> 5411.2257
B71: 45525.517 | C71: =INT(B71) -> 45525 | D71: 11651 | F71: =WORKDAY(F70,-1) -> 45469 | G71: =SUMIF(C:C, F71, D:D) -> 17037 | H71: =ROUNDUP(MONTH(Table3[[#This Row],[Date]])/3, 0) -> 2 | I71: {=(SUM(OFFSET(G71, -$M$4/2+1, 0, $M$4-1, 1)) + (INDIRECT("G" & ROW(G71) - $M$4/2) + INDIRECT("G" & ROW(G71) + $M$4/2))/2) / $M$4} -> 20447.591 | J71: =Table3[[#This Row],[Moving Average on Months]] - 1.96*STDEV(OFFSET(Table3[[#This Row],[Combined Daily order]], -$M$4/2, 0, $M$4+1, 1)) -> 12381.412 | K71: =Table3[[#This Row],[Moving Average on Months]] + 1.96*STDEV(OFFSET(Table3[[#This Row],[Combined Daily order]], -$M$4/2, 0, $M$4+1, 1)) -> 28513.77 | L71: #N/A | N71: =$V$46 -> 45729.883 | O71: =$U$46 -> 5411.2257 | R71: Column Labels
B72: 45525.125 | C72: =INT(B72) -> 45525 | D72: 12347 | F72: =WORKDAY(F71,-1) -> 45468 | G72: =SUMIF(C:C, F72, D:D) -> 24073 | H72: =ROUNDUP(MONTH(Table3[[#This Row],[Date]])/3, 0) -> 2 | I72: {=(SUM(OFFSET(G72, -$M$4/2+1, 0, $M$4-1, 1)) + (INDIRECT("G" & ROW(G72) - $M$4/2) + INDIRECT("G" & ROW(G72) + $M$4/2))/2) / $M$4} -> 20558.955 | J72: =Table3[[#This Row],[Moving Average on Months]] - 1.96*STDEV(OFFSET(Table3[[#This Row],[Combined Daily order]], -$M$4/2, 0, $M$4+1, 1)) -> 12708.781 | K72: =Table3[[#This Row],[Moving Average on Months]] + 1.96*STDEV(OFFSET(Table3[[#This Row],[Combined Daily order]], -$M$4/2, 0, $M$4+1, 1)) -> 28409.128 | L72: #N/A | N72: =$V$46 -> 45729.883 | O72: =$U$46 -> 5411.2257 | R72: 2021 | T72: 2022 | V72: 2023 | X72: 2024 | Z72: Total Average of Orders aggregated | AA72: Total StdDev of Orders aggregated
B73: 45524.737 | C73: =INT(B73) -> 45524 | D73: 12746 | F73: =WORKDAY(F72,-1) -> 45467 | G73: =SUMIF(C:C, F73, D:D) -> 17779 | H73: =ROUNDUP(MONTH(Table3[[#This Row],[Date]])/3, 0) -> 2 | I73: {=(SUM(OFFSET(G73, -$M$4/2+1, 0, $M$4-1, 1)) + (INDIRECT("G" & ROW(G73) - $M$4/2) + INDIRECT("G" & ROW(G73) + $M$4/2))/2) / $M$4} -> 20723.932 | J73: =Table3[[#This Row],[Moving Average on Months]] - 1.96*STDEV(OFFSET(Table3[[#This Row],[Combined Daily order]], -$M$4/2, 0, $M$4+1, 1)) -> 12523.851 | K73: =Table3[[#This Row],[Moving Average on Months]] + 1.96*STDEV(OFFSET(Table3[[#This Row],[Combined Daily order]], -$M$4/2, 0, $M$4+1, 1)) -> 28924.012 | L73: #N/A | N73: =$V$46 -> 45729.883 | O73: =$U$46 -> 5411.2257 | Q73: Row Labels | R73: Average of Orders aggregated | S73: StdDev of Orders aggregated | T73: Average of Orders aggregated | U73: StdDev of Orders aggregated | V73: Average of Orders aggregated | W73: StdDev of Orders aggregated | X73: Average of Orders aggregated | Y73: StdDev of Orders aggregated
B74: 45524.359 | C74: =INT(B74) -> 45524 | D74: 11240 | F74: =WORKDAY(F73,-1) -> 45464 | G74: =SUMIF(C:C, F74, D:D) -> 25669 | H74: =ROUNDUP(MONTH(Table3[[#This Row],[Date]])/3, 0) -> 2 | I74: {=(SUM(OFFSET(G74, -$M$4/2+1, 0, $M$4-1, 1)) + (INDIRECT("G" & ROW(G74) - $M$4/2) + INDIRECT("G" & ROW(G74) + $M$4/2))/2) / $M$4} -> 20893.727 | J74: =Table3[[#This Row],[Moving Average on Months]] - 1.96*STDEV(OFFSET(Table3[[#This Row],[Combined Daily order]], -$M$4/2, 0, $M$4+1, 1)) -> 12959.756 | K74: =Table3[[#This Row],[Moving Average on Months]] + 1.96*STDEV(OFFSET(Table3[[#This Row],[Combined Daily order]], -$M$4/2, 0, $M$4+1, 1)) -> 28827.699 | L74: #N/A | N74: =$V$46 -> 45729.883 | O74: =$U$46 -> 5411.2257 | Q74: Qtr1 | T74: 19408.719 | U74: 4513.8346 | V74: 20340.631 | W74: 5849.6796 | X74: 22757.908 | Y74: 5823.0441 | Z74: 20843.108 | AA74: 5589.6452
B75: 45523.929 | C75: =INT(B75) -> 45523 | D75: 10799 | F75: =WORKDAY(F74,-1) -> 45463 | G75: =SUMIF(C:C, F75, D:D) -> 18334 | H75: =ROUNDUP(MONTH(Table3[[#This Row],[Date]])/3, 0) -> 2 | I75: {=(SUM(OFFSET(G75, -$M$4/2+1, 0, $M$4-1, 1)) + (INDIRECT("G" & ROW(G75) - $M$4/2) + INDIRECT("G" & ROW(G75) + $M$4/2))/2) / $M$4} -> 21150.159 | J75: =Table3[[#This Row],[Moving Average on Months]] - 1.96*STDEV(OFFSET(Table3[[#This Row],[Combined Daily order]], -$M$4/2, 0, $M$4+1, 1)) -> 12420.687 | K75: =Table3[[#This Row],[Moving Average on Months]] + 1.96*STDEV(OFFSET(Table3[[#This Row],[Combined Daily order]], -$M$4/2, 0, $M$4+1, 1)) -> 29879.631 | L75: #N/A | N75: =$V$46 -> 45729.883 | O75: =$U$46 -> 5411.2257 | Q75: Qtr2 | T75: 18412.554 | U75: 4202.7456 | V75: 21157.708 | W75: 4816.2704 | X75: 22955.154 | Y75: 4929.0165 | Z75: 20841.805 | AA75: 5000.143
B76: 45523.554 | C76: =INT(B76) -> 45523 | D76: 10553 | F76: =WORKDAY(F75,-1) -> 45462 | G76: =SUMIF(C:C, F76, D:D) -> 25203 | H76: =ROUNDUP(MONTH(Table3[[#This Row],[Date]])/3, 0) -> 2 | I76: {=(SUM(OFFSET(G76, -$M$4/2+1, 0, $M$4-1, 1)) + (INDIRECT("G" & ROW(G76) - $M$4/2) + INDIRECT("G" & ROW(G76) + $M$4/2))/2) / $M$4} -> 21419.841 | J76: =Table3[[#This Row],[Moving Average on Months]] - 1.96*STDEV(OFFSET(Table3[[#This Row],[Combined Daily order]], -$M$4/2, 0, $M$4+1, 1)) -> 13183.666 | K76: =Table3[[#This Row],[Moving Average on Months]] + 1.96*STDEV(OFFSET(Table3[[#This Row],[Combined Daily order]], -$M$4/2, 0, $M$4+1, 1)) -> 29656.016 | L76: #N/A | N76: =$V$46 -> 45729.883 | O76: =$U$46 -> 5411.2257 | Q76: Qtr3 | R76: 24911.091 | S76: 5053.9299 | T76: 20522.848 | U76: 5964.2088 | V76: 23866.015 | W76: 7643.0273 | X76: 25557.677 | Y76: 7513.0878 | Z76: 23463.725 | AA76: 7155.9871
B77: 45523.17 | C77: =INT(B77) -> 45523 | D77: 10729 | F77: =WORKDAY(F76,-1) -> 45461 | G77: =SUMIF(C:C, F77, D:D) -> 18041 | H77: =ROUNDUP(MONTH(Table3[[#This Row],[Date]])/3, 0) -> 2 | I77: {=(SUM(OFFSET(G77, -$M$4/2+1, 0, $M$4-1, 1)) + (INDIRECT("G" & ROW(G77) - $M$4/2) + INDIRECT("G" & ROW(G77) + $M$4/2))/2) / $M$4} -> 21620.591 | J77: =Table3[[#This Row],[Moving Average on Months]] - 1.96*STDEV(OFFSET(Table3[[#This Row],[Combined Daily order]], -$M$4/2, 0, $M$4+1, 1)) -> 12886.822 | K77: =Table3[[#This Row],[Moving Average on Months]] + 1.96*STDEV(OFFSET(Table3[[#This Row],[Combined Daily order]], -$M$4/2, 0, $M$4+1, 1)) -> 30354.359 | L77: #N/A | N77: =$V$46 -> 45729.883 | O77: =$U$46 -> 5411.2257 | Q77: Qtr4 | R77: 36110.015 | S77: 11573.915 | T77: 34820.338 | U77: 10070.497 | V77: 40981 | W77: 12285.549 | Z77: 37297.694 | AA77: 11598.263
B78: 45520.724 | C78: =INT(B78) -> 45520 | D78: 10571 | F78: =WORKDAY(F77,-1) -> 45460 | G78: =SUMIF(C:C, F78, D:D) -> 27417 | H78: =ROUNDUP(MONTH(Table3[[#This Row],[Date]])/3, 0) -> 2 | I78: {=(SUM(OFFSET(G78, -$M$4/2+1, 0, $M$4-1, 1)) + (INDIRECT("G" & ROW(G78) - $M$4/2) + INDIRECT("G" & ROW(G78) + $M$4/2))/2) / $M$4} -> 22036.386 | J78: =Table3[[#This Row],[Moving Average on Months]] - 1.96*STDEV(OFFSET(Table3[[#This Row],[Combined Daily order]], -$M$4/2, 0, $M$4+1, 1)) -> 13262.109 | K78: =Table3[[#This Row],[Moving Average on Months]] + 1.96*STDEV(OFFSET(Table3[[#This Row],[Combined Daily order]], -$M$4/2, 0, $M$4+1, 1)) -> 30810.664 | L78: #N/A | N78: =$V$46 -> 45729.883 | O78: =$U$46 -> 5411.2257 | Q78: Grand Total | R78: 33310.284 | S78: 11403.194 | T78: 23295.4 | U78: 9397.7378 | V78: 26586.338 | W78: 11703.142 | X78: 23756.913 | Y78: 6281.6222 | Z78: 25570.554 | AA78: 10285.372
B79: 45520.352 | C79: =INT(B79) -> 45520 | D79: 10092 | F79: =WORKDAY(F78,-1) -> 45457 | G79: =SUMIF(C:C, F79, D:D) -> 17813 | H79: =ROUNDUP(MONTH(Table3[[#This Row],[Date]])/3, 0) -> 2 | I79: {=(SUM(OFFSET(G79, -$M$4/2+1, 0, $M$4-1, 1)) + (INDIRECT("G" & ROW(G79) - $M$4/2) + INDIRECT("G" & ROW(G79) + $M$4/2))/2) / $M$4} -> 22073.068 | J79: =Table3[[#This Row],[Moving Average on Months]] - 1.96*STDEV(OFFSET(Table3[[#This Row],[Combined Daily order]], -$M$4/2, 0, $M$4+1, 1)) -> 13147.19 | K79: =Table3[[#This Row],[Moving Average on Months]] + 1.96*STDEV(OFFSET(Table3[[#This Row],[Combined Daily order]], -$M$4/2, 0, $M$4+1, 1)) -> 30998.946 | L79: #N/A | N79: =$V$46 -> 45729.883 | O79: =$U$46 -> 5411.2257
B80: 45519.927 | C80: =INT(B80) -> 45519 | D80: 11712 | F80: =WORKDAY(F79,-1) -> 45456 | G80: =SUMIF(C:C, F80, D:D) -> 25711 | H80: =ROUNDUP(MONTH(Table3[[#This Row],[Date]])/3, 0) -> 2 | I80: {=(SUM(OFFSET(G80, -$M$4/2+1, 0, $M$4-1, 1)) + (INDIRECT("G" & ROW(G80) - $M$4/2) + INDIRECT("G" & ROW(G80) + $M$4/2))/2) / $M$4} -> 22236.318 | J80: =Table3[[#This Row],[Moving Average on Months]] - 1.96*STDEV(OFFSET(Table3[[#This Row],[Combined Daily order]], -$M$4/2, 0, $M$4+1, 1)) -> 12969.799 | K80: =Table3[[#This Row],[Moving Average on Months]] + 1.96*STDEV(OFFSET(Table3[[#This Row],[Combined Daily order]], -$M$4/2, 0, $M$4+1, 1)) -> 31502.837 | L80: #N/A | N80: =$V$46 -> 45729.883 | O80: =$U$46 -> 5411.2257
B81: 45519.51 | C81: =INT(B81) -> 45519 | D81: 11062 | F81: =WORKDAY(F80,-1) -> 45455 | G81: =SUMIF(C:C, F81, D:D) -> 16870 | H81: =ROUNDUP(MONTH(Table3[[#This Row],[Date]])/3, 0) -> 2 | I81: {=(SUM(OFFSET(G81, -$M$4/2+1, 0, $M$4-1, 1)) + (INDIRECT("G" & ROW(G81) - $M$4/2) + INDIRECT("G" & ROW(G81) + $M$4/2))/2) / $M$4} -> 22354.705 | J81: =Table3[[#This Row],[Moving Average on Months]] - 1.96*STDEV(OFFSET(Table3[[#This Row],[Combined Daily order]], -$M$4/2, 0, $M$4+1, 1)) -> 13176.337 | K81: =Table3[[#This Row],[Moving Average on Months]] + 1.96*STDEV(OFFSET(Table3[[#This Row],[Combined Daily order]], -$M$4/2, 0, $M$4+1, 1)) -> 31533.072 | L81: #N/A | N81: =$V$46 -> 45729.883 | O81: =$U$46 -> 5411.2257
B82: 45519.123 | C82: =INT(B82) -> 45519 | D82: 10324 | F82: =WORKDAY(F81,-1) -> 45454 | G82: =SUMIF(C:C, F82, D:D) -> 24567 | H82: =ROUNDUP(MONTH(Table3[[#This Row],[Date]])/3, 0) -> 2 | I82: {=(SUM(OFFSET(G82, -$M$4/2+1, 0, $M$4-1, 1)) + (INDIRECT("G" & ROW(G82) - $M$4/2) + INDIRECT("G" & ROW(G82) + $M$4/2))/2) / $M$4} -> 22485.591 | J82: =Table3[[#This Row],[Moving Average on Months]] - 1.96*STDEV(OFFSET(Table3[[#This Row],[Combined Daily order]], -$M$4/2, 0, $M$4+1, 1)) -> 12949.333 | K82: =Table3[[#This Row],[Moving Average on Months]] + 1.96*STDEV(OFFSET(Table3[[#This Row],[Combined Daily order]], -$M$4/2, 0, $M$4+1, 1)) -> 32021.849 | L82: #N/A | N82: =$V$46 -> 45729.883 | O82: =$U$46 -> 5411.2257
B83: 45518.736 | C83: =INT(B83) -> 45518 | D83: 12094 | F83: =WORKDAY(F82,-1) -> 45453 | G83: =SUMIF(C:C, F83, D:D) -> 17281 | H83: =ROUNDUP(MONTH(Table3[[#This Row],[Date]])/3, 0) -> 2 | I83: {=(SUM(OFFSET(G83, -$M$4/2+1, 0, $M$4-1, 1)) + (INDIRECT("G" & ROW(G83) - $M$4/2) + INDIRECT("G" & ROW(G83) + $M$4/2))/2) / $M$4} -> 22659.159 | J83: =Table3[[#This Row],[Moving Average on Months]] - 1.96*STDEV(OFFSET(Table3[[#This Row],[Combined Daily order]], -$M$4/2, 0, $M$4+1, 1)) -> 13344.989 | K83: =Table3[[#This Row],[Moving Average on Months]] + 1.96*STDEV(OFFSET(Table3[[#This Row],[Combined Daily order]], -$M$4/2, 0, $M$4+1, 1)) -> 31973.329 | L83: #N/A | N83: =$V$46 -> 45729.883 | O83: =$U$46 -> 5411.2257
B84: 45518.346 | C84: =INT(B84) -> 45518 | D84: 9653 | F84: =WORKDAY(F83,-1) -> 45450 | G84: =SUMIF(C:C, F84, D:D) -> 26440 | H84: =ROUNDUP(MONTH(Table3[[#This Row],[Date]])/3, 0) -> 2 | I84: {=(SUM(OFFSET(G84, -$M$4/2+1, 0, $M$4-1, 1)) + (INDIRECT("G" & ROW(G84) - $M$4/2) + INDIRECT("G" & ROW(G84) + $M$4/2))/2) / $M$4} -> 22830.659 | J84: =Table3[[#This Row],[Moving Average on Months]] - 1.96*STDEV(OFFSET(Table3[[#This Row],[Combined Daily order]], -$M$4/2, 0, $M$4+1, 1)) -> 13126.081 | K84: =Table3[[#This Row],[Moving Average on Months]] + 1.96*STDEV(OFFSET(Table3[[#This Row],[Combined Daily order]], -$M$4/2, 0, $M$4+1, 1)) -> 32535.237 | L84: #N/A | N84: =$V$46 -> 45729.883 | O84: =$U$46 -> 5411.2257
B85: 45517.969 | C85: =INT(B85) -> 45517 | D85: 9673 | F85: =WORKDAY(F84,-1) -> 45449 | G85: =SUMIF(C:C, F85, D:D) -> 16966 | H85: =ROUNDUP(MONTH(Table3[[#This Row],[Date]])/3, 0) -> 2 | I85: {=(SUM(OFFSET(G85, -$M$4/2+1, 0, $M$4-1, 1)) + (INDIRECT("G" & ROW(G85) - $M$4/2) + INDIRECT("G" & ROW(G85) + $M$4/2))/2) / $M$4} -> 22920.773 | J85: =Table3[[#This Row],[Moving Average on Months]] - 1.96*STDEV(OFFSET(Table3[[#This Row],[Combined Daily order]], -$M$4/2, 0, $M$4+1, 1)) -> 13236.98 | K85: =Table3[[#This Row],[Moving Average on Months]] + 1.96*STDEV(OFFSET(Table3[[#This Row],[Combined Daily order]], -$M$4/2, 0, $M$4+1, 1)) -> 32604.566 | L85: #N/A | N85: =$V$46 -> 45729.883 | O85: =$U$46 -> 5411.2257
B86: 45517.589 | C86: =INT(B86) -> 45517 | D86: 11309 | F86: =WORKDAY(F85,-1) -> 45448 | G86: =SUMIF(C:C, F86, D:D) -> 29723 | H86: =ROUNDUP(MONTH(Table3[[#This Row],[Date]])/3, 0) -> 2 | I86: {=(SUM(OFFSET(G86, -$M$4/2+1, 0, $M$4-1, 1)) + (INDIRECT("G" & ROW(G86) - $M$4/2) + INDIRECT("G" & ROW(G86) + $M$4/2))/2) / $M$4} -> 22981.386 | J86: =Table3[[#This Row],[Moving Average on Months]] - 1.96*STDEV(OFFSET(Table3[[#This Row],[Combined Daily order]], -$M$4/2, 0, $M$4+1, 1)) -> 13072.406 | K86: =Table3[[#This Row],[Moving Average on Months]] + 1.96*STDEV(OFFSET(Table3[[#This Row],[Combined Daily order]], -$M$4/2, 0, $M$4+1, 1)) -> 32890.366 | L86: #N/A | N86: =$V$46 -> 45729.883 | O86: =$U$46 -> 5411.2257
B87: 45517.173 | C87: =INT(B87) -> 45517 | D87: 10941 | F87: =WORKDAY(F86,-1) -> 45447 | G87: =SUMIF(C:C, F87, D:D) -> 18976 | H87: =ROUNDUP(MONTH(Table3[[#This Row],[Date]])/3, 0) -> 2 | I87: {=(SUM(OFFSET(G87, -$M$4/2+1, 0, $M$4-1, 1)) + (INDIRECT("G" & ROW(G87) - $M$4/2) + INDIRECT("G" & ROW(G87) + $M$4/2))/2) / $M$4} -> 23039.545 | J87: =Table3[[#This Row],[Moving Average on Months]] - 1.96*STDEV(OFFSET(Table3[[#This Row],[Combined Daily order]], -$M$4/2, 0, $M$4+1, 1)) -> 13050.293 | K87: =Table3[[#This Row],[Moving Average on Months]] + 1.96*STDEV(OFFSET(Table3[[#This Row],[Combined Daily order]], -$M$4/2, 0, $M$4+1, 1)) -> 33028.798 | L87: #N/A | N87: =$V$46 -> 45729.883 | O87: =$U$46 -> 5411.2257
B88: 45516.785 | C88: =INT(B88) -> 45516 | D88: 9810 | F88: =WORKDAY(F87,-1) -> 45446 | G88: =SUMIF(C:C, F88, D:D) -> 28601 | H88: =ROUNDUP(MONTH(Table3[[#This Row],[Date]])/3, 0) -> 2 | I88: {=(SUM(OFFSET(G88, -$M$4/2+1, 0, $M$4-1, 1)) + (INDIRECT("G" & ROW(G88) - $M$4/2) + INDIRECT("G" & ROW(G88) + $M$4/2))/2) / $M$4} -> 23117.409 | J88: =Table3[[#This Row],[Moving Average on Months]] - 1.96*STDEV(OFFSET(Table3[[#This Row],[Combined Daily order]], -$M$4/2, 0, $M$4+1, 1)) -> 12838.891 | K88: =Table3[[#This Row],[Moving Average on Months]] + 1.96*STDEV(OFFSET(Table3[[#This Row],[Combined Daily order]], -$M$4/2, 0, $M$4+1, 1)) -> 33395.927 | L88: #N/A | N88: =$V$46 -> 45729.883 | O88: =$U$46 -> 5411.2257
B89: 45516.39 | C89: =INT(B89) -> 45516 | D89: 10150 | F89: =WORKDAY(F88,-1) -> 45443 | G89: =SUMIF(C:C, F89, D:D) -> 28261 | H89: =ROUNDUP(MONTH(Table3[[#This Row],[Date]])/3, 0) -> 2 | I89: {=(SUM(OFFSET(G89, -$M$4/2+1, 0, $M$4-1, 1)) + (INDIRECT("G" & ROW(G89) - $M$4/2) + INDIRECT("G" & ROW(G89) + $M$4/2))/2) / $M$4} -> 23185.364 | J89: =Table3[[#This Row],[Moving Average on Months]] - 1.96*STDEV(OFFSET(Table3[[#This Row],[Combined Daily order]], -$M$4/2, 0, $M$4+1, 1)) -> 12997.747 | K89: =Table3[[#This Row],[Moving Average on Months]] + 1.96*STDEV(OFFSET(Table3[[#This Row],[Combined Daily order]], -$M$4/2, 0, $M$4+1, 1)) -> 33372.98 | L89: #N/A | N89: =$V$46 -> 45729.883 | O89: =$U$46 -> 5411.2257
B90: 45513.999 | C90: =INT(B90) -> 45513 | D90: 11389 | F90: =WORKDAY(F89,-1) -> 45442 | G90: =SUMIF(C:C, F90, D:D) -> 18124 | H90: =ROUNDUP(MONTH(Table3[[#This Row],[Date]])/3, 0) -> 2 | I90: {=(SUM(OFFSET(G90, -$M$4/2+1, 0, $M$4-1, 1)) + (INDIRECT("G" & ROW(G90) - $M$4/2) + INDIRECT("G" & ROW(G90) + $M$4/2))/2) / $M$4} -> 23252.705 | J90: =Table3[[#This Row],[Moving Average on Months]] - 1.96*STDEV(OFFSET(Table3[[#This Row],[Combined Daily order]], -$M$4/2, 0, $M$4+1, 1)) -> 12932.901 | K90: =Table3[[#This Row],[Moving Average on Months]] + 1.96*STDEV(OFFSET(Table3[[#This Row],[Combined Daily order]], -$M$4/2, 0, $M$4+1, 1)) -> 33572.508 | L90: #N/A | N90: =$V$46 -> 45729.883 | O90: =$U$46 -> 5411.2257
... B193: 45456.938 | C193: =INT(B193) -> 45456 | D193: 8579 | F193: =WORKDAY(F192,-1) -> 45299 | G193: =SUMIF(C:C, F193, D:D) -> 22551 | H193: =ROUNDUP(MONTH(Table3[[#This Row],[Date]])/3, 0) -> 1 | I193: {=(SUM(OFFSET(G193, -$M$4/2+1, 0, $M$4-1, 1)) + (INDIRECT("G" & ROW(G193) - $M$4/2) + INDIRECT("G" & ROW(G193) + $M$4/2))/2) / $M$4} -> 29995.273 | J193: =Table3[[#This Row],[Moving Average on Months]] - 1.96*STDEV(OFFSET(Table3[[#This Row],[Combined Daily order]], -$M$4/2, 0, $M$4+1, 1)) -> 7768.7024 | K193: =Table3[[#This Row],[Moving Average on Months]] + 1.96*STDEV(OFFSET(Table3[[#This Row],[Combined Daily order]], -$M$4/2, 0, $M$4+1, 1)) -> 52221.843 | L193: #N/A | N193: =$V$46 -> 45729.883 | O193: =$U$46 -> 5411.2257
B194: 45456.547 | C194: =INT(B194) -> 45456 | D194: 9066 | F194: =WORKDAY(F193,-1) -> 45296 | G194: =SUMIF(C:C, F194, D:D) -> 37373 | H194: =ROUNDUP(MONTH(Table3[[#This Row],[Date]])/3, 0) -> 1 | I194: {=(SUM(OFFSET(G194, -$M$4/2+1, 0, $M$4-1, 1)) + (INDIRECT("G" & ROW(G194) - $M$4/2) + INDIRECT("G" & ROW(G194) + $M$4/2))/2) / $M$4} -> 31177.545 | J194: =Table3[[#This Row],[Moving Average on Months]] - 1.96*STDEV(OFFSET(Table3[[#This Row],[Combined Daily order]], -$M$4/2, 0, $M$4+1, 1)) -> 8954.2045 | K194: =Table3[[#This Row],[Moving Average on Months]] + 1.96*STDEV(OFFSET(Table3[[#This Row],[Combined Daily order]], -$M$4/2, 0, $M$4+1, 1)) -> 53400.886 | L194: =Table3[[#This Row],[Combined Daily order]] -> 37373 | N194: =$V$46 -> 45729.883 | O194: =$U$46 -> 5411.2257
B195: 45456.175 | C195: =INT(B195) -> 45456 | D195: 8066 | F195: =WORKDAY(F194,-1) -> 45295 | G195: =SUMIF(C:C, F195, D:D) -> 25641 | H195: =ROUNDUP(MONTH(Table3[[#This Row],[Date]])/3, 0) -> 1 | I195: {=(SUM(OFFSET(G195, -$M$4/2+1, 0, $M$4-1, 1)) + (INDIRECT("G" & ROW(G195) - $M$4/2) + INDIRECT("G" & ROW(G195) + $M$4/2))/2) / $M$4} -> 32419.364 | J195: =Table3[[#This Row],[Moving Average on Months]] - 1.96*STDEV(OFFSET(Table3[[#This Row],[Combined Daily order]], -$M$4/2, 0, $M$4+1, 1)) -> 8215.366 | K195: =Table3[[#This Row],[Moving Average on Months]] + 1.96*STDEV(OFFSET(Table3[[#This Row],[Combined Daily order]], -$M$4/2, 0, $M$4+1, 1)) -> 56623.361 | L195: #N/A | N195: =$V$46 -> 45729.883 | O195: =$U$46 -> 5411.2257
B196: 45455.791 | C196: =INT(B196) -> 45455 | D196: 9167 | F196: =WORKDAY(F195,-1) -> 45294 | G196: =SUMIF(C:C, F196, D:D) -> 40101 | H196: =ROUNDUP(MONTH(Table3[[#This Row],[Date]])/3, 0) -> 1 | I196: {=(SUM(OFFSET(G196, -$M$4/2+1, 0, $M$4-1, 1)) + (INDIRECT("G" & ROW(G196) - $M$4/2) + INDIRECT("G" & ROW(G196) + $M$4/2))/2) / $M$4} -> 33742.682 | J196: =Table3[[#This Row],[Moving Average on Months]] - 1.96*STDEV(OFFSET(Table3[[#This Row],[Combined Daily order]], -$M$4/2, 0, $M$4+1, 1)) -> 9565.5678 | K196: =Table3[[#This Row],[Moving Average on Months]] + 1.96*STDEV(OFFSET(Table3[[#This Row],[Combined Daily order]], -$M$4/2, 0, $M$4+1, 1)) -> 57919.796 | L196: =Table3[[#This Row],[Combined Daily order]] -> 40101 | N196: =$V$46 -> 45729.883 | O196: =$U$46 -> 5411.2257
B197: 45455.363 | C197: =INT(B197) -> 45455 | D197: 7703 | F197: =WORKDAY(F196,-1) -> 45293 | G197: =SUMIF(C:C, F197, D:D) -> 28461 | H197: =ROUNDUP(MONTH(Table3[[#This Row],[Date]])/3, 0) -> 1 | I197: {=(SUM(OFFSET(G197, -$M$4/2+1, 0, $M$4-1, 1)) + (INDIRECT("G" & ROW(G197) - $M$4/2) + INDIRECT("G" & ROW(G197) + $M$4/2))/2) / $M$4} -> 35118.409 | J197: =Table3[[#This Row],[Moving Average on Months]] - 1.96*STDEV(OFFSET(Table3[[#This Row],[Combined Daily order]], -$M$4/2, 0, $M$4+1, 1)) -> 9143.8916 | K197: =Table3[[#This Row],[Moving Average on Months]] + 1.96*STDEV(OFFSET(Table3[[#This Row],[Combined Daily order]], -$M$4/2, 0, $M$4+1, 1)) -> 61092.927 | L197: #N/A | N197: =$V$46 -> 45729.883 | O197: =$U$46 -> 5411.2257
B198: 45454.983 | C198: =INT(B198) -> 45454 | D198: 8218 | F198: =WORKDAY(F197,-1) -> 45292 | G198: =SUMIF(C:C, F198, D:D) -> 42191 | H198: =ROUNDUP(MONTH(Table3[[#This Row],[Date]])/3, 0) -> 1 | I198: {=(SUM(OFFSET(G198, -$M$4/2+1, 0, $M$4-1, 1)) + (INDIRECT("G" & ROW(G198) - $M$4/2) + INDIRECT("G" & ROW(G198) + $M$4/2))/2) / $M$4} -> 36665.5 | J198: =Table3[[#This Row],[Moving Average on Months]] - 1.96*STDEV(OFFSET(Table3[[#This Row],[Combined Daily order]], -$M$4/2, 0, $M$4+1, 1)) -> 10622.849 | K198: =Table3[[#This Row],[Moving Average on Months]] + 1.96*STDEV(OFFSET(Table3[[#This Row],[Combined Daily order]], -$M$4/2, 0, $M$4+1, 1)) -> 62708.151 | L198: =Table3[[#This Row],[Combined Daily order]] -> 42191 | N198: =$V$46 -> 45729.883 | O198: =$U$46 -> 5411.2257
B199: 45454.589 | C199: =INT(B199) -> 45454 | D199: 8103 | F199: =WORKDAY(F198,-1) -> 45289 | G199: =SUMIF(C:C, F199, D:D) -> 32667 | H199: =ROUNDUP(MONTH(Table3[[#This Row],[Date]])/3, 0) -> 4 | I199: {=(SUM(OFFSET(G199, -$M$4/2+1, 0, $M$4-1, 1)) + (INDIRECT("G" & ROW(G199) - $M$4/2) + INDIRECT("G" & ROW(G199) + $M$4/2))/2) / $M$4} -> 38369.818 | J199: =Table3[[#This Row],[Moving Average on Months]] - 1.96*STDEV(OFFSET(Table3[[#This Row],[Combined Daily order]], -$M$4/2, 0, $M$4+1, 1)) -> 10731.138 | K199: =Table3[[#This Row],[Moving Average on Months]] + 1.96*STDEV(OFFSET(Table3[[#This Row],[Combined Daily order]], -$M$4/2, 0, $M$4+1, 1)) -> 66008.498 | L199: #N/A | N199: =$V$46 -> 45729.883 | O199: =$U$46 -> 5411.2257
B200: 45454.171 | C200: =INT(B200) -> 45454 | D200: 8246 | F200: =WORKDAY(F199,-1) -> 45288 | G200: =SUMIF(C:C, F200, D:D) -> 46651 | H200: =ROUNDUP(MONTH(Table3[[#This Row],[Date]])/3, 0) -> 4 | I200: {=(SUM(OFFSET(G200, -$M$4/2+1, 0, $M$4-1, 1)) + (INDIRECT("G" & ROW(G200) - $M$4/2) + INDIRECT("G" & ROW(G200) + $M$4/2))/2) / $M$4} -> 39965.477 | J200: =Table3[[#This Row],[Moving Average on Months]] - 1.96*STDEV(OFFSET(Table3[[#This Row],[Combined Daily order]], -$M$4/2, 0, $M$4+1, 1)) -> 12956.899 | K200: =Table3[[#This Row],[Moving Average on Months]] + 1.96*STDEV(OFFSET(Table3[[#This Row],[Combined Daily order]], -$M$4/2, 0, $M$4+1, 1)) -> 66974.055 | L200: #N/A | N200: =$V$46 -> 45729.883 | O200: =$U$46 -> 5411.2257
B201: 45453.771 | C201: =INT(B201) -> 45453 | D201: 7756 | F201: =WORKDAY(F200,-1) -> 45287 | G201: =SUMIF(C:C, F201, D:D) -> 33123 | H201: =ROUNDUP(MONTH(Table3[[#This Row],[Date]])/3, 0) -> 4 | I201: {=(SUM(OFFSET(G201, -$M$4/2+1, 0, $M$4-1, 1)) + (INDIRECT("G" & ROW(G201) - $M$4/2) + INDIRECT("G" & ROW(G201) + $M$4/2))/2) / $M$4} -> 41228.409 | J201: =Table3[[#This Row],[Moving Average on Months]] - 1.96*STDEV(OFFSET(Table3[[#This Row],[Combined Daily order]], -$M$4/2, 0, $M$4+1, 1)) -> 14933.009 | K201: =Table3[[#This Row],[Moving Average on Months]] + 1.96*STDEV(OFFSET(Table3[[#This Row],[Combined Daily order]], -$M$4/2, 0, $M$4+1, 1)) -> 67523.809 | L201: #N/A | N201: =$V$46 -> 45729.883 | O201: =$U$46 -> 5411.2257
B202: 45453.349 | C202: =INT(B202) -> 45453 | D202: 9525 | F202: =WORKDAY(F201,-1) -> 45286 | G202: =SUMIF(C:C, F202, D:D) -> 52401 | H202: =ROUNDUP(MONTH(Table3[[#This Row],[Date]])/3, 0) -> 4 | I202: {=(SUM(OFFSET(G202, -$M$4/2+1, 0, $M$4-1, 1)) + (INDIRECT("G" & ROW(G202) - $M$4/2) + INDIRECT("G" & ROW(G202) + $M$4/2))/2) / $M$4} -> 42398.795 | J202: =Table3[[#This Row],[Moving Average on Months]] - 1.96*STDEV(OFFSET(Table3[[#This Row],[Combined Daily order]], -$M$4/2, 0, $M$4+1, 1)) -> 16724.948 | K202: =Table3[[#This Row],[Moving Average on Months]] + 1.96*STDEV(OFFSET(Table3[[#This Row],[Combined Daily order]], -$M$4/2, 0, $M$4+1, 1)) -> 68072.643 | L202: #N/A | N202: =$V$46 -> 45729.883 | O202: =$U$46 -> 5411.2257
B203: 45450.911 | C203: =INT(B203) -> 45450 | D203: 8254 | F203: =WORKDAY(F202,-1) -> 45285 | G203: =SUMIF(C:C, F203, D:D) -> 34112 | H203: =ROUNDUP(MONTH(Table3[[#This Row],[Date]])/3, 0) -> 4 | I203: {=(SUM(OFFSET(G203, -$M$4/2+1, 0, $M$4-1, 1)) + (INDIRECT("G" & ROW(G203) - $M$4/2) + INDIRECT("G" & ROW(G203) + $M$4/2))/2) / $M$4} -> 43660.909 | J203: =Table3[[#This Row],[Moving Average on Months]] - 1.96*STDEV(OFFSET(Table3[[#This Row],[Combined Daily order]], -$M$4/2, 0, $M$4+1, 1)) -> 18000.894 | K203: =Table3[[#This Row],[Moving Average on Months]] + 1.96*STDEV(OFFSET(Table3[[#This Row],[Combined Daily order]], -$M$4/2, 0, $M$4+1, 1)) -> 69320.924 | L203: #N/A | N203: =$V$46 -> 45729.883 | O203: =$U$46 -> 5411.2257
B204: 45450.524 | C204: =INT(B204) -> 45450 | D204: 8349 | F204: =WORKDAY(F203,-1) -> 45282 | G204: =SUMIF(C:C, F204, D:D) -> 58062 | H204: =ROUNDUP(MONTH(Table3[[#This Row],[Date]])/3, 0) -> 4 | I204: {=(SUM(OFFSET(G204, -$M$4/2+1, 0, $M$4-1, 1)) + (INDIRECT("G" & ROW(G204) - $M$4/2) + INDIRECT("G" & ROW(G204) + $M$4/2))/2) / $M$4} -> 44787.432 | J204: =Table3[[#This Row],[Moving Average on Months]] - 1.96*STDEV(OFFSET(Table3[[#This Row],[Combined Daily order]], -$M$4/2, 0, $M$4+1, 1)) -> 19677.129 | K204: =Table3[[#This Row],[Moving Average on Months]] + 1.96*STDEV(OFFSET(Table3[[#This Row],[Combined Daily order]], -$M$4/2, 0, $M$4+1, 1)) -> 69897.735 | L204: #N/A | N204: =$V$46 -> 45729.883 | O204: =$U$46 -> 5411.2257
B205: 45450.117 | C205: =INT(B205) -> 45450 | D205: 9837 | F205: =WORKDAY(F204,-1) -> 45281 | G205: =SUMIF(C:C, F205, D:D) -> 35552 | H205: =ROUNDUP(MONTH(Table3[[#This Row],[Date]])/3, 0) -> 4 | I205: {=(SUM(OFFSET(G205, -$M$4/2+1, 0, $M$4-1, 1)) + (INDIRECT("G" & ROW(G205) - $M$4/2) + INDIRECT("G" & ROW(G205) + $M$4/2))/2) / $M$4} -> 45671.091 | J205: =Table3[[#This Row],[Moving Average on Months]] - 1.96*STDEV(OFFSET(Table3[[#This Row],[Combined Daily order]], -$M$4/2, 0, $M$4+1, 1)) -> 21528.095 | K205: =Table3[[#This Row],[Moving Average on Months]] + 1.96*STDEV(OFFSET(Table3[[#This Row],[Combined Daily order]], -$M$4/2, 0, $M$4+1, 1)) -> 69814.087 | L205: #N/A | N205: =$V$46 -> 45729.883 | O205: =$U$46 -> 5411.2257
...

Sheet Raw Beige and outliers handling
A1: Beige QC Headphones: Raw Data and Outliers Handling
B3: Date | C3: Column1 | D3: Orders | F3: Unique Date | G3: Combined Daily Order | H3: Quarter | I3: Moving Average on Months | J3: Lower Bound Computed on Moving Average | K3: Upper Bound Computed on Moving Average | L3: Presumed Outliers | M3: Period of Moving Average | N3: Lower Bound Computed on the whole series of data | O3: Upper Bound Computed on the whole series of data | S3: Bose Quiet Confort Beige
B4: 45562.707 | C4: =INT(B4) -> 45562 | D4: 6388 | F4: 45562 | G4: =SUMIF(C:C, F4, D:D) -> 12033 | H4: =ROUNDUP(MONTH(Table3[[#This Row],[Date]])/3, 0) -> 3 | L4: #N/A | M4: 22 | N4: =$W$48 -> 2594.4026 | O4: =$X$48 -> 23487.587
B5: 45562.285 | C5: =INT(B5) -> 45562 | D5: 5645 | F5: =WORKDAY(F4,-1) -> 45561 | G5: =SUMIF(C:C, F5, D:D) -> 18563 | H5: =ROUNDUP(MONTH(Table3[[#This Row],[Date]])/3, 0) -> 3 | L5: #N/A | N5: =$W$48 -> 2594.4026 | O5: =$X$48 -> 23487.587
B6: 45561.902 | C6: =INT(B6) -> 45561 | D6: 6615 | F6: =WORKDAY(F5,-1) -> 45560 | G6: =SUMIF(C:C, F6, D:D) -> 12821 | H6: =ROUNDUP(MONTH(Table3[[#This Row],[Date]])/3, 0) -> 3 | L6: #N/A | N6: =$W$48 -> 2594.4026 | O6: =$X$48 -> 23487.587
B7: 45561.481 | C7: =INT(B7) -> 45561 | D7: 5755 | F7: =WORKDAY(F6,-1) -> 45559 | G7: =SUMIF(C:C, F7, D:D) -> 19276 | H7: =ROUNDUP(MONTH(Table3[[#This Row],[Date]])/3, 0) -> 3 | L7: #N/A | N7: =$W$48 -> 2594.4026 | O7: =$X$48 -> 23487.587
B8: 45561.098 | C8: =INT(B8) -> 45561 | D8: 6193 | F8: =WORKDAY(F7,-1) -> 45558 | G8: =SUMIF(C:C, F8, D:D) -> 12583 | H8: =ROUNDUP(MONTH(Table3[[#This Row],[Date]])/3, 0) -> 3 | L8: #N/A | N8: =$W$48 -> 2594.4026 | O8: =$X$48 -> 23487.587
B9: 45560.725 | C9: =INT(B9) -> 45560 | D9: 6732 | F9: =WORKDAY(F8,-1) -> 45555 | G9: =SUMIF(C:C, F9, D:D) -> 18787 | H9: =ROUNDUP(MONTH(Table3[[#This Row],[Date]])/3, 0) -> 3 | L9: #N/A | N9: =$W$48 -> 2594.4026 | O9: =$X$48 -> 23487.587
B10: 45560.306 | C10: =INT(B10) -> 45560 | D10: 6089 | F10: =WORKDAY(F9,-1) -> 45554 | G10: =SUMIF(C:C, F10, D:D) -> 11693 | H10: =ROUNDUP(MONTH(Table3[[#This Row],[Date]])/3, 0) -> 3 | L10: #N/A | N10: =$W$48 -> 2594.4026 | O10: =$X$48 -> 23487.587
B11: 45559.887 | C11: =INT(B11) -> 45559 | D11: 7041 | F11: =WORKDAY(F10,-1) -> 45553 | G11: =SUMIF(C:C, F11, D:D) -> 11473 | H11: =ROUNDUP(MONTH(Table3[[#This Row],[Date]])/3, 0) -> 3 | L11: #N/A | N11: =$W$48 -> 2594.4026 | O11: =$X$48 -> 23487.587
B12: 45559.459 | C12: =INT(B12) -> 45559 | D12: 6565 | F12: =WORKDAY(F11,-1) -> 45552 | G12: =SUMIF(C:C, F12, D:D) -> 18928 | H12: =ROUNDUP(MONTH(Table3[[#This Row],[Date]])/3, 0) -> 3 | L12: #N/A | N12: =$W$48 -> 2594.4026 | O12: =$X$48 -> 23487.587
B13: 45559.055 | C13: =INT(B13) -> 45559 | D13: 5670 | F13: =WORKDAY(F12,-1) -> 45551 | G13: =SUMIF(C:C, F13, D:D) -> 13779 | H13: =ROUNDUP(MONTH(Table3[[#This Row],[Date]])/3, 0) -> 3 | L13: #N/A | N13: =$W$48 -> 2594.4026 | O13: =$X$48 -> 23487.587
B14: 45558.654 | C14: =INT(B14) -> 45558 | D14: 6088 | F14: =WORKDAY(F13,-1) -> 45548 | G14: =SUMIF(C:C, F14, D:D) -> 18795 | H14: =ROUNDUP(MONTH(Table3[[#This Row],[Date]])/3, 0) -> 3 | L14: #N/A | N14: =$W$48 -> 2594.4026 | O14: =$X$48 -> 23487.587
B15: 45558.26 | C15: =INT(B15) -> 45558 | D15: 6495 | F15: =WORKDAY(F14,-1) -> 45547 | G15: =SUMIF(C:C, F15, D:D) -> 11667 | H15: =ROUNDUP(MONTH(Table3[[#This Row],[Date]])/3, 0) -> 3 | I15: {=(SUM(OFFSET(G15, -$M$4/2+1, 0, $M$4-1, 1)) + (INDIRECT("G" & ROW(G15) - $M$4/2) + INDIRECT("G" & ROW(G15) + $M$4/2))/2) / $M$4} -> 15034.182 | J15: =Table5[[#This Row],[Moving Average on Months]] - 1.96*STDEV(OFFSET(Table5[[#This Row],[Combined Daily Order]], -$M$4/2, 0, $M$4+1, 1)) -> 8619.1002 | K15: =Table5[[#This Row],[Moving Average on Months]] + 1.96*STDEV(OFFSET(Table5[[#This Row],[Combined Daily Order]], -$M$4/2, 0, $M$4+1, 1)) -> 21449.263 | L15: #N/A | N15: =$W$48 -> 2594.4026 | O15: =$X$48 -> 23487.587
B16: 45555.835 | C16: =INT(B16) -> 45555 | D16: 5677 | F16: =WORKDAY(F15,-1) -> 45546 | G16: =SUMIF(C:C, F16, D:D) -> 17317 | H16: =ROUNDUP(MONTH(Table3[[#This Row],[Date]])/3, 0) -> 3 | I16: {=(SUM(OFFSET(G16, -$M$4/2+1, 0, $M$4-1, 1)) + (INDIRECT("G" & ROW(G16) - $M$4/2) + INDIRECT("G" & ROW(G16) + $M$4/2))/2) / $M$4} -> 15029.614 | J16: =Table5[[#This Row],[Moving Average on Months]] - 1.96*STDEV(OFFSET(Table5[[#This Row],[Combined Daily Order]], -$M$4/2, 0, $M$4+1, 1)) -> 8602.2126 | K16: =Table5[[#This Row],[Moving Average on Months]] + 1.96*STDEV(OFFSET(Table5[[#This Row],[Combined Daily Order]], -$M$4/2, 0, $M$4+1, 1)) -> 21457.015 | L16: #N/A | N16: =$W$48 -> 2594.4026 | O16: =$X$48 -> 23487.587
B17: 45555.406 | C17: =INT(B17) -> 45555 | D17: 6584 | F17: =WORKDAY(F16,-1) -> 45545 | G17: =SUMIF(C:C, F17, D:D) -> 12128 | H17: =ROUNDUP(MONTH(Table3[[#This Row],[Date]])/3, 0) -> 3 | I17: {=(SUM(OFFSET(G17, -$M$4/2+1, 0, $M$4-1, 1)) + (INDIRECT("G" & ROW(G17) - $M$4/2) + INDIRECT("G" & ROW(G17) + $M$4/2))/2) / $M$4} -> 14970.409 | J17: =Table5[[#This Row],[Moving Average on Months]] - 1.96*STDEV(OFFSET(Table5[[#This Row],[Combined Daily Order]], -$M$4/2, 0, $M$4+1, 1)) -> 8667.9106 | K17: =Table5[[#This Row],[Moving Average on Months]] + 1.96*STDEV(OFFSET(Table5[[#This Row],[Combined Daily Order]], -$M$4/2, 0, $M$4+1, 1)) -> 21272.908 | L17: #N/A | N17: =$W$48 -> 2594.4026 | O17: =$X$48 -> 23487.587
B18: 45555.002 | C18: =INT(B18) -> 45555 | D18: 6526 | F18: =WORKDAY(F17,-1) -> 45544 | G18: =SUMIF(C:C, F18, D:D) -> 19007 | H18: =ROUNDUP(MONTH(Table3[[#This Row],[Date]])/3, 0) -> 3 | I18: {=(SUM(OFFSET(G18, -$M$4/2+1, 0, $M$4-1, 1)) + (INDIRECT("G" & ROW(G18) - $M$4/2) + INDIRECT("G" & ROW(G18) + $M$4/2))/2) / $M$4} -> 14901.886 | J18: =Table5[[#This Row],[Moving Average on Months]] - 1.96*STDEV(OFFSET(Table5[[#This Row],[Combined Daily Order]], -$M$4/2, 0, $M$4+1, 1)) -> 8556.6894 | K18: =Table5[[#This Row],[Moving Average on Months]] + 1.96*STDEV(OFFSET(Table5[[#This Row],[Combined Daily Order]], -$M$4/2, 0, $M$4+1, 1)) -> 21247.083 | L18: #N/A | N18: =$W$48 -> 2594.4026 | O18: =$X$48 -> 23487.587
B19: 45554.574 | C19: =INT(B19) -> 45554 | D19: 5713 | F19: =WORKDAY(F18,-1) -> 45541 | G19: =SUMIF(C:C, F19, D:D) -> 17738 | H19: =ROUNDUP(MONTH(Table3[[#This Row],[Date]])/3, 0) -> 3 | I19: {=(SUM(OFFSET(G19, -$M$4/2+1, 0, $M$4-1, 1)) + (INDIRECT("G" & ROW(G19) - $M$4/2) + INDIRECT("G" & ROW(G19) + $M$4/2))/2) / $M$4} -> 14829 | J19: =Table5[[#This Row],[Moving Average on Months]] - 1.96*STDEV(OFFSET(Table5[[#This Row],[Combined Daily Order]], -$M$4/2, 0, $M$4+1, 1)) -> 8719.8644 | K19: =Table5[[#This Row],[Moving Average on Months]] + 1.96*STDEV(OFFSET(Table5[[#This Row],[Combined Daily Order]], -$M$4/2, 0, $M$4+1, 1)) -> 20938.136 | L19: #N/A | N19: =$W$48 -> 2594.4026 | O19: =$X$48 -> 23487.587
B20: 45554.185 | C20: =INT(B20) -> 45554 | D20: 5980 | F20: =WORKDAY(F19,-1) -> 45540 | G20: =SUMIF(C:C, F20, D:D) -> 10845 | H20: =ROUNDUP(MONTH(Table3[[#This Row],[Date]])/3, 0) -> 3 | I20: {=(SUM(OFFSET(G20, -$M$4/2+1, 0, $M$4-1, 1)) + (INDIRECT("G" & ROW(G20) - $M$4/2) + INDIRECT("G" & ROW(G20) + $M$4/2))/2) / $M$4} -> 14744.477 | J20: =Table5[[#This Row],[Moving Average on Months]] - 1.96*STDEV(OFFSET(Table5[[#This Row],[Combined Daily Order]], -$M$4/2, 0, $M$4+1, 1)) -> 8520.7879 | K20: =Table5[[#This Row],[Moving Average on Months]] + 1.96*STDEV(OFFSET(Table5[[#This Row],[Combined Daily Order]], -$M$4/2, 0, $M$4+1, 1)) -> 20968.167 | L20: #N/A | N20: =$W$48 -> 2594.4026 | O20: =$X$48 -> 23487.587
B21: 45553.763 | C21: =INT(B21) -> 45553 | D21: 5914 | F21: =WORKDAY(F20,-1) -> 45539 | G21: =SUMIF(C:C, F21, D:D) -> 17695 | H21: =ROUNDUP(MONTH(Table3[[#This Row],[Date]])/3, 0) -> 3 | I21: {=(SUM(OFFSET(G21, -$M$4/2+1, 0, $M$4-1, 1)) + (INDIRECT("G" & ROW(G21) - $M$4/2) + INDIRECT("G" & ROW(G21) + $M$4/2))/2) / $M$4} -> 14690.841 | J21: =Table5[[#This Row],[Moving Average on Months]] - 1.96*STDEV(OFFSET(Table5[[#This Row],[Combined Daily Order]], -$M$4/2, 0, $M$4+1, 1)) -> 8633.0348 | K21: =Table5[[#This Row],[Moving Average on Months]] + 1.96*STDEV(OFFSET(Table5[[#This Row],[Combined Daily Order]], -$M$4/2, 0, $M$4+1, 1)) -> 20748.647 | L21: #N/A | N21: =$W$48 -> 2594.4026 | O21: =$X$48 -> 23487.587
B22: 45553.377 | C22: =INT(B22) -> 45553 | D22: 5559 | F22: =WORKDAY(F21,-1) -> 45538 | G22: =SUMIF(C:C, F22, D:D) -> 12392 | H22: =ROUNDUP(MONTH(Table3[[#This Row],[Date]])/3, 0) -> 3 | I22: {=(SUM(OFFSET(G22, -$M$4/2+1, 0, $M$4-1, 1)) + (INDIRECT("G" & ROW(G22) - $M$4/2) + INDIRECT("G" & ROW(G22) + $M$4/2))/2) / $M$4} -> 14815.75 | J22: =Table5[[#This Row],[Moving Average on Months]] - 1.96*STDEV(OFFSET(Table5[[#This Row],[Combined Daily Order]], -$M$4/2, 0, $M$4+1, 1)) -> 8761.1056 | K22: =Table5[[#This Row],[Moving Average on Months]] + 1.96*STDEV(OFFSET(Table5[[#This Row],[Combined Daily Order]], -$M$4/2, 0, $M$4+1, 1)) -> 20870.394 | L22: #N/A | N22: =$W$48 -> 2594.4026 | O22: =$X$48 -> 23487.587
B23: 45552.971 | C23: =INT(B23) -> 45552 | D23: 5925 | F23: =WORKDAY(F22,-1) -> 45537 | G23: =SUMIF(C:C, F23, D:D) -> 16595 | H23: =ROUNDUP(MONTH(Table3[[#This Row],[Date]])/3, 0) -> 3 | I23: {=(SUM(OFFSET(G23, -$M$4/2+1, 0, $M$4-1, 1)) + (INDIRECT("G" & ROW(G23) - $M$4/2) + INDIRECT("G" & ROW(G23) + $M$4/2))/2) / $M$4} -> 14775.159 | J23: =Table5[[#This Row],[Moving Average on Months]] - 1.96*STDEV(OFFSET(Table5[[#This Row],[Combined Daily Order]], -$M$4/2, 0, $M$4+1, 1)) -> 8817.2245 | K23: =Table5[[#This Row],[Moving Average on Months]] + 1.96*STDEV(OFFSET(Table5[[#This Row],[Combined Daily Order]], -$M$4/2, 0, $M$4+1, 1)) -> 20733.094 | L23: #N/A | N23: =$W$48 -> 2594.4026 | O23: =$X$48 -> 23487.587
B24: 45552.58 | C24: =INT(B24) -> 45552 | D24: 6163 | F24: =WORKDAY(F23,-1) -> 45534 | G24: =SUMIF(C:C, F24, D:D) -> 11528 | H24: =ROUNDUP(MONTH(Table3[[#This Row],[Date]])/3, 0) -> 3 | I24: {=(SUM(OFFSET(G24, -$M$4/2+1, 0, $M$4-1, 1)) + (INDIRECT("G" & ROW(G24) - $M$4/2) + INDIRECT("G" & ROW(G24) + $M$4/2))/2) / $M$4} -> 14648.5 | J24: =Table5[[#This Row],[Moving Average on Months]] - 1.96*STDEV(OFFSET(Table5[[#This Row],[Combined Daily Order]], -$M$4/2, 0, $M$4+1, 1)) -> 8656.544 | K24: =Table5[[#This Row],[Moving Average on Months]] + 1.96*STDEV(OFFSET(Table5[[#This Row],[Combined Daily Order]], -$M$4/2, 0, $M$4+1, 1)) -> 20640.456 | L24: #N/A | N24: =$W$48 -> 2594.4026 | O24: =$X$48 -> 23487.587
B25: 45552.169 | C25: =INT(B25) -> 45552 | D25: 6840 | F25: =WORKDAY(F24,-1) -> 45533 | G25: =SUMIF(C:C, F25, D:D) -> 11871 | H25: =ROUNDUP(MONTH(Table3[[#This Row],[Date]])/3, 0) -> 3 | I25: {=(SUM(OFFSET(G25, -$M$4/2+1, 0, $M$4-1, 1)) + (INDIRECT("G" & ROW(G25) - $M$4/2) + INDIRECT("G" & ROW(G25) + $M$4/2))/2) / $M$4} -> 14500.386 | J25: =Table5[[#This Row],[Moving Average on Months]] - 1.96*STDEV(OFFSET(Table5[[#This Row],[Combined Daily Order]], -$M$4/2, 0, $M$4+1, 1)) -> 8495.7054 | K25: =Table5[[#This Row],[Moving Average on Months]] + 1.96*STDEV(OFFSET(Table5[[#This Row],[Combined Daily Order]], -$M$4/2, 0, $M$4+1, 1)) -> 20505.067 | L25: #N/A | N25: =$W$48 -> 2594.4026 | O25: =$X$48 -> 23487.587
B26: 45551.762 | C26: =INT(B26) -> 45551 | D26: 6787 | F26: =WORKDAY(F25,-1) -> 45532 | G26: =SUMIF(C:C, F26, D:D) -> 18509 | H26: =ROUNDUP(MONTH(Table3[[#This Row],[Date]])/3, 0) -> 3 | I26: {=(SUM(OFFSET(G26, -$M$4/2+1, 0, $M$4-1, 1)) + (INDIRECT("G" & ROW(G26) - $M$4/2) + INDIRECT("G" & ROW(G26) + $M$4/2))/2) / $M$4} -> 14487.318 | J26: =Table5[[#This Row],[Moving Average on Months]] - 1.96*STDEV(OFFSET(Table5[[#This Row],[Combined Daily Order]], -$M$4/2, 0, $M$4+1, 1)) -> 8751.6121 | K26: =Table5[[#This Row],[Moving Average on Months]] + 1.96*STDEV(OFFSET(Table5[[#This Row],[Combined Daily Order]], -$M$4/2, 0, $M$4+1, 1)) -> 20223.024 | L26: #N/A | N26: =$W$48 -> 2594.4026 | O26: =$X$48 -> 23487.587
... B40: 45544.139 | C40: =INT(B40) -> 45544 | D40: 5806 | F40: =WORKDAY(F39,-1) -> 45512 | G40: =SUMIF(C:C, F40, D:D) -> 9372 | H40: =ROUNDUP(MONTH(Table3[[#This Row],[Date]])/3, 0) -> 3 | I40: {=(SUM(OFFSET(G40, -$M$4/2+1, 0, $M$4-1, 1)) + (INDIRECT("G" & ROW(G40) - $M$4/2) + INDIRECT("G" & ROW(G40) + $M$4/2))/2) / $M$4} -> 12254.795 | J40: =Table5[[#This Row],[Moving Average on Months]] - 1.96*STDEV(OFFSET(Table5[[#This Row],[Combined Daily Order]], -$M$4/2, 0, $M$4+1, 1)) -> 6783.0432 | K40: =Table5[[#This Row],[Moving Average on Months]] + 1.96*STDEV(OFFSET(Table5[[#This Row],[Combined Daily Order]], -$M$4/2, 0, $M$4+1, 1)) -> 17726.548 | L40: #N/A | N40: =$W$48 -> 2594.4026 | O40: =$X$48 -> 23487.587
B41: 45541.845 | C41: =INT(B41) -> 45541 | D41: 6184 | F41: =WORKDAY(F40,-1) -> 45511 | G41: =SUMIF(C:C, F41, D:D) -> 9242 | H41: =ROUNDUP(MONTH(Table3[[#This Row],[Date]])/3, 0) -> 3 | I41: {=(SUM(OFFSET(G41, -$M$4/2+1, 0, $M$4-1, 1)) + (INDIRECT("G" & ROW(G41) - $M$4/2) + INDIRECT("G" & ROW(G41) + $M$4/2))/2) / $M$4} -> 12073.136 | J41: =Table5[[#This Row],[Moving Average on Months]] - 1.96*STDEV(OFFSET(Table5[[#This Row],[Combined Daily Order]], -$M$4/2, 0, $M$4+1, 1)) -> 6395.0157 | K41: =Table5[[#This Row],[Moving Average on Months]] + 1.96*STDEV(OFFSET(Table5[[#This Row],[Combined Daily Order]], -$M$4/2, 0, $M$4+1, 1)) -> 17751.257 | L41: #N/A | N41: =$W$48 -> 2594.4026 | O41: =$X$48 -> 23487.587 | S41: Confidence Interval computed on the whole series of data
B42: 45541.456 | C42: =INT(B42) -> 45541 | D42: 5410 | F42: =WORKDAY(F41,-1) -> 45510 | G42: =SUMIF(C:C, F42, D:D) -> 14792 | H42: =ROUNDUP(MONTH(Table3[[#This Row],[Date]])/3, 0) -> 3 | I42: {=(SUM(OFFSET(G42, -$M$4/2+1, 0, $M$4-1, 1)) + (INDIRECT("G" & ROW(G42) - $M$4/2) + INDIRECT("G" & ROW(G42) + $M$4/2))/2) / $M$4} -> 11904.159 | J42: =Table5[[#This Row],[Moving Average on Months]] - 1.96*STDEV(OFFSET(Table5[[#This Row],[Combined Daily Order]], -$M$4/2, 0, $M$4+1, 1)) -> 6541.2482 | K42: =Table5[[#This Row],[Moving Average on Months]] + 1.96*STDEV(OFFSET(Table5[[#This Row],[Combined Daily Order]], -$M$4/2, 0, $M$4+1, 1)) -> 17267.07 | L42: #N/A | N42: =$W$48 -> 2594.4026 | O42: =$X$48 -> 23487.587
B43: 45541.055 | C43: =INT(B43) -> 45541 | D43: 6144 | F43: =WORKDAY(F42,-1) -> 45509 | G43: =SUMIF(C:C, F43, D:D) -> 8842 | H43: =ROUNDUP(MONTH(Table3[[#This Row],[Date]])/3, 0) -> 3 | I43: {=(SUM(OFFSET(G43, -$M$4/2+1, 0, $M$4-1, 1)) + (INDIRECT("G" & ROW(G43) - $M$4/2) + INDIRECT("G" & ROW(G43) + $M$4/2))/2) / $M$4} -> 11704.455 | J43: =Table5[[#This Row],[Moving Average on Months]] - 1.96*STDEV(OFFSET(Table5[[#This Row],[Combined Daily Order]], -$M$4/2, 0, $M$4+1, 1)) -> 6074.2096 | K43: =Table5[[#This Row],[Moving Average on Months]] + 1.96*STDEV(OFFSET(Table5[[#This Row],[Combined Daily Order]], -$M$4/2, 0, $M$4+1, 1)) -> 17334.7 | L43: #N/A | N43: =$W$48 -> 2594.4026 | O43: =$X$48 -> 23487.587
B44: 45540.667 | C44: =INT(B44) -> 45540 | D44: 5343 | F44: =WORKDAY(F43,-1) -> 45506 | G44: =SUMIF(C:C, F44, D:D) -> 13816 | H44: =ROUNDUP(MONTH(Table3[[#This Row],[Date]])/3, 0) -> 3 | I44: {=(SUM(OFFSET(G44, -$M$4/2+1, 0, $M$4-1, 1)) + (INDIRECT("G" & ROW(G44) - $M$4/2) + INDIRECT("G" & ROW(G44) + $M$4/2))/2) / $M$4} -> 11472.25 | J44: =Table5[[#This Row],[Moving Average on Months]] - 1.96*STDEV(OFFSET(Table5[[#This Row],[Combined Daily Order]], -$M$4/2, 0, $M$4+1, 1)) -> 6291.2053 | K44: =Table5[[#This Row],[Moving Average on Months]] + 1.96*STDEV(OFFSET(Table5[[#This Row],[Combined Daily Order]], -$M$4/2, 0, $M$4+1, 1)) -> 16653.295 | L44: #N/A | N44: =$W$48 -> 2594.4026 | O44: =$X$48 -> 23487.587
B45: 45540.285 | C45: =INT(B45) -> 45540 | D45: 5502 | F45: =WORKDAY(F44,-1) -> 45505 | G45: =SUMIF(C:C, F45, D:D) -> 8437 | H45: =ROUNDUP(MONTH(Table3[[#This Row],[Date]])/3, 0) -> 3 | I45: {=(SUM(OFFSET(G45, -$M$4/2+1, 0, $M$4-1, 1)) + (INDIRECT("G" & ROW(G45) - $M$4/2) + INDIRECT("G" & ROW(G45) + $M$4/2))/2) / $M$4} -> 11217.568 | J45: =Table5[[#This Row],[Moving Average on Months]] - 1.96*STDEV(OFFSET(Table5[[#This Row],[Combined Daily Order]], -$M$4/2, 0, $M$4+1, 1)) -> 5674.5696 | K45: =Table5[[#This Row],[Moving Average on Months]] + 1.96*STDEV(OFFSET(Table5[[#This Row],[Combined Daily Order]], -$M$4/2, 0, $M$4+1, 1)) -> 16760.567 | L45: #N/A | N45: =$W$48 -> 2594.4026 | O45: =$X$48 -> 23487.587 | S45: Confidence Interval computed on the whole series of data
B46: 45539.862 | C46: =INT(B46) -> 45539 | D46: 6189 | F46: =WORKDAY(F45,-1) -> 45504 | G46: =SUMIF(C:C, F46, D:D) -> 12711 | H46: =ROUNDUP(MONTH(Table3[[#This Row],[Date]])/3, 0) -> 3 | I46: {=(SUM(OFFSET(G46, -$M$4/2+1, 0, $M$4-1, 1)) + (INDIRECT("G" & ROW(G46) - $M$4/2) + INDIRECT("G" & ROW(G46) + $M$4/2))/2) / $M$4} -> 10981.932 | J46: =Table5[[#This Row],[Moving Average on Months]] - 1.96*STDEV(OFFSET(Table5[[#This Row],[Combined Daily Order]], -$M$4/2, 0, $M$4+1, 1)) -> 5979.2071 | K46: =Table5[[#This Row],[Moving Average on Months]] + 1.96*STDEV(OFFSET(Table5[[#This Row],[Combined Daily Order]], -$M$4/2, 0, $M$4+1, 1)) -> 15984.657 | L46: #N/A | N46: =$W$48 -> 2594.4026 | O46: =$X$48 -> 23487.587
B47: 45539.455 | C47: =INT(B47) -> 45539 | D47: 5253 | F47: =WORKDAY(F46,-1) -> 45503 | G47: =SUMIF(C:C, F47, D:D) -> 8729 | H47: =ROUNDUP(MONTH(Table3[[#This Row],[Date]])/3, 0) -> 3 | I47: {=(SUM(OFFSET(G47, -$M$4/2+1, 0, $M$4-1, 1)) + (INDIRECT("G" & ROW(G47) - $M$4/2) + INDIRECT("G" & ROW(G47) + $M$4/2))/2) / $M$4} -> 10790.568 | J47: =Table5[[#This Row],[Moving Average on Months]] - 1.96*STDEV(OFFSET(Table5[[#This Row],[Combined Daily Order]], -$M$4/2, 0, $M$4+1, 1)) -> 5597.4494 | K47: =Table5[[#This Row],[Moving Average on Months]] + 1.96*STDEV(OFFSET(Table5[[#This Row],[Combined Daily Order]], -$M$4/2, 0, $M$4+1, 1)) -> 15983.687 | L47: #N/A | N47: =$W$48 -> 2594.4026 | O47: =$X$48 -> 23487.587 | S47: Average | T47: Standard Deviation | U47: Confidence Level | V47: Z-Score | W47: CI1 | X47: CI2
B48: 45539.063 | C48: =INT(B48) -> 45539 | D48: 6253 | F48: =WORKDAY(F47,-1) -> 45502 | G48: =SUMIF(C:C, F48, D:D) -> 12264 | H48: =ROUNDUP(MONTH(Table3[[#This Row],[Date]])/3, 0) -> 3 | I48: {=(SUM(OFFSET(G48, -$M$4/2+1, 0, $M$4-1, 1)) + (INDIRECT("G" & ROW(G48) - $M$4/2) + INDIRECT("G" & ROW(G48) + $M$4/2))/2) / $M$4} -> 10520.068 | J48: =Table5[[#This Row],[Moving Average on Months]] - 1.96*STDEV(OFFSET(Table5[[#This Row],[Combined Daily Order]], -$M$4/2, 0, $M$4+1, 1)) -> 5782.6677 | K48: =Table5[[#This Row],[Moving Average on Months]] + 1.96*STDEV(OFFSET(Table5[[#This Row],[Combined Daily Order]], -$M$4/2, 0, $M$4+1, 1)) -> 15257.469 | L48: #N/A | N48: =$W$48 -> 2594.4026 | O48: =$X$48 -> 23487.587 | S48: =AVERAGE(G4:G806) -> 13040.995 | T48: =STDEV(G4:G806) -> 5329.8941 | U48: 0.95 | V48: 1.96 | W48: =S48-V48*T48 -> 2594.4026 | X48: =S48+V48*T48 -> 23487.587
B49: 45538.65 | C49: =INT(B49) -> 45538 | D49: 5735 | F49: =WORKDAY(F48,-1) -> 45499 | G49: =SUMIF(C:C, F49, D:D) -> 12629 | H49: =ROUNDUP(MONTH(Table3[[#This Row],[Date]])/3, 0) -> 3 | I49: {=(SUM(OFFSET(G49, -$M$4/2+1, 0, $M$4-1, 1)) + (INDIRECT("G" & ROW(G49) - $M$4/2) + INDIRECT("G" & ROW(G49) + $M$4/2))/2) / $M$4} -> 10348.432 | J49: =Table5[[#This Row],[Moving Average on Months]] - 1.96*STDEV(OFFSET(Table5[[#This Row],[Combined Daily Order]], -$M$4/2, 0, $M$4+1, 1)) -> 5555.8947 | K49: =Table5[[#This Row],[Moving Average on Months]] + 1.96*STDEV(OFFSET(Table5[[#This Row],[Combined Daily Order]], -$M$4/2, 0, $M$4+1, 1)) -> 15140.969 | L49: #N/A | N49: =$W$48 -> 2594.4026 | O49: =$X$48 -> 23487.587
B50: 45538.266 | C50: =INT(B50) -> 45538 | D50: 6657 | F50: =WORKDAY(F49,-1) -> 45498 | G50: =SUMIF(C:C, F50, D:D) -> 8391 | H50: =ROUNDUP(MONTH(Table3[[#This Row],[Date]])/3, 0) -> 3 | I50: {=(SUM(OFFSET(G50, -$M$4/2+1, 0, $M$4-1, 1)) + (INDIRECT("G" & ROW(G50) - $M$4/2) + INDIRECT("G" & ROW(G50) + $M$4/2))/2) / $M$4} -> 10193.682 | J50: =Table5[[#This Row],[Moving Average on Months]] - 1.96*STDEV(OFFSET(Table5[[#This Row],[Combined Daily Order]], -$M$4/2, 0, $M$4+1, 1)) -> 5365.4695 | K50: =Table5[[#This Row],[Moving Average on Months]] + 1.96*STDEV(OFFSET(Table5[[#This Row],[Combined Daily Order]], -$M$4/2, 0, $M$4+1, 1)) -> 15021.894 | L50: #N/A | N50: =$W$48 -> 2594.4026 | O50: =$X$48 -> 23487.587
B51: 45537.84 | C51: =INT(B51) -> 45537 | D51: 5179 | F51: =WORKDAY(F50,-1) -> 45497 | G51: =SUMIF(C:C, F51, D:D) -> 12118 | H51: =ROUNDUP(MONTH(Table3[[#This Row],[Date]])/3, 0) -> 3 | I51: {=(SUM(OFFSET(G51, -$M$4/2+1, 0, $M$4-1, 1)) + (INDIRECT("G" & ROW(G51) - $M$4/2) + INDIRECT("G" & ROW(G51) + $M$4/2))/2) / $M$4} -> 10069.114 | J51: =Table5[[#This Row],[Moving Average on Months]] - 1.96*STDEV(OFFSET(Table5[[#This Row],[Combined Daily Order]], -$M$4/2, 0, $M$4+1, 1)) -> 5380.0386 | K51: =Table5[[#This Row],[Moving Average on Months]] + 1.96*STDEV(OFFSET(Table5[[#This Row],[Combined Daily Order]], -$M$4/2, 0, $M$4+1, 1)) -> 14758.189 | L51: #N/A | N51: =$W$48 -> 2594.4026 | O51: =$X$48 -> 23487.587
B52: 45537.453 | C52: =INT(B52) -> 45537 | D52: 5174 | F52: =WORKDAY(F51,-1) -> 45496 | G52: =SUMIF(C:C, F52, D:D) -> 8541 | H52: =ROUNDUP(MONTH(Table3[[#This Row],[Date]])/3, 0) -> 3 | I52: {=(SUM(OFFSET(G52, -$M$4/2+1, 0, $M$4-1, 1)) + (INDIRECT("G" & ROW(G52) - $M$4/2) + INDIRECT("G" & ROW(G52) + $M$4/2))/2) / $M$4} -> 10057.568 | J52: =Table5[[#This Row],[Moving Average on Months]] - 1.96*STDEV(OFFSET(Table5[[#This Row],[Combined Daily Order]], -$M$4/2, 0, $M$4+1, 1)) -> 5342.7648 | K52: =Table5[[#This Row],[Moving Average on Months]] + 1.96*STDEV(OFFSET(Table5[[#This Row],[Combined Daily Order]], -$M$4/2, 0, $M$4+1, 1)) -> 14772.372 | L52: #N/A | N52: =$W$48 -> 2594.4026 | O52: =$X$48 -> 23487.587 | S52: Confidence Interval computed on each year
B53: 45537.066 | C53: =INT(B53) -> 45537 | D53: 6242 | F53: =WORKDAY(F52,-1) -> 45495 | G53: =SUMIF(C:C, F53, D:D) -> 11675 | H53: =ROUNDUP(MONTH(Table3[[#This Row],[Date]])/3, 0) -> 3 | I53: {=(SUM(OFFSET(G53, -$M$4/2+1, 0, $M$4-1, 1)) + (INDIRECT("G" & ROW(G53) - $M$4/2) + INDIRECT("G" & ROW(G53) + $M$4/2))/2) / $M$4} -> 9938.2727 | J53: =Table5[[#This Row],[Moving Average on Months]] - 1.96*STDEV(OFFSET(Table5[[#This Row],[Combined Daily Order]], -$M$4/2, 0, $M$4+1, 1)) -> 5109.7042 | K53: =Table5[[#This Row],[Moving Average on Months]] + 1.96*STDEV(OFFSET(Table5[[#This Row],[Combined Daily Order]], -$M$4/2, 0, $M$4+1, 1)) -> 14766.841 | L53: #N/A | N53: =$W$48 -> 2594.4026 | O53: =$X$48 -> 23487.587
B54: 45534.578 | C54: =INT(B54) -> 45534 | D54: 6175 | F54: =WORKDAY(F53,-1) -> 45492 | G54: =SUMIF(C:C, F54, D:D) -> 7658 | H54: =ROUNDUP(MONTH(Table3[[#This Row],[Date]])/3, 0) -> 3 | I54: {=(SUM(OFFSET(G54, -$M$4/2+1, 0, $M$4-1, 1)) + (INDIRECT("G" & ROW(G54) - $M$4/2) + INDIRECT("G" & ROW(G54) + $M$4/2))/2) / $M$4} -> 9824 | J54: =Table5[[#This Row],[Moving Average on Months]] - 1.96*STDEV(OFFSET(Table5[[#This Row],[Combined Daily Order]], -$M$4/2, 0, $M$4+1, 1)) -> 5414.7998 | K54: =Table5[[#This Row],[Moving Average on Months]] + 1.96*STDEV(OFFSET(Table5[[#This Row],[Combined Daily Order]], -$M$4/2, 0, $M$4+1, 1)) -> 14233.2 | L54: #N/A | N54: =$W$48 -> 2594.4026 | O54: =$X$48 -> 23487.587 | S54: Year 2021 | U54: Year 2022 | W54: Year 2023 | Y54: Year 2024
B55: 45534.178 | C55: =INT(B55) -> 45534 | D55: 5353 | F55: =WORKDAY(F54,-1) -> 45491 | G55: =SUMIF(C:C, F55, D:D) -> 10787 | H55: =ROUNDUP(MONTH(Table3[[#This Row],[Date]])/3, 0) -> 3 | I55: {=(SUM(OFFSET(G55, -$M$4/2+1, 0, $M$4-1, 1)) + (INDIRECT("G" & ROW(G55) - $M$4/2) + INDIRECT("G" & ROW(G55) + $M$4/2))/2) / $M$4} -> 9731.5227 | J55: =Table5[[#This Row],[Moving Average on Months]] - 1.96*STDEV(OFFSET(Table5[[#This Row],[Combined Daily Order]], -$M$4/2, 0, $M$4+1, 1)) -> 5227.125 | K55: =Table5[[#This Row],[Moving Average on Months]] + 1.96*STDEV(OFFSET(Table5[[#This Row],[Combined Daily Order]], -$M$4/2, 0, $M$4+1, 1)) -> 14235.92 | L55: #N/A | N55: =$W$48 -> 2594.4026 | O55: =$X$48 -> 23487.587 | S55: IC1 | T55: IC2 | U55: IC1 | V55: IC2 | W55: IC1 | X55: IC2 | Y55: IC1 | Z55: IC2
B56: 45533.759 | C56: =INT(B56) -> 45533 | D56: 5404 | F56: =WORKDAY(F55,-1) -> 45490 | G56: =SUMIF(C:C, F56, D:D) -> 6622 | H56: =ROUNDUP(MONTH(Table3[[#This Row],[Date]])/3, 0) -> 3 | I56: {=(SUM(OFFSET(G56, -$M$4/2+1, 0, $M$4-1, 1)) + (INDIRECT("G" & ROW(G56) - $M$4/2) + INDIRECT("G" & ROW(G56) + $M$4/2))/2) / $M$4} -> 9639.3182 | J56: =Table5[[#This Row],[Moving Average on Months]] - 1.96*STDEV(OFFSET(Table5[[#This Row],[Combined Daily Order]], -$M$4/2, 0, $M$4+1, 1)) -> 5450.4749 | K56: =Table5[[#This Row],[Moving Average on Months]] + 1.96*STDEV(OFFSET(Table5[[#This Row],[Combined Daily Order]], -$M$4/2, 0, $M$4+1, 1)) -> 13828.161 | L56: #N/A | N56: =$W$48 -> 2594.4026 | O56: =$X$48 -> 23487.587 | S56: =AVERAGE(G719:G806) - V48*STDEV(G719:G806) -> 6033.5266 | T56: =AVERAGE(G719:G806) + V48*STDEV(G719:G806) -> 26082.36 | U56: =AVERAGE(G459:G718)-V48*STDEV(G459:G718) -> 1617.6978 | V56: =AVERAGE(G459:G718)+V48*STDEV(G459:G718) -> 23343.402 | W56: =AVERAGE(G199:G458) - V48*STDEV(G199:G458) -> 1767.7497 | X56: =AVERAGE(G199:G458) + V48*STDEV(G199:G458) -> 25258.812 | Y56: =AVERAGE(G4:G198) - V48*STDEV(G4:G198) -> 5491.0006 | Z56: =AVERAGE(G4:G198) + V48*STDEV(G4:G198) -> 18103.092
B57: 45533.384 | C57: =INT(B57) -> 45533 | D57: 6467 | F57: =WORKDAY(F56,-1) -> 45489 | G57: =SUMIF(C:C, F57, D:D) -> 10144 | H57: =ROUNDUP(MONTH(Table3[[#This Row],[Date]])/3, 0) -> 3 | I57: {=(SUM(OFFSET(G57, -$M$4/2+1, 0, $M$4-1, 1)) + (INDIRECT("G" & ROW(G57) - $M$4/2) + INDIRECT("G" & ROW(G57) + $M$4/2))/2) / $M$4} -> 9580.9318 | J57: =Table5[[#This Row],[Moving Average on Months]] - 1.96*STDEV(OFFSET(Table5[[#This Row],[Combined Daily Order]], -$M$4/2, 0, $M$4+1, 1)) -> 5350.7827 | K57: =Table5[[#This Row],[Moving Average on Months]] + 1.96*STDEV(OFFSET(Table5[[#This Row],[Combined Daily Order]], -$M$4/2, 0, $M$4+1, 1)) -> 13811.081 | L57: #N/A | N57: =$W$48 -> 2594.4026 | O57: =$X$48 -> 23487.587
B58: 45532.954 | C58: =INT(B58) -> 45532 | D58: 5724 | F58: =WORKDAY(F57,-1) -> 45488 | G58: =SUMIF(C:C, F58, D:D) -> 7493 | H58: =ROUNDUP(MONTH(Table3[[#This Row],[Date]])/3, 0) -> 3 | I58: {=(SUM(OFFSET(G58, -$M$4/2+1, 0, $M$4-1, 1)) + (INDIRECT("G" & ROW(G58) - $M$4/2) + INDIRECT("G" & ROW(G58) + $M$4/2))/2) / $M$4} -> 9545 | J58: =Table5[[#This Row],[Moving Average on Months]] - 1.96*STDEV(OFFSET(Table5[[#This Row],[Combined Daily Order]], -$M$4/2, 0, $M$4+1, 1)) -> 5388.5119 | K58: =Table5[[#This Row],[Moving Average on Months]] + 1.96*STDEV(OFFSET(Table5[[#This Row],[Combined Daily Order]], -$M$4/2, 0, $M$4+1, 1)) -> 13701.488 | L58: #N/A | N58: =$W$48 -> 2594.4026 | O58: =$X$48 -> 23487.587 | V58: Confidence Interval computed on each quarter of each year
B59: 45532.545 | C59: =INT(B59) -> 45532 | D59: 6301 | F59: =WORKDAY(F58,-1) -> 45485 | G59: =SUMIF(C:C, F59, D:D) -> 10492 | H59: =ROUNDUP(MONTH(Table3[[#This Row],[Date]])/3, 0) -> 3 | I59: {=(SUM(OFFSET(G59, -$M$4/2+1, 0, $M$4-1, 1)) + (INDIRECT("G" & ROW(G59) - $M$4/2) + INDIRECT("G" & ROW(G59) + $M$4/2))/2) / $M$4} -> 9533.8636 | J59: =Table5[[#This Row],[Moving Average on Months]] - 1.96*STDEV(OFFSET(Table5[[#This Row],[Combined Daily Order]], -$M$4/2, 0, $M$4+1, 1)) -> 5364.5919 | K59: =Table5[[#This Row],[Moving Average on Months]] + 1.96*STDEV(OFFSET(Table5[[#This Row],[Combined Daily Order]], -$M$4/2, 0, $M$4+1, 1)) -> 13703.135 | L59: #N/A | N59: =$W$48 -> 2594.4026 | O59: =$X$48 -> 23487.587
B60: 45532.131 | C60: =INT(B60) -> 45532 | D60: 6484 | F60: =WORKDAY(F59,-1) -> 45484 | G60: =SUMIF(C:C, F60, D:D) -> 6389 | H60: =ROUNDUP(MONTH(Table3[[#This Row],[Date]])/3, 0) -> 3 | I60: {=(SUM(OFFSET(G60, -$M$4/2+1, 0, $M$4-1, 1)) + (INDIRECT("G" & ROW(G60) - $M$4/2) + INDIRECT("G" & ROW(G60) + $M$4/2))/2) / $M$4} -> 9430.6136 | J60: =Table5[[#This Row],[Moving Average on Months]] - 1.96*STDEV(OFFSET(Table5[[#This Row],[Combined Daily Order]], -$M$4/2, 0, $M$4+1, 1)) -> 5297.3588 | K60: =Table5[[#This Row],[Moving Average on Months]] + 1.96*STDEV(OFFSET(Table5[[#This Row],[Combined Daily Order]], -$M$4/2, 0, $M$4+1, 1)) -> 13563.869 | L60: #N/A | N60: =$W$48 -> 2594.4026 | O60: =$X$48 -> 23487.587 | T60: Year 2021 | V60: Year 2022 | X60: Year 2023 | Z60: Year 2024
B61: 45531.731 | C61: =INT(B61) -> 45531 | D61: 5673 | F61: =WORKDAY(F60,-1) -> 45483 | G61: =SUMIF(C:C, F61, D:D) -> 11695 | H61: =ROUNDUP(MONTH(Table3[[#This Row],[Date]])/3, 0) -> 3 | I61: {=(SUM(OFFSET(G61, -$M$4/2+1, 0, $M$4-1, 1)) + (INDIRECT("G" & ROW(G61) - $M$4/2) + INDIRECT("G" & ROW(G61) + $M$4/2))/2) / $M$4} -> 9406.8864 | J61: =Table5[[#This Row],[Moving Average on Months]] - 1.96*STDEV(OFFSET(Table5[[#This Row],[Combined Daily Order]], -$M$4/2, 0, $M$4+1, 1)) -> 5448.4648 | K61: =Table5[[#This Row],[Moving Average on Months]] + 1.96*STDEV(OFFSET(Table5[[#This Row],[Combined Daily Order]], -$M$4/2, 0, $M$4+1, 1)) -> 13365.308 | L61: #N/A | N61: =$W$48 -> 2594.4026 | O61: =$X$48 -> 23487.587 | T61: IC1 | U61: IC2 | V61: IC1 | W61: IC2 | X61: IC1 | Y61: IC2 | Z61: IC1 | AA61: IC2
B62: 45531.36 | C62: =INT(B62) -> 45531 | D62: 6213 | F62: =WORKDAY(F61,-1) -> 45482 | G62: =SUMIF(C:C, F62, D:D) -> 6735 | H62: =ROUNDUP(MONTH(Table3[[#This Row],[Date]])/3, 0) -> 3 | I62: {=(SUM(OFFSET(G62, -$M$4/2+1, 0, $M$4-1, 1)) + (INDIRECT("G" & ROW(G62) - $M$4/2) + INDIRECT("G" & ROW(G62) + $M$4/2))/2) / $M$4} -> 9415.2045 | J62: =Table5[[#This Row],[Moving Average on Months]] - 1.96*STDEV(OFFSET(Table5[[#This Row],[Combined Daily Order]], -$M$4/2, 0, $M$4+1, 1)) -> 5236.7293 | K62: =Table5[[#This Row],[Moving Average on Months]] + 1.96*STDEV(OFFSET(Table5[[#This Row],[Combined Daily Order]], -$M$4/2, 0, $M$4+1, 1)) -> 13593.68 | L62: #N/A | N62: =$W$48 -> 2594.4026 | O62: =$X$48 -> 23487.587 | S62: 1st Quarter | V62: =GETPIVOTDATA("Average of Orders Aggregated",$S$72,"Quarters (Unique Date)",1,"Years (Unique Date)",2022)-$V$48*GETPIVOTDATA("StdDev of Orders Aggregated2",$S$72,"Quarters (Unique Date)",1,"Years (Unique Date)",2022) -> 4825.4665 | W62: =GETPIVOTDATA("Average of Orders Aggregated",$S$72,"Quarters (Unique Date)",1,"Years (Unique Date)",2022)+$V$48*GETPIVOTDATA("StdDev of Orders Aggregated2",$S$72,"Quarters (Unique Date)",1,"Years (Unique Date)",2022) -> 14902.44 | X62: =GETPIVOTDATA("Average of Orders Aggregated",$S$72,"Quarters (Unique Date)",1,"Years (Unique Date)",2023)-$V$48*GETPIVOTDATA("StdDev of Orders Aggregated2",$S$72,"Quarters (Unique Date)",1,"Years (Unique Date)",2023) -> 4491.8959 | Y62: =GETPIVOTDATA("Average of Orders Aggregated",$S$72,"Quarters (Unique Date)",1,"Years (Unique Date)",2023)+$V$48*GETPIVOTDATA("StdDev of Orders Aggregated2",$S$72,"Quarters (Unique Date)",1,"Years (Unique Date)",2023) -> 16574.658 | Z62: =GETPIVOTDATA("Average of Orders Aggregated",$S$72,"Quarters (Unique Date)",1,"Years (Unique Date)",2024)-$V$48*GETPIVOTDATA("StdDev of Orders Aggregated2",$S$72,"Quarters (Unique Date)",1,"Years (Unique Date)",2024) -> 4770.7411 | AA62: =GETPIVOTDATA("Average of Orders Aggregated",$S$72,"Quarters (Unique Date)",1,"Years (Unique Date)",2024)+$V$48*GETPIVOTDATA("StdDev of Orders Aggregated2",$S$72,"Quarters (Unique Date)",1,"Years (Unique Date)",2024) -> 18051.597
B63: 45530.984 | C63: =INT(B63) -> 45530 | D63: 5503 | F63: =WORKDAY(F62,-1) -> 45481 | G63: =SUMIF(C:C, F63, D:D) -> 11371 | H63: =ROUNDUP(MONTH(Table3[[#This Row],[Date]])/3, 0) -> 3 | I63: {=(SUM(OFFSET(G63, -$M$4/2+1, 0, $M$4-1, 1)) + (INDIRECT("G" & ROW(G63) - $M$4/2) + INDIRECT("G" & ROW(G63) + $M$4/2))/2) / $M$4} -> 9515.0227 | J63: =Table5[[#This Row],[Moving Average on Months]] - 1.96*STDEV(OFFSET(Table5[[#This Row],[Combined Daily Order]], -$M$4/2, 0, $M$4+1, 1)) -> 5324.7323 | K63: =Table5[[#This Row],[Moving Average on Months]] + 1.96*STDEV(OFFSET(Table5[[#This Row],[Combined Daily Order]], -$M$4/2, 0, $M$4+1, 1)) -> 13705.313 | L63: #N/A | N63: =$W$48 -> 2594.4026 | O63: =$X$48 -> 23487.587 | S63: 2nd Quarter | V63: =GETPIVOTDATA("Average of Orders Aggregated",$S$72,"Quarters (Unique Date)",2,"Years (Unique Date)",2022)-$V$48*GETPIVOTDATA("StdDev of Orders Aggregated2",$S$72,"Quarters (Unique Date)",2,"Years (Unique Date)",2022) -> 4921.3329 | W63: =GETPIVOTDATA("Average of Orders Aggregated",$S$72,"Quarters (Unique Date)",2,"Years (Unique Date)",2022)+$V$48*GETPIVOTDATA("StdDev of Orders Aggregated2",$S$72,"Quarters (Unique Date)",2,"Years (Unique Date)",2022) -> 13565.621 | X63: =GETPIVOTDATA("Average of Orders Aggregated",$S$72,"Quarters (Unique Date)",2,"Years (Unique Date)",2023)-$V$48*GETPIVOTDATA("StdDev of Orders Aggregated2",$S$72,"Quarters (Unique Date)",2,"Years (Unique Date)",2023) -> 3145.539 | Y63: =GETPIVOTDATA("Average of Orders Aggregated",$S$72,"Quarters (Unique Date)",2,"Years (Unique Date)",2023)+$V$48*GETPIVOTDATA("StdDev of Orders Aggregated2",$S$72,"Quarters (Unique Date)",2,"Years (Unique Date)",2023) -> 19414.307 | Z63: =GETPIVOTDATA("Average of Orders Aggregated",$S$72,"Quarters (Unique Date)",2,"Years (Unique Date)",2024)-$V$48*GETPIVOTDATA("StdDev of Orders Aggregated2",$S$72,"Quarters (Unique Date)",2,"Years (Unique Date)",2024) -> 6678.636 | AA63: =GETPIVOTDATA("Average of Orders Aggregated",$S$72,"Quarters (Unique Date)",2,"Years (Unique Date)",2024)+$V$48*GETPIVOTDATA("StdDev of Orders Aggregated2",$S$72,"Quarters (Unique Date)",2,"Years (Unique Date)",2024) -> 16335.302
B64: 45530.605 | C64: =INT(B64) -> 45530 | D64: 6276 | F64: =WORKDAY(F63,-1) -> 45478 | G64: =SUMIF(C:C, F64, D:D) -> 7414 | H64: =ROUNDUP(MONTH(Table3[[#This Row],[Date]])/3, 0) -> 3 | I64: {=(SUM(OFFSET(G64, -$M$4/2+1, 0, $M$4-1, 1)) + (INDIRECT("G" & ROW(G64) - $M$4/2) + INDIRECT("G" & ROW(G64) + $M$4/2))/2) / $M$4} -> 9639.8636 | J64: =Table5[[#This Row],[Moving Average on Months]] - 1.96*STDEV(OFFSET(Table5[[#This Row],[Combined Daily Order]], -$M$4/2, 0, $M$4+1, 1)) -> 5179.8624 | K64: =Table5[[#This Row],[Moving Average on Months]] + 1.96*STDEV(OFFSET(Table5[[#This Row],[Combined Daily Order]], -$M$4/2, 0, $M$4+1, 1)) -> 14099.865 | L64: #N/A | N64: =$W$48 -> 2594.4026 | O64: =$X$48 -> 23487.587 | S64: 3rd Quarter | T64: =GETPIVOTDATA("Average of Orders Aggregated",$S$72,"Quarters (Unique Date)",3,"Years (Unique Date)",2021)-$V$48*GETPIVOTDATA("StdDev of Orders Aggregated2",$S$72,"Quarters (Unique Date)",3,"Years (Unique Date)",2021) -> 6932.9989 | U64: =GETPIVOTDATA("Average of Orders Aggregated",S72,"Quarters (Unique Date)",3,"Years (Unique Date)",2021)+$V$48*GETPIVOTDATA("StdDev of Orders Aggregated2",S72,"Quarters (Unique Date)",3,"Years (Unique Date)",2021) -> 17104.001 | V64: =GETPIVOTDATA("Average of Orders Aggregated",$S$72,"Quarters (Unique Date)",3,"Years (Unique Date)",2022)-$V$48*GETPIVOTDATA("StdDev of Orders Aggregated2",$S$72,"Quarters (Unique Date)",3,"Years (Unique Date)",2022) -> 4679.7935 | W64: =GETPIVOTDATA("Average of Orders Aggregated",$S$72,"Quarters (Unique Date)",3,"Years (Unique Date)",2022)+$V$48*GETPIVOTDATA("StdDev of Orders Aggregated2",$S$72,"Quarters (Unique Date)",3,"Years (Unique Date)",2022) -> 18041.964 | X64: =GETPIVOTDATA("Average of Orders Aggregated",$S$72,"Quarters (Unique Date)",3,"Years (Unique Date)",2023)-$V$48*GETPIVOTDATA("StdDev of Orders Aggregated2",$S$72,"Quarters (Unique Date)",3,"Years (Unique Date)",2023) -> 5357.6613 | Y64: =GETPIVOTDATA("Average of Orders Aggregated",$S$72,"Quarters (Unique Date)",3,"Years (Unique Date)",2023)+$V$48*GETPIVOTDATA("StdDev of Orders Aggregated2",$S$72,"Quarters (Unique Date)",3,"Years (Unique Date)",2023) -> 18079.293 | Z64: =GETPIVOTDATA("Average of Orders Aggregated",$S$72,"Quarters (Unique Date)",3,"Years (Unique Date)",2024)- $V$48*GETPIVOTDATA("StdDev of Orders Aggregated2",$S$72,"Quarters (Unique Date)",3,"Years (Unique Date)",2024) -> 5370.7977 | AA64: =GETPIVOTDATA("Average of Orders Aggregated",$S$72,"Quarters (Unique Date)",3,"Years (Unique Date)",2024) + $V$48*GETPIVOTDATA("StdDev of Orders Aggregated2",$S$72,"Quarters (Unique Date)",3,"Years (Unique Date)",2024) -> 19575.202
B65: 45530.203 | C65: =INT(B65) -> 45530 | D65: 5114 | F65: =WORKDAY(F64,-1) -> 45477 | G65: =SUMIF(C:C, F65, D:D) -> 11192 | H65: =ROUNDUP(MONTH(Table3[[#This Row],[Date]])/3, 0) -> 3 | I65: {=(SUM(OFFSET(G65, -$M$4/2+1, 0, $M$4-1, 1)) + (INDIRECT("G" & ROW(G65) - $M$4/2) + INDIRECT("G" & ROW(G65) + $M$4/2))/2) / $M$4} -> 9679.7727 | J65: =Table5[[#This Row],[Moving Average on Months]] - 1.96*STDEV(OFFSET(Table5[[#This Row],[Combined Daily Order]], -$M$4/2, 0, $M$4+1, 1)) -> 5213.6112 | K65: =Table5[[#This Row],[Moving Average on Months]] + 1.96*STDEV(OFFSET(Table5[[#This Row],[Combined Daily Order]], -$M$4/2, 0, $M$4+1, 1)) -> 14145.934 | L65: #N/A | N65: =$W$48 -> 2594.4026 | O65: =$X$48 -> 23487.587 | S65: 4th Quarter | T65: =GETPIVOTDATA("Average of Orders Aggregated",$S$72,"Quarters (Unique Date)",4,"Years (Unique Date)",2021)-$V$48*GETPIVOTDATA("StdDev of Orders Aggregated2",$S$72,"Quarters (Unique Date)",4,"Years (Unique Date)",2021) -> 7512.1554 | U65: =GETPIVOTDATA("Average of Orders Aggregated",$S$72,"Quarters (Unique Date)",4,"Years (Unique Date)",2021)+$V$48*GETPIVOTDATA("StdDev of Orders Aggregated2",$S$72,"Quarters (Unique Date)",4,"Years (Unique Date)",2021) -> 27296.693 | V65: =GETPIVOTDATA("Average of Orders Aggregated",$S$72,"Quarters (Unique Date)",4,"Years (Unique Date)",2022)-$V$48*GETPIVOTDATA("StdDev of Orders Aggregated2",$S$72,"Quarters (Unique Date)",4,"Years (Unique Date)",2022) -> 8121.3381 | W65: =GETPIVOTDATA("Average of Orders Aggregated",$S$72,"Quarters (Unique Date)",4,"Years (Unique Date)",2022)+$V$48*GETPIVOTDATA("StdDev of Orders Aggregated2",$S$72,"Quarters (Unique Date)",4,"Years (Unique Date)",2022) -> 30740.385 | X65: =GETPIVOTDATA("Average of Orders Aggregated",$S$72,"Quarters (Unique Date)",4,"Years (Unique Date)",2023)-$V$48*GETPIVOTDATA("StdDev of Orders Aggregated2",$S$72,"Quarters (Unique Date)",4,"Years (Unique Date)",2023) -> 7996.788 | Y65: =GETPIVOTDATA("Average of Orders Aggregated",$S$72,"Quarters (Unique Date)",4,"Years (Unique Date)",2023)+$V$48*GETPIVOTDATA("StdDev of Orders Aggregated2",$S$72,"Quarters (Unique Date)",4,"Years (Unique Date)",2023) -> 33046.104
B66: 45527.748 | C66: =INT(B66) -> 45527 | D66: 5818 | F66: =WORKDAY(F65,-1) -> 45476 | G66: =SUMIF(C:C, F66, D:D) -> 7397 | H66: =ROUNDUP(MONTH(Table3[[#This Row],[Date]])/3, 0) -> 3 | I66: {=(SUM(OFFSET(G66, -$M$4/2+1, 0, $M$4-1, 1)) + (INDIRECT("G" & ROW(G66) - $M$4/2) + INDIRECT("G" & ROW(G66) + $M$4/2))/2) / $M$4} -> 9629.8409 | J66: =Table5[[#This Row],[Moving Average on Months]] - 1.96*STDEV(OFFSET(Table5[[#This Row],[Combined Daily Order]], -$M$4/2, 0, $M$4+1, 1)) -> 5220.2899 | K66: =Table5[[#This Row],[Moving Average on Months]] + 1.96*STDEV(OFFSET(Table5[[#This Row],[Combined Daily Order]], -$M$4/2, 0, $M$4+1, 1)) -> 14039.392 | L66: #N/A | N66: =$W$48 -> 2594.4026 | O66: =$X$48 -> 23487.587
B67: 45527.352 | C67: =INT(B67) -> 45527 | D67: 6371 | F67: =WORKDAY(F66,-1) -> 45475 | G67: =SUMIF(C:C, F67, D:D) -> 10799 | H67: =ROUNDUP(MONTH(Table3[[#This Row],[Date]])/3, 0) -> 3 | I67: {=(SUM(OFFSET(G67, -$M$4/2+1, 0, $M$4-1, 1)) + (INDIRECT("G" & ROW(G67) - $M$4/2) + INDIRECT("G" & ROW(G67) + $M$4/2))/2) / $M$4} -> 9719.7955 | J67: =Table5[[#This Row],[Moving Average on Months]] - 1.96*STDEV(OFFSET(Table5[[#This Row],[Combined Daily Order]], -$M$4/2, 0, $M$4+1, 1)) -> 5153.3788 | K67: =Table5[[#This Row],[Moving Average on Months]] + 1.96*STDEV(OFFSET(Table5[[#This Row],[Combined Daily Order]], -$M$4/2, 0, $M$4+1, 1)) -> 14286.212 | L67: #N/A | N67: =$W$48 -> 2594.4026 | O67: =$X$48 -> 23487.587
B68: 45526.941 | C68: =INT(B68) -> 45526 | D68: 6223 | F68: =WORKDAY(F67,-1) -> 45474 | G68: =SUMIF(C:C, F68, D:D) -> 7780 | H68: =ROUNDUP(MONTH(Table3[[#This Row],[Date]])/3, 0) -> 3 | I68: {=(SUM(OFFSET(G68, -$M$4/2+1, 0, $M$4-1, 1)) + (INDIRECT("G" & ROW(G68) - $M$4/2) + INDIRECT("G" & ROW(G68) + $M$4/2))/2) / $M$4} -> 9895.7955 | J68: =Table5[[#This Row],[Moving Average on Months]] - 1.96*STDEV(OFFSET(Table5[[#This Row],[Combined Daily Order]], -$M$4/2, 0, $M$4+1, 1)) -> 5454.7961 | K68: =Table5[[#This Row],[Moving Average on Months]] + 1.96*STDEV(OFFSET(Table5[[#This Row],[Combined Daily Order]], -$M$4/2, 0, $M$4+1, 1)) -> 14336.795 | L68: #N/A | N68: =$W$48 -> 2594.4026 | O68: =$X$48 -> 23487.587
B69: 45526.535 | C69: =INT(B69) -> 45526 | D69: 4854 | F69: =WORKDAY(F68,-1) -> 45471 | G69: =SUMIF(C:C, F69, D:D) -> 12079 | H69: =ROUNDUP(MONTH(Table3[[#This Row],[Date]])/3, 0) -> 2 | I69: {=(SUM(OFFSET(G69, -$M$4/2+1, 0, $M$4-1, 1)) + (INDIRECT("G" & ROW(G69) - $M$4/2) + INDIRECT("G" & ROW(G69) + $M$4/2))/2) / $M$4} -> 9975.5909 | J69: =Table5[[#This Row],[Moving Average on Months]] - 1.96*STDEV(OFFSET(Table5[[#This Row],[Combined Daily Order]], -$M$4/2, 0, $M$4+1, 1)) -> 5529.3195 | K69: =Table5[[#This Row],[Moving Average on Months]] + 1.96*STDEV(OFFSET(Table5[[#This Row],[Combined Daily Order]], -$M$4/2, 0, $M$4+1, 1)) -> 14421.862 | L69: #N/A | N69: =$W$48 -> 2594.4026 | O69: =$X$48 -> 23487.587
B70: 45526.134 | C70: =INT(B70) -> 45526 | D70: 5386 | F70: =WORKDAY(F69,-1) -> 45470 | G70: =SUMIF(C:C, F70, D:D) -> 8424 | H70: =ROUNDUP(MONTH(Table3[[#This Row],[Date]])/3, 0) -> 2 | I70: {=(SUM(OFFSET(G70, -$M$4/2+1, 0, $M$4-1, 1)) + (INDIRECT("G" & ROW(G70) - $M$4/2) + INDIRECT("G" & ROW(G70) + $M$4/2))/2) / $M$4} -> 10088.636 | J70: =Table5[[#This Row],[Moving Average on Months]] - 1.96*STDEV(OFFSET(Table5[[#This Row],[Combined Daily Order]], -$M$4/2, 0, $M$4+1, 1)) -> 5523.2743 | K70: =Table5[[#This Row],[Moving Average on Months]] + 1.96*STDEV(OFFSET(Table5[[#This Row],[Combined Daily Order]], -$M$4/2, 0, $M$4+1, 1)) -> 14653.998 | L70: #N/A | N70: =$W$48 -> 2594.4026 | O70: =$X$48 -> 23487.587
B71: 45525.762 | C71: =INT(B71) -> 45525 | D71: 6218 | F71: =WORKDAY(F70,-1) -> 45469 | G71: =SUMIF(C:C, F71, D:D) -> 11926 | H71: =ROUNDUP(MONTH(Table3[[#This Row],[Date]])/3, 0) -> 2 | I71: {=(SUM(OFFSET(G71, -$M$4/2+1, 0, $M$4-1, 1)) + (INDIRECT("G" & ROW(G71) - $M$4/2) + INDIRECT("G" & ROW(G71) + $M$4/2))/2) / $M$4} -> 10202.614 | J71: =Table5[[#This Row],[Moving Average on Months]] - 1.96*STDEV(OFFSET(Table5[[#This Row],[Combined Daily Order]], -$M$4/2, 0, $M$4+1, 1)) -> 5576.4528 | K71: =Table5[[#This Row],[Moving Average on Months]] + 1.96*STDEV(OFFSET(Table5[[#This Row],[Combined Daily Order]], -$M$4/2, 0, $M$4+1, 1)) -> 14828.775 | L71: #N/A | N71: =$W$48 -> 2594.4026 | O71: =$X$48 -> 23487.587
B72: 45525.346 | C72: =INT(B72) -> 45525 | D72: 4970 | F72: =WORKDAY(F71,-1) -> 45468 | G72: =SUMIF(C:C, F72, D:D) -> 8050 | H72: =ROUNDUP(MONTH(Table3[[#This Row],[Date]])/3, 0) -> 2 | I72: {=(SUM(OFFSET(G72, -$M$4/2+1, 0, $M$4-1, 1)) + (INDIRECT("G" & ROW(G72) - $M$4/2) + INDIRECT("G" & ROW(G72) + $M$4/2))/2) / $M$4} -> 10184.045 | J72: =Table5[[#This Row],[Moving Average on Months]] - 1.96*STDEV(OFFSET(Table5[[#This Row],[Combined Daily Order]], -$M$4/2, 0, $M$4+1, 1)) -> 5803.4292 | K72: =Table5[[#This Row],[Moving Average on Months]] + 1.96*STDEV(OFFSET(Table5[[#This Row],[Combined Daily Order]], -$M$4/2, 0, $M$4+1, 1)) -> 14564.662 | L72: #N/A | N72: =$W$48 -> 2594.4026 | O72: =$X$48 -> 23487.587 | T72: Column Labels
B73: 45524.974 | C73: =INT(B73) -> 45524 | D73: 5727 | F73: =WORKDAY(F72,-1) -> 45467 | G73: =SUMIF(C:C, F73, D:D) -> 12825 | H73: =ROUNDUP(MONTH(Table3[[#This Row],[Date]])/3, 0) -> 2 | I73: {=(SUM(OFFSET(G73, -$M$4/2+1, 0, $M$4-1, 1)) + (INDIRECT("G" & ROW(G73) - $M$4/2) + INDIRECT("G" & ROW(G73) + $M$4/2))/2) / $M$4} -> 10277.023 | J73: =Table5[[#This Row],[Moving Average on Months]] - 1.96*STDEV(OFFSET(Table5[[#This Row],[Combined Daily Order]], -$M$4/2, 0, $M$4+1, 1)) -> 5722.4832 | K73: =Table5[[#This Row],[Moving Average on Months]] + 1.96*STDEV(OFFSET(Table5[[#This Row],[Combined Daily Order]], -$M$4/2, 0, $M$4+1, 1)) -> 14831.562 | L73: #N/A | N73: =$W$48 -> 2594.4026 | O73: =$X$48 -> 23487.587 | T73: 2021 | V73: 2022 | X73: 2023 | Z73: 2024 | AB73: Total Average of Orders Aggregated | AC73: Total StdDev of Orders Aggregated2
B74: 45524.596 | C74: =INT(B74) -> 45524 | D74: 6210 | F74: =WORKDAY(F73,-1) -> 45464 | G74: =SUMIF(C:C, F74, D:D) -> 12226 | H74: =ROUNDUP(MONTH(Table3[[#This Row],[Date]])/3, 0) -> 2 | I74: {=(SUM(OFFSET(G74, -$M$4/2+1, 0, $M$4-1, 1)) + (INDIRECT("G" & ROW(G74) - $M$4/2) + INDIRECT("G" & ROW(G74) + $M$4/2))/2) / $M$4} -> 10476.614 | J74: =Table5[[#This Row],[Moving Average on Months]] - 1.96*STDEV(OFFSET(Table5[[#This Row],[Combined Daily Order]], -$M$4/2, 0, $M$4+1, 1)) -> 6019.3076 | K74: =Table5[[#This Row],[Moving Average on Months]] + 1.96*STDEV(OFFSET(Table5[[#This Row],[Combined Daily Order]], -$M$4/2, 0, $M$4+1, 1)) -> 14933.92 | L74: #N/A | N74: =$W$48 -> 2594.4026 | O74: =$X$48 -> 23487.587 | S74: Row Labels | T74: Average of Orders Aggregated | U74: StdDev of Orders Aggregated2 | V74: Average of Orders Aggregated | W74: StdDev of Orders Aggregated2 | X74: Average of Orders Aggregated | Y74: StdDev of Orders Aggregated2 | Z74: Average of Orders Aggregated | AA74: StdDev of Orders Aggregated2
B75: 45524.193 | C75: =INT(B75) -> 45524 | D75: 4995 | F75: =WORKDAY(F74,-1) -> 45463 | G75: =SUMIF(C:C, F75, D:D) -> 13483 | H75: =ROUNDUP(MONTH(Table3[[#This Row],[Date]])/3, 0) -> 2 | I75: {=(SUM(OFFSET(G75, -$M$4/2+1, 0, $M$4-1, 1)) + (INDIRECT("G" & ROW(G75) - $M$4/2) + INDIRECT("G" & ROW(G75) + $M$4/2))/2) / $M$4} -> 10548.182 | J75: =Table5[[#This Row],[Moving Average on Months]] - 1.96*STDEV(OFFSET(Table5[[#This Row],[Combined Daily Order]], -$M$4/2, 0, $M$4+1, 1)) -> 6035.5908 | K75: =Table5[[#This Row],[Moving Average on Months]] + 1.96*STDEV(OFFSET(Table5[[#This Row],[Combined Daily Order]], -$M$4/2, 0, $M$4+1, 1)) -> 15060.773 | L75: #N/A | N75: =$W$48 -> 2594.4026 | O75: =$X$48 -> 23487.587 | S75: Qtr1 | V75: 9863.9531 | W75: 2570.6564 | X75: 10533.277 | Y75: 3082.3372 | Z75: 11411.169 | AA75: 3387.9735 | AB75: 10606.608 | AC75: 3084.9052
B76: 45523.772 | C76: =INT(B76) -> 45523 | D76: 5856 | F76: =WORKDAY(F75,-1) -> 45462 | G76: =SUMIF(C:C, F76, D:D) -> 7606 | H76: =ROUNDUP(MONTH(Table3[[#This Row],[Date]])/3, 0) -> 2 | I76: {=(SUM(OFFSET(G76, -$M$4/2+1, 0, $M$4-1, 1)) + (INDIRECT("G" & ROW(G76) - $M$4/2) + INDIRECT("G" & ROW(G76) + $M$4/2))/2) / $M$4} -> 10530.591 | J76: =Table5[[#This Row],[Moving Average on Months]] - 1.96*STDEV(OFFSET(Table5[[#This Row],[Combined Daily Order]], -$M$4/2, 0, $M$4+1, 1)) -> 6172.1807 | K76: =Table5[[#This Row],[Moving Average on Months]] + 1.96*STDEV(OFFSET(Table5[[#This Row],[Combined Daily Order]], -$M$4/2, 0, $M$4+1, 1)) -> 14889.001 | L76: #N/A | N76: =$W$48 -> 2594.4026 | O76: =$X$48 -> 23487.587 | S76: Qtr2 | V76: 9243.4769 | W76: 2205.1755 | X76: 11279.923 | Y76: 4150.196 | Z76: 11506.969 | AA76: 2463.4353 | AB76: 10676.79 | AC76: 3213.9564
B77: 45523.358 | C77: =INT(B77) -> 45523 | D77: 5874 | F77: =WORKDAY(F76,-1) -> 45461 | G77: =SUMIF(C:C, F77, D:D) -> 8642 | H77: =ROUNDUP(MONTH(Table3[[#This Row],[Date]])/3, 0) -> 2 | I77: {=(SUM(OFFSET(G77, -$M$4/2+1, 0, $M$4-1, 1)) + (INDIRECT("G" & ROW(G77) - $M$4/2) + INDIRECT("G" & ROW(G77) + $M$4/2))/2) / $M$4} -> 10654.659 | J77: =Table5[[#This Row],[Moving Average on Months]] - 1.96*STDEV(OFFSET(Table5[[#This Row],[Combined Daily Order]], -$M$4/2, 0, $M$4+1, 1)) -> 5959.5565 | K77: =Table5[[#This Row],[Moving Average on Months]] + 1.96*STDEV(OFFSET(Table5[[#This Row],[Combined Daily Order]], -$M$4/2, 0, $M$4+1, 1)) -> 15349.762 | L77: #N/A | N77: =$W$48 -> 2594.4026 | O77: =$X$48 -> 23487.587 | S77: Qtr3 | T77: 12018.5 | U77: 2594.6434 | V77: 11360.879 | W77: 3408.717 | X77: 11718.477 | Y77: 3245.3141 | Z77: 12473 | AA77: 3623.5726 | AB77: 11865.463 | AC77: 3362.6702
B78: 45520.964 | C78: =INT(B78) -> 45520 | D78: 4733 | F78: =WORKDAY(F77,-1) -> 45460 | G78: =SUMIF(C:C, F78, D:D) -> 12725 | H78: =ROUNDUP(MONTH(Table3[[#This Row],[Date]])/3, 0) -> 2 | I78: {=(SUM(OFFSET(G78, -$M$4/2+1, 0, $M$4-1, 1)) + (INDIRECT("G" & ROW(G78) - $M$4/2) + INDIRECT("G" & ROW(G78) + $M$4/2))/2) / $M$4} -> 10904.159 | J78: =Table5[[#This Row],[Moving Average on Months]] - 1.96*STDEV(OFFSET(Table5[[#This Row],[Combined Daily Order]], -$M$4/2, 0, $M$4+1, 1)) -> 6195.6471 | K78: =Table5[[#This Row],[Moving Average on Months]] + 1.96*STDEV(OFFSET(Table5[[#This Row],[Combined Daily Order]], -$M$4/2, 0, $M$4+1, 1)) -> 15612.671 | L78: #N/A | N78: =$W$48 -> 2594.4026 | O78: =$X$48 -> 23487.587 | S78: Qtr4 | T78: 17404.424 | U78: 5047.076 | V78: 19430.862 | W78: 5770.165 | X78: 20521.446 | Y78: 6390.1317 | AB78: 19110.163 | AC78: 5873.9537
B79: 45520.556 | C79: =INT(B79) -> 45520 | D79: 6107 | F79: =WORKDAY(F78,-1) -> 45457 | G79: =SUMIF(C:C, F79, D:D) -> 11785 | H79: =ROUNDUP(MONTH(Table3[[#This Row],[Date]])/3, 0) -> 2 | I79: {=(SUM(OFFSET(G79, -$M$4/2+1, 0, $M$4-1, 1)) + (INDIRECT("G" & ROW(G79) - $M$4/2) + INDIRECT("G" & ROW(G79) + $M$4/2))/2) / $M$4} -> 11019.705 | J79: =Table5[[#This Row],[Moving Average on Months]] - 1.96*STDEV(OFFSET(Table5[[#This Row],[Combined Daily Order]], -$M$4/2, 0, $M$4+1, 1)) -> 6262.0009 | K79: =Table5[[#This Row],[Moving Average on Months]] + 1.96*STDEV(OFFSET(Table5[[#This Row],[Combined Daily Order]], -$M$4/2, 0, $M$4+1, 1)) -> 15777.408 | L79: #N/A | N79: =$W$48 -> 2594.4026 | O79: =$X$48 -> 23487.587 | S79: Grand Total | T79: 16057.943 | U79: 5114.4983 | V79: 12480.55 | W79: 5542.2715 | X79: 13513.281 | Y79: 5992.6179 | Z79: 11797.046 | AA79: 3217.3702 | AB79: 13040.995 | AC79: 5329.8941
B80: 45520.161 | C80: =INT(B80) -> 45520 | D80: 6045 | F80: =WORKDAY(F79,-1) -> 45456 | G80: =SUMIF(C:C, F80, D:D) -> 9363 | H80: =ROUNDUP(MONTH(Table3[[#This Row],[Date]])/3, 0) -> 2 | I80: {=(SUM(OFFSET(G80, -$M$4/2+1, 0, $M$4-1, 1)) + (INDIRECT("G" & ROW(G80) - $M$4/2) + INDIRECT("G" & ROW(G80) + $M$4/2))/2) / $M$4} -> 11094.864 | J80: =Table5[[#This Row],[Moving Average on Months]] - 1.96*STDEV(OFFSET(Table5[[#This Row],[Combined Daily Order]], -$M$4/2, 0, $M$4+1, 1)) -> 6387.3505 | K80: =Table5[[#This Row],[Moving Average on Months]] + 1.96*STDEV(OFFSET(Table5[[#This Row],[Combined Daily Order]], -$M$4/2, 0, $M$4+1, 1)) -> 15802.377 | L80: #N/A | N80: =$W$48 -> 2594.4026 | O80: =$X$48 -> 23487.587
B81: 45519.748 | C81: =INT(B81) -> 45519 | D81: 4808 | F81: =WORKDAY(F80,-1) -> 45455 | G81: =SUMIF(C:C, F81, D:D) -> 13596 | H81: =ROUNDUP(MONTH(Table3[[#This Row],[Date]])/3, 0) -> 2 | I81: {=(SUM(OFFSET(G81, -$M$4/2+1, 0, $M$4-1, 1)) + (INDIRECT("G" & ROW(G81) - $M$4/2) + INDIRECT("G" & ROW(G81) + $M$4/2))/2) / $M$4} -> 11147.295 | J81: =Table5[[#This Row],[Moving Average on Months]] - 1.96*STDEV(OFFSET(Table5[[#This Row],[Combined Daily Order]], -$M$4/2, 0, $M$4+1, 1)) -> 6371.2754 | K81: =Table5[[#This Row],[Moving Average on Months]] + 1.96*STDEV(OFFSET(Table5[[#This Row],[Combined Daily Order]], -$M$4/2, 0, $M$4+1, 1)) -> 15923.315 | L81: #N/A | N81: =$W$48 -> 2594.4026 | O81: =$X$48 -> 23487.587
B82: 45519.376 | C82: =INT(B82) -> 45519 | D82: 5441 | F82: =WORKDAY(F81,-1) -> 45454 | G82: =SUMIF(C:C, F82, D:D) -> 8300 | H82: =ROUNDUP(MONTH(Table3[[#This Row],[Date]])/3, 0) -> 2 | I82: {=(SUM(OFFSET(G82, -$M$4/2+1, 0, $M$4-1, 1)) + (INDIRECT("G" & ROW(G82) - $M$4/2) + INDIRECT("G" & ROW(G82) + $M$4/2))/2) / $M$4} -> 11216 | J82: =Table5[[#This Row],[Moving Average on Months]] - 1.96*STDEV(OFFSET(Table5[[#This Row],[Combined Daily Order]], -$M$4/2, 0, $M$4+1, 1)) -> 6384.7419 | K82: =Table5[[#This Row],[Moving Average on Months]] + 1.96*STDEV(OFFSET(Table5[[#This Row],[Combined Daily Order]], -$M$4/2, 0, $M$4+1, 1)) -> 16047.258 | L82: #N/A | N82: =$W$48 -> 2594.4026 | O82: =$X$48 -> 23487.587
B83: 45518.969 | C83: =INT(B83) -> 45518 | D83: 5852 | F83: =WORKDAY(F82,-1) -> 45453 | G83: =SUMIF(C:C, F83, D:D) -> 8967 | H83: =ROUNDUP(MONTH(Table3[[#This Row],[Date]])/3, 0) -> 2 | I83: {=(SUM(OFFSET(G83, -$M$4/2+1, 0, $M$4-1, 1)) + (INDIRECT("G" & ROW(G83) - $M$4/2) + INDIRECT("G" & ROW(G83) + $M$4/2))/2) / $M$4} -> 11287.955 | J83: =Table5[[#This Row],[Moving Average on Months]] - 1.96*STDEV(OFFSET(Table5[[#This Row],[Combined Daily Order]], -$M$4/2, 0, $M$4+1, 1)) -> 6352.3755 | K83: =Table5[[#This Row],[Moving Average on Months]] + 1.96*STDEV(OFFSET(Table5[[#This Row],[Combined Daily Order]], -$M$4/2, 0, $M$4+1, 1)) -> 16223.534 | L83: #N/A | N83: =$W$48 -> 2594.4026 | O83: =$X$48 -> 23487.587
B84: 45518.578 | C84: =INT(B84) -> 45518 | D84: 5152 | F84: =WORKDAY(F83,-1) -> 45450 | G84: =SUMIF(C:C, F84, D:D) -> 13554 | H84: =ROUNDUP(MONTH(Table3[[#This Row],[Date]])/3, 0) -> 2 | I84: {=(SUM(OFFSET(G84, -$M$4/2+1, 0, $M$4-1, 1)) + (INDIRECT("G" & ROW(G84) - $M$4/2) + INDIRECT("G" & ROW(G84) + $M$4/2))/2) / $M$4} -> 11319.25 | J84: =Table5[[#This Row],[Moving Average on Months]] - 1.96*STDEV(OFFSET(Table5[[#This Row],[Combined Daily Order]], -$M$4/2, 0, $M$4+1, 1)) -> 6479.4599 | K84: =Table5[[#This Row],[Moving Average on Months]] + 1.96*STDEV(OFFSET(Table5[[#This Row],[Combined Daily Order]], -$M$4/2, 0, $M$4+1, 1)) -> 16159.04 | L84: #N/A | N84: =$W$48 -> 2594.4026 | O84: =$X$48 -> 23487.587
B85: 45518.187 | C85: =INT(B85) -> 45518 | D85: 4804 | F85: =WORKDAY(F84,-1) -> 45449 | G85: =SUMIF(C:C, F85, D:D) -> 13334 | H85: =ROUNDUP(MONTH(Table3[[#This Row],[Date]])/3, 0) -> 2 | I85: {=(SUM(OFFSET(G85, -$M$4/2+1, 0, $M$4-1, 1)) + (INDIRECT("G" & ROW(G85) - $M$4/2) + INDIRECT("G" & ROW(G85) + $M$4/2))/2) / $M$4} -> 11275.864 | J85: =Table5[[#This Row],[Moving Average on Months]] - 1.96*STDEV(OFFSET(Table5[[#This Row],[Combined Daily Order]], -$M$4/2, 0, $M$4+1, 1)) -> 6422.895 | K85: =Table5[[#This Row],[Moving Average on Months]] + 1.96*STDEV(OFFSET(Table5[[#This Row],[Combined Daily Order]], -$M$4/2, 0, $M$4+1, 1)) -> 16128.832 | L85: #N/A | N85: =$W$48 -> 2594.4026 | O85: =$X$48 -> 23487.587
B86: 45517.804 | C86: =INT(B86) -> 45517 | D86: 5062 | F86: =WORKDAY(F85,-1) -> 45448 | G86: =SUMIF(C:C, F86, D:D) -> 8600 | H86: =ROUNDUP(MONTH(Table3[[#This Row],[Date]])/3, 0) -> 2 | I86: {=(SUM(OFFSET(G86, -$M$4/2+1, 0, $M$4-1, 1)) + (INDIRECT("G" & ROW(G86) - $M$4/2) + INDIRECT("G" & ROW(G86) + $M$4/2))/2) / $M$4} -> 11266.568 | J86: =Table5[[#This Row],[Moving Average on Months]] - 1.96*STDEV(OFFSET(Table5[[#This Row],[Combined Daily Order]], -$M$4/2, 0, $M$4+1, 1)) -> 6096.7716 | K86: =Table5[[#This Row],[Moving Average on Months]] + 1.96*STDEV(OFFSET(Table5[[#This Row],[Combined Daily Order]], -$M$4/2, 0, $M$4+1, 1)) -> 16436.365 | L86: #N/A | N86: =$W$48 -> 2594.4026 | O86: =$X$48 -> 23487.587
B87: 45517.405 | C87: =INT(B87) -> 45517 | D87: 3675 | F87: =WORKDAY(F86,-1) -> 45447 | G87: =SUMIF(C:C, F87, D:D) -> 9232 | H87: =ROUNDUP(MONTH(Table3[[#This Row],[Date]])/3, 0) -> 2 | I87: {=(SUM(OFFSET(G87, -$M$4/2+1, 0, $M$4-1, 1)) + (INDIRECT("G" & ROW(G87) - $M$4/2) + INDIRECT("G" & ROW(G87) + $M$4/2))/2) / $M$4} -> 11356.432 | J87: =Table5[[#This Row],[Moving Average on Months]] - 1.96*STDEV(OFFSET(Table5[[#This Row],[Combined Daily Order]], -$M$4/2, 0, $M$4+1, 1)) -> 6200.0326 | K87: =Table5[[#This Row],[Moving Average on Months]] + 1.96*STDEV(OFFSET(Table5[[#This Row],[Combined Daily Order]], -$M$4/2, 0, $M$4+1, 1)) -> 16512.831 | L87: #N/A | N87: =$W$48 -> 2594.4026 | O87: =$X$48 -> 23487.587
B88: 45517.022 | C88: =INT(B88) -> 45517 | D88: 5342 | F88: =WORKDAY(F87,-1) -> 45446 | G88: =SUMIF(C:C, F88, D:D) -> 14816 | H88: =ROUNDUP(MONTH(Table3[[#This Row],[Date]])/3, 0) -> 2 | I88: {=(SUM(OFFSET(G88, -$M$4/2+1, 0, $M$4-1, 1)) + (INDIRECT("G" & ROW(G88) - $M$4/2) + INDIRECT("G" & ROW(G88) + $M$4/2))/2) / $M$4} -> 11527.75 | J88: =Table5[[#This Row],[Moving Average on Months]] - 1.96*STDEV(OFFSET(Table5[[#This Row],[Combined Daily Order]], -$M$4/2, 0, $M$4+1, 1)) -> 6455.1137 | K88: =Table5[[#This Row],[Moving Average on Months]] + 1.96*STDEV(OFFSET(Table5[[#This Row],[Combined Daily Order]], -$M$4/2, 0, $M$4+1, 1)) -> 16600.386 | L88: #N/A | N88: =$W$48 -> 2594.4026 | O88: =$X$48 -> 23487.587
B89: 45516.634 | C89: =INT(B89) -> 45516 | D89: 5675 | F89: =WORKDAY(F88,-1) -> 45443 | G89: =SUMIF(C:C, F89, D:D) -> 14358 | H89: =ROUNDUP(MONTH(Table3[[#This Row],[Date]])/3, 0) -> 2 | I89: {=(SUM(OFFSET(G89, -$M$4/2+1, 0, $M$4-1, 1)) + (INDIRECT("G" & ROW(G89) - $M$4/2) + INDIRECT("G" & ROW(G89) + $M$4/2))/2) / $M$4} -> 11618.636 | J89: =Table5[[#This Row],[Moving Average on Months]] - 1.96*STDEV(OFFSET(Table5[[#This Row],[Combined Daily Order]], -$M$4/2, 0, $M$4+1, 1)) -> 6689.1813 | K89: =Table5[[#This Row],[Moving Average on Months]] + 1.96*STDEV(OFFSET(Table5[[#This Row],[Combined Daily Order]], -$M$4/2, 0, $M$4+1, 1)) -> 16548.091 | L89: #N/A | N89: =$W$48 -> 2594.4026 | O89: =$X$48 -> 23487.587
B90: 45516.235 | C90: =INT(B90) -> 45516 | D90: 4679 | F90: =WORKDAY(F89,-1) -> 45442 | G90: =SUMIF(C:C, F90, D:D) -> 9305 | H90: =ROUNDUP(MONTH(Table3[[#This Row],[Date]])/3, 0) -> 2 | I90: {=(SUM(OFFSET(G90, -$M$4/2+1, 0, $M$4-1, 1)) + (INDIRECT("G" & ROW(G90) - $M$4/2) + INDIRECT("G" & ROW(G90) + $M$4/2))/2) / $M$4} -> 11674.341 | J90: =Table5[[#This Row],[Moving Average on Months]] - 1.96*STDEV(OFFSET(Table5[[#This Row],[Combined Daily Order]], -$M$4/2, 0, $M$4+1, 1)) -> 6440.7528 | K90: =Table5[[#This Row],[Moving Average on Months]] + 1.96*STDEV(OFFSET(Table5[[#This Row],[Combined Daily Order]], -$M$4/2, 0, $M$4+1, 1)) -> 16907.929 | L90: #N/A | N90: =$W$48 -> 2594.4026 | O90: =$X$48 -> 23487.587
B91: 45513.815 | C91: =INT(B91) -> 45513 | D91: 4858 | F91: =WORKDAY(F90,-1) -> 45441 | G91: =SUMIF(C:C, F91, D:D) -> 13861 | H91: =ROUNDUP(MONTH(Table3[[#This Row],[Date]])/3, 0) -> 2 | I91: {=(SUM(OFFSET(G91, -$M$4/2+1, 0, $M$4-1, 1)) + (INDIRECT("G" & ROW(G91) - $M$4/2) + INDIRECT("G" & ROW(G91) + $M$4/2))/2) / $M$4} -> 11782.955 | J91: =Table5[[#This Row],[Moving Average on Months]] - 1.96*STDEV(OFFSET(Table5[[#This Row],[Combined Daily Order]], -$M$4/2, 0, $M$4+1, 1)) -> 6493.6377 | K91: =Table5[[#This Row],[Moving Average on Months]] + 1.96*STDEV(OFFSET(Table5[[#This Row],[Combined Daily Order]], -$M$4/2, 0, $M$4+1, 1)) -> 17072.271 | L91: #N/A | N91: =$W$48 -> 2594.4026 | O91: =$X$48 -> 23487.587
... B193: 45457.431 | C193: =INT(B193) -> 45457 | D193: 4056 | F193: =WORKDAY(F192,-1) -> 45299 | G193: =SUMIF(C:C, F193, D:D) -> 10706 | H193: =ROUNDUP(MONTH(Table3[[#This Row],[Date]])/3, 0) -> 1 | I193: {=(SUM(OFFSET(G193, -$M$4/2+1, 0, $M$4-1, 1)) + (INDIRECT("G" & ROW(G193) - $M$4/2) + INDIRECT("G" & ROW(G193) + $M$4/2))/2) / $M$4} -> 15470.886 | J193: =Table5[[#This Row],[Moving Average on Months]] - 1.96*STDEV(OFFSET(Table5[[#This Row],[Combined Daily Order]], -$M$4/2, 0, $M$4+1, 1)) -> 2605.4929 | K193: =Table5[[#This Row],[Moving Average on Months]] + 1.96*STDEV(OFFSET(Table5[[#This Row],[Combined Daily Order]], -$M$4/2, 0, $M$4+1, 1)) -> 28336.28 | L193: #N/A | N193: =$W$48 -> 2594.4026 | O193: =$X$48 -> 23487.587
B194: 45457.05 | C194: =INT(B194) -> 45457 | D194: 3938 | F194: =WORKDAY(F193,-1) -> 45296 | G194: =SUMIF(C:C, F194, D:D) -> 20229 | H194: =ROUNDUP(MONTH(Table3[[#This Row],[Date]])/3, 0) -> 1 | I194: {=(SUM(OFFSET(G194, -$M$4/2+1, 0, $M$4-1, 1)) + (INDIRECT("G" & ROW(G194) - $M$4/2) + INDIRECT("G" & ROW(G194) + $M$4/2))/2) / $M$4} -> 16157.659 | J194: =Table5[[#This Row],[Moving Average on Months]] - 1.96*STDEV(OFFSET(Table5[[#This Row],[Combined Daily Order]], -$M$4/2, 0, $M$4+1, 1)) -> 3306.8027 | K194: =Table5[[#This Row],[Moving Average on Months]] + 1.96*STDEV(OFFSET(Table5[[#This Row],[Combined Daily Order]], -$M$4/2, 0, $M$4+1, 1)) -> 29008.515 | L194: =Table5[[#This Row],[Combined Daily Order]] -> 20229 | N194: =$W$48 -> 2594.4026 | O194: =$X$48 -> 23487.587
B195: 45456.666 | C195: =INT(B195) -> 45456 | D195: 4623 | F195: =WORKDAY(F194,-1) -> 45295 | G195: =SUMIF(C:C, F195, D:D) -> 14168 | H195: =ROUNDUP(MONTH(Table3[[#This Row],[Date]])/3, 0) -> 1 | I195: {=(SUM(OFFSET(G195, -$M$4/2+1, 0, $M$4-1, 1)) + (INDIRECT("G" & ROW(G195) - $M$4/2) + INDIRECT("G" & ROW(G195) + $M$4/2))/2) / $M$4} -> 16883.409 | J195: =Table5[[#This Row],[Moving Average on Months]] - 1.96*STDEV(OFFSET(Table5[[#This Row],[Combined Daily Order]], -$M$4/2, 0, $M$4+1, 1)) -> 2867.9186 | K195: =Table5[[#This Row],[Moving Average on Months]] + 1.96*STDEV(OFFSET(Table5[[#This Row],[Combined Daily Order]], -$M$4/2, 0, $M$4+1, 1)) -> 30898.9 | L195: #N/A | N195: =$W$48 -> 2594.4026 | O195: =$X$48 -> 23487.587
B196: 45456.243 | C196: =INT(B196) -> 45456 | D196: 4740 | F196: =WORKDAY(F195,-1) -> 45294 | G196: =SUMIF(C:C, F196, D:D) -> 20801 | H196: =ROUNDUP(MONTH(Table3[[#This Row],[Date]])/3, 0) -> 1 | I196: {=(SUM(OFFSET(G196, -$M$4/2+1, 0, $M$4-1, 1)) + (INDIRECT("G" & ROW(G196) - $M$4/2) + INDIRECT("G" & ROW(G196) + $M$4/2))/2) / $M$4} -> 17681.568 | J196: =Table5[[#This Row],[Moving Average on Months]] - 1.96*STDEV(OFFSET(Table5[[#This Row],[Combined Daily Order]], -$M$4/2, 0, $M$4+1, 1)) -> 3702.4415 | K196: =Table5[[#This Row],[Moving Average on Months]] + 1.96*STDEV(OFFSET(Table5[[#This Row],[Combined Daily Order]], -$M$4/2, 0, $M$4+1, 1)) -> 31660.695 | L196: =Table5[[#This Row],[Combined Daily Order]] -> 20801 | N196: =$W$48 -> 2594.4026 | O196: =$X$48 -> 23487.587
B197: 45455.854 | C197: =INT(B197) -> 45455 | D197: 4097 | F197: =WORKDAY(F196,-1) -> 45293 | G197: =SUMIF(C:C, F197, D:D) -> 14383 | H197: =ROUNDUP(MONTH(Table3[[#This Row],[Date]])/3, 0) -> 1 | I197: {=(SUM(OFFSET(G197, -$M$4/2+1, 0, $M$4-1, 1)) + (INDIRECT("G" & ROW(G197) - $M$4/2) + INDIRECT("G" & ROW(G197) + $M$4/2))/2) / $M$4} -> 18435 | J197: =Table5[[#This Row],[Moving Average on Months]] - 1.96*STDEV(OFFSET(Table5[[#This Row],[Combined Daily Order]], -$M$4/2, 0, $M$4+1, 1)) -> 4137.444 | K197: =Table5[[#This Row],[Moving Average on Months]] + 1.96*STDEV(OFFSET(Table5[[#This Row],[Combined Daily Order]], -$M$4/2, 0, $M$4+1, 1)) -> 32732.556 | L197: #N/A | N197: =$W$48 -> 2594.4026 | O197: =$X$48 -> 23487.587
B198: 45455.459 | C198: =INT(B198) -> 45455 | D198: 4653 | F198: =WORKDAY(F197,-1) -> 45292 | G198: =SUMIF(C:C, F198, D:D) -> 23719 | H198: =ROUNDUP(MONTH(Table3[[#This Row],[Date]])/3, 0) -> 1 | I198: {=(SUM(OFFSET(G198, -$M$4/2+1, 0, $M$4-1, 1)) + (INDIRECT("G" & ROW(G198) - $M$4/2) + INDIRECT("G" & ROW(G198) + $M$4/2))/2) / $M$4} -> 19221.023 | J198: =Table5[[#This Row],[Moving Average on Months]] - 1.96*STDEV(OFFSET(Table5[[#This Row],[Combined Daily Order]], -$M$4/2, 0, $M$4+1, 1)) -> 5029.1725 | K198: =Table5[[#This Row],[Moving Average on Months]] + 1.96*STDEV(OFFSET(Table5[[#This Row],[Combined Daily Order]], -$M$4/2, 0, $M$4+1, 1)) -> 33412.873 | L198: =Table5[[#This Row],[Combined Daily Order]] -> 23719 | N198: =$W$48 -> 2594.4026 | O198: =$X$48 -> 23487.587
B199: 45455.042 | C199: =INT(B199) -> 45455 | D199: 4846 | F199: =WORKDAY(F198,-1) -> 45289 | G199: =SUMIF(C:C, F199, D:D) -> 17075 | H199: =ROUNDUP(MONTH(Table3[[#This Row],[Date]])/3, 0) -> 4 | I199: {=(SUM(OFFSET(G199, -$M$4/2+1, 0, $M$4-1, 1)) + (INDIRECT("G" & ROW(G199) - $M$4/2) + INDIRECT("G" & ROW(G199) + $M$4/2))/2) / $M$4} -> 20093 | J199: =Table5[[#This Row],[Moving Average on Months]] - 1.96*STDEV(OFFSET(Table5[[#This Row],[Combined Daily Order]], -$M$4/2, 0, $M$4+1, 1)) -> 5508.0489 | K199: =Table5[[#This Row],[Moving Average on Months]] + 1.96*STDEV(OFFSET(Table5[[#This Row],[Combined Daily Order]], -$M$4/2, 0, $M$4+1, 1)) -> 34677.951 | L199: #N/A | N199: =$W$48 -> 2594.4026 | O199: =$X$48 -> 23487.587
B200: 45454.615 | C200: =INT(B200) -> 45454 | D200: 3972 | F200: =WORKDAY(F199,-1) -> 45288 | G200: =SUMIF(C:C, F200, D:D) -> 24266 | H200: =ROUNDUP(MONTH(Table3[[#This Row],[Date]])/3, 0) -> 4 | I200: {=(SUM(OFFSET(G200, -$M$4/2+1, 0, $M$4-1, 1)) + (INDIRECT("G" & ROW(G200) - $M$4/2) + INDIRECT("G" & ROW(G200) + $M$4/2))/2) / $M$4} -> 20911.136 | J200: =Table5[[#This Row],[Moving Average on Months]] - 1.96*STDEV(OFFSET(Table5[[#This Row],[Combined Daily Order]], -$M$4/2, 0, $M$4+1, 1)) -> 6742.0311 | K200: =Table5[[#This Row],[Moving Average on Months]] + 1.96*STDEV(OFFSET(Table5[[#This Row],[Combined Daily Order]], -$M$4/2, 0, $M$4+1, 1)) -> 35080.242 | L200: #N/A | N200: =$W$48 -> 2594.4026 | O200: =$X$48 -> 23487.587
B201: 45454.189 | C201: =INT(B201) -> 45454 | D201: 4328 | F201: =WORKDAY(F200,-1) -> 45287 | G201: =SUMIF(C:C, F201, D:D) -> 18959 | H201: =ROUNDUP(MONTH(Table3[[#This Row],[Date]])/3, 0) -> 4 | I201: {=(SUM(OFFSET(G201, -$M$4/2+1, 0, $M$4-1, 1)) + (INDIRECT("G" & ROW(G201) - $M$4/2) + INDIRECT("G" & ROW(G201) + $M$4/2))/2) / $M$4} -> 21637.795 | J201: =Table5[[#This Row],[Moving Average on Months]] - 1.96*STDEV(OFFSET(Table5[[#This Row],[Combined Daily Order]], -$M$4/2, 0, $M$4+1, 1)) -> 7598.8063 | K201: =Table5[[#This Row],[Moving Average on Months]] + 1.96*STDEV(OFFSET(Table5[[#This Row],[Combined Daily Order]], -$M$4/2, 0, $M$4+1, 1)) -> 35676.785 | L201: #N/A | N201: =$W$48 -> 2594.4026 | O201: =$X$48 -> 23487.587
B202: 45453.767 | C202: =INT(B202) -> 45453 | D202: 4597 | F202: =WORKDAY(F201,-1) -> 45286 | G202: =SUMIF(C:C, F202, D:D) -> 27940 | H202: =ROUNDUP(MONTH(Table3[[#This Row],[Date]])/3, 0) -> 4 | I202: {=(SUM(OFFSET(G202, -$M$4/2+1, 0, $M$4-1, 1)) + (INDIRECT("G" & ROW(G202) - $M$4/2) + INDIRECT("G" & ROW(G202) + $M$4/2))/2) / $M$4} -> 22342.545 | J202: =Table5[[#This Row],[Moving Average on Months]] - 1.96*STDEV(OFFSET(Table5[[#This Row],[Combined Daily Order]], -$M$4/2, 0, $M$4+1, 1)) -> 8600.398 | K202: =Table5[[#This Row],[Moving Average on Months]] + 1.96*STDEV(OFFSET(Table5[[#This Row],[Combined Daily Order]], -$M$4/2, 0, $M$4+1, 1)) -> 36084.693 | L202: #N/A | N202: =$W$48 -> 2594.4026 | O202: =$X$48 -> 23487.587
B203: 45453.349 | C203: =INT(B203) -> 45453 | D203: 4370 | F203: =WORKDAY(F202,-1) -> 45285 | G203: =SUMIF(C:C, F203, D:D) -> 17741 | H203: =ROUNDUP(MONTH(Table3[[#This Row],[Date]])/3, 0) -> 4 | I203: {=(SUM(OFFSET(G203, -$M$4/2+1, 0, $M$4-1, 1)) + (INDIRECT("G" & ROW(G203) - $M$4/2) + INDIRECT("G" & ROW(G203) + $M$4/2))/2) / $M$4} -> 22966.864 | J203: =Table5[[#This Row],[Moving Average on Months]] - 1.96*STDEV(OFFSET(Table5[[#This Row],[Combined Daily Order]], -$M$4/2, 0, $M$4+1, 1)) -> 9754.2172 | K203: =Table5[[#This Row],[Moving Average on Months]] + 1.96*STDEV(OFFSET(Table5[[#This Row],[Combined Daily Order]], -$M$4/2, 0, $M$4+1, 1)) -> 36179.51 | L203: #N/A | N203: =$W$48 -> 2594.4026 | O203: =$X$48 -> 23487.587
B204: 45450.978 | C204: =INT(B204) -> 45450 | D204: 4357 | F204: =WORKDAY(F203,-1) -> 45282 | G204: =SUMIF(C:C, F204, D:D) -> 31027 | H204: =ROUNDUP(MONTH(Table3[[#This Row],[Date]])/3, 0) -> 4 | I204: {=(SUM(OFFSET(G204, -$M$4/2+1, 0, $M$4-1, 1)) + (INDIRECT("G" & ROW(G204) - $M$4/2) + INDIRECT("G" & ROW(G204) + $M$4/2))/2) / $M$4} -> 23503.614 | J204: =Table5[[#This Row],[Moving Average on Months]] - 1.96*STDEV(OFFSET(Table5[[#This Row],[Combined Daily Order]], -$M$4/2, 0, $M$4+1, 1)) -> 10559.494 | K204: =Table5[[#This Row],[Moving Average on Months]] + 1.96*STDEV(OFFSET(Table5[[#This Row],[Combined Daily Order]], -$M$4/2, 0, $M$4+1, 1)) -> 36447.733 | L204: #N/A | N204: =$W$48 -> 2594.4026 | O204: =$X$48 -> 23487.587
B205: 45450.59 | C205: =INT(B205) -> 45450 | D205: 4591 | F205: =WORKDAY(F204,-1) -> 45281 | G205: =SUMIF(C:C, F205, D:D) -> 19190 | H205: =ROUNDUP(MONTH(Table3[[#This Row],[Date]])/3, 0) -> 4 | I205: {=(SUM(OFFSET(G205, -$M$4/2+1, 0, $M$4-1, 1)) + (INDIRECT("G" & ROW(G205) - $M$4/2) + INDIRECT("G" & ROW(G205) + $M$4/2))/2) / $M$4} -> 23962.273 | J205: =Table5[[#This Row],[Moving Average on Months]] - 1.96*STDEV(OFFSET(Table5[[#This Row],[Combined Daily Order]], -$M$4/2, 0, $M$4+1, 1)) -> 11735.987 | K205: =Table5[[#This Row],[Moving Average on Months]] + 1.96*STDEV(OFFSET(Table5[[#This Row],[Combined Daily Order]], -$M$4/2, 0, $M$4+1, 1)) -> 36188.559 | L205: #N/A | N205: =$W$48 -> 2594.4026 | O205: =$X$48 -> 23487.587
B206: 45450.218 | C206: =INT(B206) -> 45450 | D206: 4606 | F206: =WORKDAY(F205,-1) -> 45280 | G206: =SUMIF(C:C, F206, D:D) -> 32636 | H206: =ROUNDUP(MONTH(Table3[[#This Row],[Date]])/3, 0) -> 4 | I206: {=(SUM(OFFSET(G206, -$M$4/2+1, 0, $M$4-1, 1)) + (INDIRECT("G" & ROW(G206) - $M$4/2) + INDIRECT("G" & ROW(G206) + $M$4/2))/2) / $M$4} -> 24383.227 | J206: =Table5[[#This Row],[Moving Average on Months]] - 1.96*STDEV(OFFSET(Table5[[#This Row],[Combined Daily Order]], -$M$4/2, 0, $M$4+1, 1)) -> 12212.059 | K206: =Table5[[#This Row],[Moving Average on Months]] + 1.96*STDEV(OFFSET(Table5[[#This Row],[Combined Daily Order]], -$M$4/2, 0, $M$4+1, 1)) -> 36554.396 | L206: #N/A | N206: =$W$48 -> 2594.4026 | O206: =$X$48 -> 23487.587
B207: 45449.847 | C207: =INT(B207) -> 45449 | D207: 4924 | F207: =WORKDAY(F206,-1) -> 45279 | G207: =SUMIF(C:C, F207, D:D) -> 21896 | H207: =ROUNDUP(MONTH(Table3[[#This Row],[Date]])/3, 0) -> 4 | I207: {=(SUM(OFFSET(G207, -$M$4/2+1, 0, $M$4-1, 1)) + (INDIRECT("G" & ROW(G207) - $M$4/2) + INDIRECT("G" & ROW(G207) + $M$4/2))/2) / $M$4} -> 24780.932 | J207: =Table5[[#This Row],[Moving Average on Months]] - 1.96*STDEV(OFFSET(Table5[[#This Row],[Combined Daily Order]], -$M$4/2, 0, $M$4+1, 1)) -> 13067.195 | K207: =Table5[[#This Row],[Moving Average on Months]] + 1.96*STDEV(OFFSET(Table5[[#This Row],[Combined Daily Order]], -$M$4/2, 0, $M$4+1, 1)) -> 36494.668 | L207: #N/A | N207: =$W$48 -> 2594.4026 | O207: =$X$48 -> 23487.587
B208: 45449.451 | C208: =INT(B208) -> 45449 | D208: 4401 | F208: =WORKDAY(F207,-1) -> 45278 | G208: =SUMIF(C:C, F208, D:D) -> 31054 | H208: =ROUNDUP(MONTH(Table3[[#This Row],[Date]])/3, 0) -> 4 | I208: {=(SUM(OFFSET(G208, -$M$4/2+1, 0, $M$4-1, 1)) + (INDIRECT("G" & ROW(G208) - $M$4/2) + INDIRECT("G" & ROW(G208) + $M$4/2))/2) / $M$4} -> 25155.159 | J208: =Table5[[#This Row],[Moving Average on Months]] - 1.96*STDEV(OFFSET(Table5[[#This Row],[Combined Daily Order]], -$M$4/2, 0, $M$4+1, 1)) -> 13428.815 | K208: =Table5[[#This Row],[Moving Average on Months]] + 1.96*STDEV(OFFSET(Table5[[#This Row],[Combined Daily Order]], -$M$4/2, 0, $M$4+1, 1)) -> 36881.503 | L208: #N/A | N208: =$W$48 -> 2594.4026 | O208: =$X$48 -> 23487.587
B209: 45449.033 | C209: =INT(B209) -> 45449 | D209: 4009 | F209: =WORKDAY(F208,-1) -> 45275 | G209: =SUMIF(C:C, F209, D:D) -> 23503 | H209: =ROUNDUP(MONTH(Table3[[#This Row],[Date]])/3, 0) -> 4 | I209: {=(SUM(OFFSET(G209, -$M$4/2+1, 0, $M$4-1, 1)) + (INDIRECT("G" & ROW(G209) - $M$4/2) + INDIRECT("G" & ROW(G209) + $M$4/2))/2) / $M$4} -> 25394.409 | J209: =Table5[[#This Row],[Moving Average on Months]] - 1.96*STDEV(OFFSET(Table5[[#This Row],[Combined Daily Order]], -$M$4/2, 0, $M$4+1, 1)) -> 14491.888 | K209: =Table5[[#This Row],[Moving Average on Months]] + 1.96*STDEV(OFFSET(Table5[[#This Row],[Combined Daily Order]], -$M$4/2, 0, $M$4+1, 1)) -> 36296.931 | L209: #N/A | N209: =$W$48 -> 2594.4026 | O209: =$X$48 -> 23487.587
B210: 45448.632 | C210: =INT(B210) -> 45448 | D210: 4437 | F210: =WORKDAY(F209,-1) -> 45274 | G210: =SUMIF(C:C, F210, D:D) -> 34282 | H210: =ROUNDUP(MONTH(Table3[[#This Row],[Date]])/3, 0) -> 4 | I210: {=(SUM(OFFSET(G210, -$M$4/2+1, 0, $M$4-1, 1)) + (INDIRECT("G" & ROW(G210) - $M$4/2) + INDIRECT("G" & ROW(G210) + $M$4/2))/2) / $M$4} -> 25555.955 | J210: =Table5[[#This Row],[Moving Average on Months]] - 1.96*STDEV(OFFSET(Table5[[#This Row],[Combined Daily Order]], -$M$4/2, 0, $M$4+1, 1)) -> 14437.431 | K210: =Table5[[#This Row],[Moving Average on Months]] + 1.96*STDEV(OFFSET(Table5[[#This Row],[Combined Daily Order]], -$M$4/2, 0, $M$4+1, 1)) -> 36674.478 | L210: =Table5[[#This Row],[Combined Daily Order]] -> 34282 | N210: =$W$48 -> 2594.4026 | O210: =$X$48 -> 23487.587
B211: 45448.213 | C211: =INT(B211) -> 45448 | D211: 4163 | F211: =WORKDAY(F210,-1) -> 45273 | G211: =SUMIF(C:C, F211, D:D) -> 22101 | H211: =ROUNDUP(MONTH(Table3[[#This Row],[Date]])/3, 0) -> 4 | I211: {=(SUM(OFFSET(G211, -$M$4/2+1, 0, $M$4-1, 1)) + (INDIRECT("G" & ROW(G211) - $M$4/2) + INDIRECT("G" & ROW(G211) + $M$4/2))/2) / $M$4} -> 25730.591 | J211: =Table5[[#This Row],[Moving Average on Months]] - 1.96*STDEV(OFFSET(Table5[[#This Row],[Combined Daily Order]], -$M$4/2, 0, $M$4+1, 1)) -> 15076.184 | K211: =Table5[[#This Row],[Moving Average on Months]] + 1.96*STDEV(OFFSET(Table5[[#This Row],[Combined Daily Order]], -$M$4/2, 0, $M$4+1, 1)) -> 36384.998 | L211: #N/A | N211: =$W$48 -> 2594.4026 | O211: =$X$48 -> 23487.587
B212: 45447.786 | C212: =INT(B212) -> 45447 | D212: 4295 | F212: =WORKDAY(F211,-1) -> 45272 | G212: =SUMIF(C:C, F212, D:D) -> 33181 | H212: =ROUNDUP(MONTH(Table3[[#This Row],[Date]])/3, 0) -> 4 | I212: {=(SUM(OFFSET(G212, -$M$4/2+1, 0, $M$4-1, 1)) + (INDIRECT("G" & ROW(G212) - $M$4/2) + INDIRECT("G" & ROW(G212) + $M$4/2))/2) / $M$4} -> 25858.432 | J212: =Table5[[#This Row],[Moving Average on Months]] - 1.96*STDEV(OFFSET(Table5[[#This Row],[Combined Daily Order]], -$M$4/2, 0, $M$4+1, 1)) -> 14930.744 | K212: =Table5[[#This Row],[Moving Average on Months]] + 1.96*STDEV(OFFSET(Table5[[#This Row],[Combined Daily Order]], -$M$4/2, 0, $M$4+1, 1)) -> 36786.119 | L212: =Table5[[#This Row],[Combined Daily Order]] -> 33181 | N212: =$W$48 -> 2594.4026 | O212: =$X$48 -> 23487.587
B213: 45447.399 | C213: =INT(B213) -> 45447 | D213: 4937 | F213: =WORKDAY(F212,-1) -> 45271 | G213: =SUMIF(C:C, F213, D:D) -> 23218 | H213: =ROUNDUP(MONTH(Table3[[#This Row],[Date]])/3, 0) -> 4 | I213: {=(SUM(OFFSET(G213, -$M$4/2+1, 0, $M$4-1, 1)) + (INDIRECT("G" & ROW(G213) - $M$4/2) + INDIRECT("G" & ROW(G213) + $M$4/2))/2) / $M$4} -> 25664 | J213: =Table5[[#This Row],[Moving Average on Months]] - 1.96*STDEV(OFFSET(Table5[[#This Row],[Combined Daily Order]], -$M$4/2, 0, $M$4+1, 1)) -> 14702.969 | K213: =Table5[[#This Row],[Moving Average on Months]] + 1.96*STDEV(OFFSET(Table5[[#This Row],[Combined Daily Order]], -$M$4/2, 0, $M$4+1, 1)) -> 36625.031 | L213: #N/A | N213: =$W$48 -> 2594.4026 | O213: =$X$48 -> 23487.587
B214: 45446.99 | C214: =INT(B214) -> 45446 | D214: 5168 | F214: =WORKDAY(F213,-1) -> 45268 | G214: =SUMIF(C:C, F214, D:D) -> 30552 | H214: =ROUNDUP(MONTH(Table3[[#This Row],[Date]])/3, 0) -> 4 | I214: {=(SUM(OFFSET(G214, -$M$4/2+1, 0, $M$4-1, 1)) + (INDIRECT("G" & ROW(G214) - $M$4/2) + INDIRECT("G" & ROW(G214) + $M$4/2))/2) / $M$4} -> 25736.841 | J214: =Table5[[#This Row],[Moving Average on Months]] - 1.96*STDEV(OFFSET(Table5[[#This Row],[Combined Daily Order]], -$M$4/2, 0, $M$4+1, 1)) -> 14649.357 | K214: =Table5[[#This Row],[Moving Average on Months]] + 1.96*STDEV(OFFSET(Table5[[#This Row],[Combined Daily Order]], -$M$4/2, 0, $M$4+1, 1)) -> 36824.325 | L214: #N/A | N214: =$W$48 -> 2594.4026 | O214: =$X$48 -> 23487.587
B215: 45446.58 | C215: =INT(B215) -> 45446 | D215: 5089 | F215: =WORKDAY(F214,-1) -> 45267 | G215: =SUMIF(C:C, F215, D:D) -> 19611 | H215: =ROUNDUP(MONTH(Table3[[#This Row],[Date]])/3, 0) -> 4 | I215: {=(SUM(OFFSET(G215, -$M$4/2+1, 0, $M$4-1, 1)) + (INDIRECT("G" & ROW(G215) - $M$4/2) + INDIRECT("G" & ROW(G215) + $M$4/2))/2) / $M$4} -> 25691.795 | J215: =Table5[[#This Row],[Moving Average on Months]] - 1.96*STDEV(OFFSET(Table5[[#This Row],[Combined Daily Order]], -$M$4/2, 0, $M$4+1, 1)) -> 14446.201 | K215: =Table5[[#This Row],[Moving Average on Months]] + 1.96*STDEV(OFFSET(Table5[[#This Row],[Combined Daily Order]], -$M$4/2, 0, $M$4+1, 1)) -> 36937.39 | L215: #N/A | N215: =$W$48 -> 2594.4026 | O215: =$X$48 -> 23487.587
...

Sheet Clean Data
A1: Clean Data
B3: Date | C3: Orders BLACK | D3: Orders BEIGE | E3: Orders TOTAL | F3: Graphs:
B4: 45562 | C4: =Table3[[#This Row],[Combined Daily order]] -> 25910 | D4: =Table5[[#This Row],[Combined Daily Order]] -> 12033 | E4: =C4+D4 -> 37943
B5: 45561 | C5: =Table3[[#This Row],[Combined Daily order]] -> 36491 | D5: =Table5[[#This Row],[Combined Daily Order]] -> 18563 | E5: =C5+D5 -> 55054
B6: 45560 | C6: =Table3[[#This Row],[Combined Daily order]] -> 26068 | D6: =Table5[[#This Row],[Combined Daily Order]] -> 12821 | E6: =C6+D6 -> 38889
B7: 45559 | C7: =Table3[[#This Row],[Combined Daily order]] -> 40865 | D7: =Table5[[#This Row],[Combined Daily Order]] -> 19276 | E7: =C7+D7 -> 60141
B8: 45558 | C8: =Table3[[#This Row],[Combined Daily order]] -> 27032 | D8: =Table5[[#This Row],[Combined Daily Order]] -> 12583 | E8: =C8+D8 -> 39615
B9: 45555 | C9: =Table3[[#This Row],[Combined Daily order]] -> 25465 | D9: =Table5[[#This Row],[Combined Daily Order]] -> 18787 | E9: =C9+D9 -> 44252
B10: 45554 | C10: =Table3[[#This Row],[Combined Daily order]] -> 36114 | D10: =Table5[[#This Row],[Combined Daily Order]] -> 11693 | E10: =C10+D10 -> 47807
B11: 45553 | C11: =Table3[[#This Row],[Combined Daily order]] -> 25049 | D11: =Table5[[#This Row],[Combined Daily Order]] -> 11473 | E11: =C11+D11 -> 36522
B12: 45552 | C12: =Table3[[#This Row],[Combined Daily order]] -> 36767 | D12: =Table5[[#This Row],[Combined Daily Order]] -> 18928 | E12: =C12+D12 -> 55695
B13: 45551 | C13: =Table3[[#This Row],[Combined Daily order]] -> 27301 | D13: =Table5[[#This Row],[Combined Daily Order]] -> 13779 | E13: =C13+D13 -> 41080
B14: 45548 | C14: =Table3[[#This Row],[Combined Daily order]] -> 35320 | D14: =Table5[[#This Row],[Combined Daily Order]] -> 18795 | E14: =C14+D14 -> 54115
B15: 45547 | C15: =Table3[[#This Row],[Combined Daily order]] -> 25240 | D15: =Table5[[#This Row],[Combined Daily Order]] -> 11667 | E15: =C15+D15 -> 36907
... B381: 45035 | C381: =Table3[[#This Row],[Combined Daily order]] -> 17195 | D381: =Table5[[#This Row],[Combined Daily Order]] -> 12759 | E381: =C381+D381 -> 29954
B382: 45034 | C382: =Table3[[#This Row],[Combined Daily order]] -> 24913 | D382: =AVERAGE(D383,D381) -> 13237 | E382: =C382+D382 -> 38150
B383: 45033 | C383: =Table3[[#This Row],[Combined Daily order]] -> 18956 | D383: =Table5[[#This Row],[Combined Daily Order]] -> 13715 | E383: =C383+D383 -> 32671
B384: 45030 | C384: =Table3[[#This Row],[Combined Daily order]] -> 25647 | D384: =Table5[[#This Row],[Combined Daily Order]] -> 8264 | E384: =C384+D384 -> 33911
B385: 45029 | C385: =Table3[[#This Row],[Combined Daily order]] -> 18341 | D385: =Table5[[#This Row],[Combined Daily Order]] -> 8391 | E385: =C385+D385 -> 26732
B386: 45028 | C386: =Table3[[#This Row],[Combined Daily order]] -> 28519 | D386: =Table5[[#This Row],[Combined Daily Order]] -> 12803 | E386: =C386+D386 -> 41322
B387: 45027 | C387: =Table3[[#This Row],[Combined Daily order]] -> 19879 | D387: =Table5[[#This Row],[Combined Daily Order]] -> 9795 | E387: =C387+D387 -> 29674
B388: 45026 | C388: =Table3[[#This Row],[Combined Daily order]] -> 27733 | D388: =Table5[[#This Row],[Combined Daily Order]] -> 13783 | E388: =C388+D388 -> 41516
B389: 45023 | C389: =Table3[[#This Row],[Combined Daily order]] -> 20034 | D389: =Table5[[#This Row],[Combined Daily Order]] -> 13237 | E389: =C389+D389 -> 33271
B390: 45022 | C390: =Table3[[#This Row],[Combined Daily order]] -> 28303 | D390: =Table5[[#This Row],[Combined Daily Order]] -> 9698 | E390: =C390+D390 -> 38001
B391: 45021 | C391: =Table3[[#This Row],[Combined Daily order]] -> 18037 | D391: =Table5[[#This Row],[Combined Daily Order]] -> 8536 | E391: =C391+D391 -> 26573
B392: 45020 | C392: =Table3[[#This Row],[Combined Daily order]] -> 26882 | D392: =Table5[[#This Row],[Combined Daily Order]] -> 12896 | E392: =C392+D392 -> 39778
B393: 45019 | C393: =Table3[[#This Row],[Combined Daily order]] -> 17677 | D393: =Table5[[#This Row],[Combined Daily Order]] -> 12616 | E393: =C393+D393 -> 30293
B394: 45016 | C394: =Table3[[#This Row],[Combined Daily order]] -> 27964 | D394: =Table5[[#This Row],[Combined Daily Order]] -> 14343 | E394: =C394+D394 -> 42307
... B806: 44440 | C806: =Table3[[#This Row],[Combined Daily order]] -> 30157 | D806: =Table5[[#This Row],[Combined Daily Order]] -> 9514 | E806: =C806+D806 -> 39671

Sheet Aggregated Data
A1: Aggregated Data
B3: Period | C3: Sum of Orders BLACK | D3: Sum of Orders BEIGE | E3: Sum of Orders TOTAL | AF3: Weekly reference period (for verification only)
B4: 2021 | C4: 2931305 | D4: 1413099 | E4: 4344404
B5: Trim.3 | C5: 548044 | D5: 264407 | E5: 812451 | AG5: Week starting on: | AH5: Orders BLACK | AI5: Orders BEIGE | AJ5: Orders TOTAL
B6: sep | C6: 548044 | D6: 264407 | E6: 812451 | AG6: 45558 | AH6: =SUM(OFFSET('Clean Data'!$C$4,(ROW()-ROW($AH$6))*5,0,5,1)) -> 156366 | AI6: =SUM(OFFSET('Clean Data'!$D$4,(ROW()-ROW($AI$6))*5,0,5,1)) -> 75276 | AJ6: =AH6+AI6 -> 231642
B7: Trim.4 | C7: 2383261 | D7: 1148692 | E7: 3531953 | AG7: =AG6-7 -> 45551 | AH7: =SUM(OFFSET('Clean Data'!$C$4,(ROW()-ROW($AH$6))*5,0,5,1)) -> 150696 | AI7: =SUM(OFFSET('Clean Data'!$D$4,(ROW()-ROW($AI$6))*5,0,5,1)) -> 74660 | AJ7: =AH7+AI7 -> 225356
B8: oct | C8: 558742 | D8: 289780 | E8: 848522 | AG8: =AG7-7 -> 45544 | AH8: =SUM(OFFSET('Clean Data'!$C$4,(ROW()-ROW($AH$6))*5,0,5,1)) -> 150598 | AI8: =SUM(OFFSET('Clean Data'!$D$4,(ROW()-ROW($AI$6))*5,0,5,1)) -> 78914 | AJ8: =AH8+AI8 -> 229512
B9: nov | C9: 834836 | D9: 377003 | E9: 1211839 | AG9: =AG8-7 -> 45537 | AH9: =SUM(OFFSET('Clean Data'!$C$4,(ROW()-ROW($AH$6))*5,0,5,1)) -> 169056 | AI9: =SUM(OFFSET('Clean Data'!$D$4,(ROW()-ROW($AI$6))*5,0,5,1)) -> 75265 | AJ9: =AH9+AI9 -> 244321
B10: dic | C10: 989683 | D10: 481909 | E10: 1471592 | AG10: =AG9-7 -> 45530 | AH10: =SUM(OFFSET('Clean Data'!$C$4,(ROW()-ROW($AH$6))*5,0,5,1)) -> 141681 | AI10: =SUM(OFFSET('Clean Data'!$D$4,(ROW()-ROW($AI$6))*5,0,5,1)) -> 70687 | AJ10: =AH10+AI10 -> 212368
B11: 2022 | C11: 6056804 | D11: 3244943 | E11: 9301747 | AG11: =AG10-7 -> 45523 | AH11: =SUM(OFFSET('Clean Data'!$C$4,(ROW()-ROW($AH$6))*5,0,5,1)) -> 148019 | AI11: =SUM(OFFSET('Clean Data'!$D$4,(ROW()-ROW($AI$6))*5,0,5,1)) -> 68502 | AJ11: =AH11+AI11 -> 216521
B12: Trim.1 | C12: 1242158 | D12: 631293 | E12: 1873451 | AG12: =AG11-7 -> 45516 | AH12: =SUM(OFFSET('Clean Data'!$C$4,(ROW()-ROW($AH$6))*5,0,5,1)) -> 127391 | AI12: =SUM(OFFSET('Clean Data'!$D$4,(ROW()-ROW($AI$6))*5,0,5,1)) -> 67375 | AJ12: =AH12+AI12 -> 194766
B13: ene | C13: 407349 | D13: 222237 | E13: 629586 | AG13: =AG12-7 -> 45509 | AH13: =SUM(OFFSET('Clean Data'!$C$4,(ROW()-ROW($AH$6))*5,0,5,1)) -> 131167 | AI13: =SUM(OFFSET('Clean Data'!$D$4,(ROW()-ROW($AI$6))*5,0,5,1)) -> 56787 | AJ13: =AH13+AI13 -> 187954
B14: feb | C14: 379315 | D14: 179556 | E14: 558871 | AG14: =AG13-7 -> 45502 | AH14: =SUM(OFFSET('Clean Data'!$C$4,(ROW()-ROW($AH$6))*5,0,5,1)) -> 107660 | AI14: =SUM(OFFSET('Clean Data'!$D$4,(ROW()-ROW($AI$6))*5,0,5,1)) -> 55957 | AJ14: =AH14+AI14 -> 163617
B15: mar | C15: 455494 | D15: 229500 | E15: 684994 | AG15: =AG14-7 -> 45495 | AH15: =SUM(OFFSET('Clean Data'!$C$4,(ROW()-ROW($AH$6))*5,0,5,1)) -> 103065 | AI15: =SUM(OFFSET('Clean Data'!$D$4,(ROW()-ROW($AI$6))*5,0,5,1)) -> 53354 | AJ15: =AH15+AI15 -> 156419
B16: Trim.2 | C16: 1196816 | D16: 600826 | E16: 1797642 | AG16: =AG15-7 -> 45488 | AH16: =SUM(OFFSET('Clean Data'!$C$4,(ROW()-ROW($AH$6))*5,0,5,1)) -> 84386 | AI16: =SUM(OFFSET('Clean Data'!$D$4,(ROW()-ROW($AI$6))*5,0,5,1)) -> 42704 | AJ16: =AH16+AI16 -> 127090
B17: abr | C17: 404221 | D17: 206568 | E17: 610789 | AG17: =AG16-7 -> 45481 | AH17: =SUM(OFFSET('Clean Data'!$C$4,(ROW()-ROW($AH$6))*5,0,5,1)) -> 93659 | AI17: =SUM(OFFSET('Clean Data'!$D$4,(ROW()-ROW($AI$6))*5,0,5,1)) -> 46682 | AJ17: =AH17+AI17 -> 140341
B18: may | C18: 427348 | D18: 218681 | E18: 646029 | AG18: =AG17-7 -> 45474 | AH18: =SUM(OFFSET('Clean Data'!$C$4,(ROW()-ROW($AH$6))*5,0,5,1)) -> 97505 | AI18: =SUM(OFFSET('Clean Data'!$D$4,(ROW()-ROW($AI$6))*5,0,5,1)) -> 44582 | AJ18: =AH18+AI18 -> 142087
... B58: Grand Total | C58: 20533155 | D58: 10446651 | E58: 30979806 | AG58: =AG57-7 -> 45194 | AH58: =SUM(OFFSET('Clean Data'!$C$4,(ROW()-ROW($AH$6))*5,0,5,1)) -> 144992 | AI58: =SUM(OFFSET('Clean Data'!$D$4,(ROW()-ROW($AI$6))*5,0,5,1)) -> 68314 | AJ58: =AH58+AI58 -> 213306
AG59: =AG58-7 -> 45187 | AH59: =SUM(OFFSET('Clean Data'!$C$4,(ROW()-ROW($AH$6))*5,0,5,1)) -> 156704 | AI59: =SUM(OFFSET('Clean Data'!$D$4,(ROW()-ROW($AI$6))*5,0,5,1)) -> 70447 | AJ59: =AH59+AI59 -> 227151
AG60: =AG59-7 -> 45180 | AH60: =SUM(OFFSET('Clean Data'!$C$4,(ROW()-ROW($AH$6))*5,0,5,1)) -> 147098 | AI60: =SUM(OFFSET('Clean Data'!$D$4,(ROW()-ROW($AI$6))*5,0,5,1)) -> 74473 | AJ60: =AH60+AI60 -> 221571
AG61: =AG60-7 -> 45173 | AH61: =SUM(OFFSET('Clean Data'!$C$4,(ROW()-ROW($AH$6))*5,0,5,1)) -> 147083 | AI61: =SUM(OFFSET('Clean Data'!$D$4,(ROW()-ROW($AI$6))*5,0,5,1)) -> 69316 | AJ61: =AH61+AI61 -> 216399
AG62: =AG61-7 -> 45166 | AH62: =SUM(OFFSET('Clean Data'!$C$4,(ROW()-ROW($AH$6))*5,0,5,1)) -> 131815 | AI62: =SUM(OFFSET('Clean Data'!$D$4,(ROW()-ROW($AI$6))*5,0,5,1)) -> 71130 | AJ62: =AH62+AI62 -> 202945
AG63: =AG62-7 -> 45159 | AH63: =SUM(OFFSET('Clean Data'!$C$4,(ROW()-ROW($AH$6))*5,0,5,1)) -> 140983 | AI63: =SUM(OFFSET('Clean Data'!$D$4,(ROW()-ROW($AI$6))*5,0,5,1)) -> 62713 | AJ63: =AH63+AI63 -> 203696
AG64: =AG63-7 -> 45152 | AH64: =SUM(OFFSET('Clean Data'!$C$4,(ROW()-ROW($AH$6))*5,0,5,1)) -> 136549 | AI64: =SUM(OFFSET('Clean Data'!$D$4,(ROW()-ROW($AI$6))*5,0,5,1)) -> 60028 | AJ64: =AH64+AI64 -> 196577
AG65: =AG64-7 -> 45145 | AH65: =SUM(OFFSET('Clean Data'!$C$4,(ROW()-ROW($AH$6))*5,0,5,1)) -> 111316 | AI65: =SUM(OFFSET('Clean Data'!$D$4,(ROW()-ROW($AI$6))*5,0,5,1)) -> 53899 | AJ65: =AH65+AI65 -> 165215
AG66: =AG65-7 -> 45138 | AH66: =SUM(OFFSET('Clean Data'!$C$4,(ROW()-ROW($AH$6))*5,0,5,1)) -> 109676 | AI66: =SUM(OFFSET('Clean Data'!$D$4,(ROW()-ROW($AI$6))*5,0,5,1)) -> 53889 | AJ66: =AH66+AI66 -> 163565
AG67: =AG66-7 -> 45131 | AH67: =SUM(OFFSET('Clean Data'!$C$4,(ROW()-ROW($AH$6))*5,0,5,1)) -> 94002 | AI67: =SUM(OFFSET('Clean Data'!$D$4,(ROW()-ROW($AI$6))*5,0,5,1)) -> 47730 | AJ67: =AH67+AI67 -> 141732
AG68: =AG67-7 -> 45124 | AH68: =SUM(OFFSET('Clean Data'!$C$4,(ROW()-ROW($AH$6))*5,0,5,1)) -> 80604 | AI68: =SUM(OFFSET('Clean Data'!$D$4,(ROW()-ROW($AI$6))*5,0,5,1)) -> 42794 | AJ68: =AH68+AI68 -> 123398
AG69: =AG68-7 -> 45117 | AH69: =SUM(OFFSET('Clean Data'!$C$4,(ROW()-ROW($AH$6))*5,0,5,1)) -> 77034 | AI69: =SUM(OFFSET('Clean Data'!$D$4,(ROW()-ROW($AI$6))*5,0,5,1)) -> 44914 | AJ69: =AH69+AI69 -> 121948
AG70: =AG69-7 -> 45110 | AH70: =SUM(OFFSET('Clean Data'!$C$4,(ROW()-ROW($AH$6))*5,0,5,1)) -> 73435 | AI70: =SUM(OFFSET('Clean Data'!$D$4,(ROW()-ROW($AI$6))*5,0,5,1)) -> 42054 | AJ70: =AH70+AI70 -> 115489
... AG166: =AG165-7 -> 44438 | AH166: =SUM(OFFSET('Clean Data'!$C$4,(ROW()-ROW($AH$6))*5,0,5,1)) -> 80706 | AI166: =SUM(OFFSET('Clean Data'!$D$4,(ROW()-ROW($AI$6))*5,0,5,1)) -> 32428 | AJ166: =AH166+AI166 -> 113134

Sheet Autocorrelation
A1: Autocorrelation Analysis
B4: Month | C4: Orders | D4: Mean | E4: Dev | F4: Dev_squared | H4: Lag | I4: Numerator | J4: Denominator | K4: ACF
B5: 44440 | C5: =GETPIVOTDATA("Sum of Orders TOTAL",'Aggregated Data'!$B$3,"Meses (Date)",9,"Trimestres (Date)",3,"Años (Date)",2021) -> 812451 | D5: =AVERAGE(C5:C41) -> 837292.05 | E5: =C5-$D$5 -> -24841.054 | F5: =E5^2 -> 6.1707797e+08 | H5: 0 | I5: {=SUMPRODUCT((E5:E41) * (E5:E41))} -> 2.7882752e+12 | J5: =SUM(F5:F41) -> 2.7882752e+12 | K5: =I5/$J$5 -> 1
B6: oct | C6: =GETPIVOTDATA("Sum of Orders TOTAL",'Aggregated Data'!B3,"Meses (Date)",10,"Trimestres (Date)",4,"Años (Date)",2021) -> 848522 | E6: =C6-$D$5 -> 11229.946 | F6: =E6^2 -> 1.2611169e+08 | H6: 1 | I6: {=SUMPRODUCT((E5:E40) * (E6:E41))} -> 1.3909457e+12 | K6: =I6/$J$5 -> 0.49885524
B7: nov | C7: =GETPIVOTDATA("Sum of Orders TOTAL",'Aggregated Data'!$B$3,"Meses (Date)",11,"Trimestres (Date)",4,"Años (Date)",2021) -> 1211839 | E7: =C7-$D$5 -> 374546.95 | F7: =E7^2 -> 1.4028541e+11 | H7: 2 | I7: {=SUMPRODUCT((E5:E39) * (E7:E41))} -> -3.7774504e+10 | K7: =I7/$J$5 -> -0.013547624
B8: dic | C8: =GETPIVOTDATA("Sum of Orders TOTAL",'Aggregated Data'!$B$3,"Meses (Date)",12,"Trimestres (Date)",4,"Años (Date)",2021) -> 1471592 | E8: =C8-$D$5 -> 634299.95 | F8: =E8^2 -> 4.0233642e+11 | H8: 3 | I8: {=SUMPRODUCT((E5:E38) * (E8:E41))} -> -2.5692208e+11 | K8: =I8/$J$5 -> -0.092143732
B9: 44562 | C9: =GETPIVOTDATA("Sum of Orders TOTAL",'Aggregated Data'!$B$3,"Meses (Date)",1,"Trimestres (Date)",1,"Años (Date)",2022) -> 629586 | E9: =C9-$D$5 -> -207706.05 | F9: =E9^2 -> 4.3141805e+10 | H9: 4 | I9: {=SUMPRODUCT((E5:E37) * (E9:E41))} -> -5.44664e+11 | K9: =I9/$J$5 -> -0.19534084
B10: feb | C10: =GETPIVOTDATA("Sum of Orders TOTAL",'Aggregated Data'!$B$3,"Meses (Date)",2,"Trimestres (Date)",1,"Años (Date)",2022) -> 558871 | E10: =C10-$D$5 -> -278421.05 | F10: =E10^2 -> 7.7518283e+10 | H10: 5 | I10: {=SUMPRODUCT((E5:E36) * (E10:E41))} -> -7.6844047e+11 | K10: =I10/$J$5 -> -0.27559707
B11: mar | C11: =GETPIVOTDATA("Sum of Orders TOTAL",'Aggregated Data'!$B$3,"Meses (Date)",3,"Trimestres (Date)",1,"Años (Date)",2022) -> 684994 | E11: =C11-$D$5 -> -152298.05 | F11: =E11^2 -> 2.3194697e+10 | H11: 6 | I11: {=SUMPRODUCT((E5:E35) * (E11:E41))} -> -9.0357942e+11 | K11: =I11/$J$5 -> -0.32406394
B12: abr | C12: =GETPIVOTDATA("Sum of Orders TOTAL",'Aggregated Data'!$B$3,"Meses (Date)",4,"Trimestres (Date)",2,"Años (Date)",2022) -> 610789 | E12: =C12-$D$5 -> -226503.05 | F12: =E12^2 -> 5.1303633e+10 | H12: 7 | I12: {=SUMPRODUCT((E5:E34) * (E12:E41))} -> -1.0096025e+12 | K12: =I12/$J$5 -> -0.36208854
B13: may | C13: =GETPIVOTDATA("Sum of Orders TOTAL",'Aggregated Data'!$B$3,"Meses (Date)",5,"Trimestres (Date)",2,"Años (Date)",2022) -> 646029 | E13: =C13-$D$5 -> -191263.05 | F13: =E13^2 -> 3.6581556e+10 | H13: 8 | I13: {=SUMPRODUCT((E5:E33) * (E13:E41))} -> -5.8284698e+11 | K13: =I13/$J$5 -> -0.20903496
B14: jun | C14: =GETPIVOTDATA("Sum of Orders TOTAL",'Aggregated Data'!$B$3,"Meses (Date)",6,"Trimestres (Date)",2,"Años (Date)",2022) -> 540824 | E14: =C14-$D$5 -> -296468.05 | F14: =E14^2 -> 8.7893307e+10 | H14: 9 | I14: {=SUMPRODUCT(($E$5:E32) * (E14:$E$41))} -> -1.6008601e+11 | K14: =I14/$J$5 -> -0.057413993
B15: jul | C15: =GETPIVOTDATA("Sum of Orders TOTAL",'Aggregated Data'!$B$3,"Meses (Date)",7,"Trimestres (Date)",3,"Años (Date)",2022) -> 488697 | E15: =C15-$D$5 -> -348595.05 | F15: =E15^2 -> 1.2151851e+11 | H15: 10 | I15: {=SUMPRODUCT(($E$5:E31) * (E15:$E$41))} -> -7.7128562e+10 | K15: =I15/$J$5 -> -0.027661747
B16: ago | C16: =GETPIVOTDATA("Sum of Orders TOTAL",'Aggregated Data'!$B$3,"Meses (Date)",8,"Trimestres (Date)",3,"Años (Date)",2022) -> 767857 | E16: =C16-$D$5 -> -69435.054 | F16: =E16^2 -> 4.8212267e+09 | H16: 11 | I16: {=SUMPRODUCT(($E$5:E30) * (E16:$E$41))} -> 7.9587633e+11 | K16: =I16/$J$5 -> 0.2854368
B17: sep | C17: =GETPIVOTDATA("Sum of Orders TOTAL",'Aggregated Data'!$B$3,"Meses (Date)",9,"Trimestres (Date)",3,"Años (Date)",2022) -> 847772 | E17: =C17-$D$5 -> 10479.946 | F17: =E17^2 -> 1.0982927e+08 | H17: 12 | I17: {=SUMPRODUCT(($E$5:E29) * (E17:$E$41))} -> 1.6854563e+12 | K17: =I17/$J$5 -> 0.60447991
B18: oct | C18: =GETPIVOTDATA("Sum of Orders TOTAL",'Aggregated Data'!$B$3,"Meses (Date)",10,"Trimestres (Date)",4,"Años (Date)",2022) -> 880802 | E18: =C18-$D$5 -> 43509.946 | F18: =E18^2 -> 1.8931154e+09 | H18: 13 | I18: {=SUMPRODUCT(($E$5:E28) * (E18:$E$41))} -> 7.8610702e+11 | K18: =I18/$J$5 -> 0.28193309
B19: nov | C19: =GETPIVOTDATA("Sum of Orders TOTAL",'Aggregated Data'!$B$3,"Meses (Date)",11,"Trimestres (Date)",4,"Años (Date)",2022) -> 1204624 | E19: =C19-$D$5 -> 367331.95 | F19: =E19^2 -> 1.3493276e+11 | H19: 14 | I19: {=SUMPRODUCT(($E$5:E27) * (E19:$E$41))} -> -1.4917351e+11 | K19: =I19/$J$5 -> -0.053500284
B20: dic | C20: =GETPIVOTDATA("Sum of Orders TOTAL",'Aggregated Data'!$B$3,"Meses (Date)",12,"Trimestres (Date)",4,"Años (Date)",2022) -> 1440902 | E20: =C20-$D$5 -> 603609.95 | F20: =E20^2 -> 3.6434497e+11 | H20: 15 | I20: {=SUMPRODUCT(($E$5:E26) * (E20:$E$41))} -> -2.6113447e+11 | K20: =I20/$J$5 -> -0.093654482
B21: 44927 | C21: =GETPIVOTDATA("Sum of Orders TOTAL",'Aggregated Data'!$B$3,"Meses (Date)",1,"Trimestres (Date)",1,"Años (Date)",2023) -> 702024 | E21: =C21-$D$5 -> -135268.05 | F21: =E21^2 -> 1.8297446e+10 | H21: 16 | I21: {=SUMPRODUCT(($E$5:E25) * (E21:$E$41))} -> -3.7113699e+11 | K21: =I21/$J$5 -> -0.1331063
B22: feb | C22: =GETPIVOTDATA("Sum of Orders TOTAL",'Aggregated Data'!$B$3,"Meses (Date)",2,"Trimestres (Date)",1,"Años (Date)",2023) -> 532900 | E22: =C22-$D$5 -> -304392.05 | F22: =E22^2 -> 9.2654523e+10 | H22: 17 | I22: {=SUMPRODUCT(($E$5:E24) * (E22:$E$41))} -> -4.203979e+11 | K22: =I22/$J$5 -> -0.15077346
B23: mar | C23: =GETPIVOTDATA("Sum of Orders TOTAL",'Aggregated Data'!$B$3,"Meses (Date)",3,"Trimestres (Date)",1,"Años (Date)",2023) -> 771880 | E23: =C23-$D$5 -> -65412.054 | F23: =E23^2 -> 4.2787368e+09 | H23: 18 | I23: {=SUMPRODUCT(($E$5:E23) * (E23:$E$41))} -> -5.8910938e+11 | K23: =I23/$J$5 -> -0.21128093
B24: abr | C24: =GETPIVOTDATA("Sum of Orders TOTAL",'Aggregated Data'!$B$3,"Meses (Date)",4,"Trimestres (Date)",2,"Años (Date)",2023) -> 689399 | E24: =C24-$D$5 -> -147893.05 | F24: =E24^2 -> 2.1872355e+10 | H24: 19 | I24: {=SUMPRODUCT(($E$5:E22) * (E24:$E$41))} -> -7.2994521e+11 | K24: =I24/$J$5 -> -0.26179095
B25: may | C25: =GETPIVOTDATA("Sum of Orders TOTAL",'Aggregated Data'!$B$3,"Meses (Date)",5,"Trimestres (Date)",2,"Años (Date)",2023) -> 776047 | E25: =C25-$D$5 -> -61245.054 | F25: =E25^2 -> 3.7509566e+09 | H25: 20 | I25: {=SUMPRODUCT(($E$5:E21) * (E25:$E$41))} -> -3.8069785e+11 | K25: =I25/$J$5 -> -0.13653525
B26: jun | C26: =GETPIVOTDATA("Sum of Orders TOTAL",'Aggregated Data'!$B$3,"Meses (Date)",6,"Trimestres (Date)",2,"Años (Date)",2023) -> 617732 | E26: =C26-$D$5 -> -219560.05 | F26: =E26^2 -> 4.8206617e+10 | H26: 21 | I26: {=SUMPRODUCT(($E$5:E20) * (E26:$E$41))} -> -9.0373438e+10 | K26: =I26/$J$5 -> -0.032411951
B27: jul | C27: =GETPIVOTDATA("Sum of Orders TOTAL",'Aggregated Data'!$B$3,"Meses (Date)",7,"Trimestres (Date)",3,"Años (Date)",2023) -> 539571 | E27: =C27-$D$5 -> -297721.05 | F27: =E27^2 -> 8.8637826e+10 | H27: 22 | I27: {=SUMPRODUCT(($E$5:E19) * (E27:$E$41))} -> -2.2871492e+10 | K27: =I27/$J$5 -> -0.0082027386
B28: ago | C28: =GETPIVOTDATA("Sum of Orders TOTAL",'Aggregated Data'!$B$3,"Meses (Date)",8,"Trimestres (Date)",3,"Años (Date)",2023) -> 856745 | E28: =C28-$D$5 -> 19452.946 | F28: =E28^2 -> 3.7841711e+08 | H28: 23 | I28: {=SUMPRODUCT(($E$5:E18) * (E28:$E$41))} -> 4.3638373e+11 | K28: =I28/$J$5 -> 0.1565067
B29: sep | C29: =GETPIVOTDATA("Sum of Orders TOTAL",'Aggregated Data'!$B$3,"Meses (Date)",9,"Trimestres (Date)",3,"Años (Date)",2023) -> 916676 | E29: =C29-$D$5 -> 79383.946 | F29: =E29^2 -> 6.3018109e+09 | H29: 24 | I29: {=SUMPRODUCT(($E$5:E17) * (E29:$E$41))} -> 8.7136218e+11 | K29: =I29/$J$5 -> 0.31250939
B30: oct | C30: =GETPIVOTDATA("Sum of Orders TOTAL",'Aggregated Data'!$B$3,"Meses (Date)",10,"Trimestres (Date)",4,"Años (Date)",2023) -> 1029842 | E30: =C30-$D$5 -> 192549.95 | F30: =E30^2 -> 3.7075482e+10 | H30: 25 | I30: {=SUMPRODUCT(($E$5:E16) * (E30:$E$41))} -> 4.3192836e+11 | K30: =I30/$J$5 -> 0.1549088
B31: nov | C31: =GETPIVOTDATA("Sum of Orders TOTAL",'Aggregated Data'!$B$3,"Meses (Date)",11,"Trimestres (Date)",4,"Años (Date)",2023) -> 1410846 | E31: =C31-$D$5 -> 573553.95 | F31: =E31^2 -> 3.2896413e+11 | H31: 26 | I31: {=SUMPRODUCT(($E$5:E15) * (E31:$E$41))} -> -3.968817e+10 | K31: =I31/$J$5 -> -0.01423395
B32: dic | C32: =GETPIVOTDATA("Sum of Orders TOTAL",'Aggregated Data'!$B$3,"Meses (Date)",12,"Trimestres (Date)",4,"Años (Date)",2023) -> 1556971 | E32: =C32-$D$5 -> 719678.95 | F32: =E32^2 -> 5.1793779e+11 | H32: 27 | I32: {=SUMPRODUCT(($E$5:E14) * (E32:$E$41))} -> -1.1196188e+11 | K32: =I32/$J$5 -> -0.040154532
B33: 45292 | C33: =GETPIVOTDATA("Sum of Orders TOTAL",'Aggregated Data'!$B$3,"Meses (Date)",1,"Trimestres (Date)",1,"Años (Date)",2024) -> 851275 | E33: =C33-$D$5 -> 13982.946 | F33: =E33^2 -> 1.9552278e+08 | H33: 28 | I33: {=SUMPRODUCT(($E$5:E13) * (E33:$E$41))} -> -4.7481193e+10 | K33: =I33/$J$5 -> -0.017028877
B34: feb | C34: =GETPIVOTDATA("Sum of Orders TOTAL",'Aggregated Data'!$B$3,"Meses (Date)",2,"Trimestres (Date)",1,"Años (Date)",2024) -> 652396 | E34: =C34-$D$5 -> -184896.05 | F34: =E34^2 -> 3.4186551e+10 | H34: 29 | I34: {=SUMPRODUCT(($E$5:E12) * (E34:$E$41))} -> 2.5239606e+10 | K34: =I34/$J$5 -> 0.0090520498
B35: mar | C35: =GETPIVOTDATA("Sum of Orders TOTAL",'Aggregated Data'!$B$3,"Meses (Date)",3,"Trimestres (Date)",1,"Años (Date)",2024) -> 717319 | E35: =C35-$D$5 -> -119973.05 | F35: =E35^2 -> 1.4393534e+10 | H35: 30 | I35: {=SUMPRODUCT(($E$5:E11) * (E35:$E$41))} -> -1.055809e+11 | K35: =I35/$J$5 -> -0.037866027
B36: abr | C36: =GETPIVOTDATA("Sum of Orders TOTAL",'Aggregated Data'!$B$3,"Meses (Date)",4,"Trimestres (Date)",2,"Años (Date)",2024) -> 755725 | E36: =C36-$D$5 -> -81567.054 | F36: =E36^2 -> 6.6531843e+09 | H36: 31 | I36: {=SUMPRODUCT(($E$5:E10) * (E36:$E$41))} -> -2.1154267e+11 | K36: =I36/$J$5 -> -0.07586865
B37: may | C37: =GETPIVOTDATA("Sum of Orders TOTAL",'Aggregated Data'!$B$3,"Meses (Date)",5,"Trimestres (Date)",2,"Años (Date)",2024) -> 827548 | E37: =C37-$D$5 -> -9744.0541 | F37: =E37^2 -> 94946589 | H37: 32 | I37: {=SUMPRODUCT(($E$5:E9) * (E37:$E$41))} -> -6.0336202e+10 | K37: =I37/$J$5 -> -0.021639257
B38: jun | C38: =GETPIVOTDATA("Sum of Orders TOTAL",'Aggregated Data'!$B$3,"Meses (Date)",6,"Trimestres (Date)",2,"Años (Date)",2024) -> 656765 | E38: =C38-$D$5 -> -180527.05 | F38: =E38^2 -> 3.2590017e+10 | H38: 33 | I38: {=SUMPRODUCT(($E$5:E8) * (E38:$E$41))} -> 7.7494014e+10 | K38: =I38/$J$5 -> 0.027792814
B39: jul | C39: =GETPIVOTDATA("Sum of Orders TOTAL",'Aggregated Data'!$B$3,"Meses (Date)",7,"Trimestres (Date)",3,"Años (Date)",2024) -> 662100 | E39: =C39-$D$5 -> -175192.05 | F39: =E39^2 -> 3.0692256e+10 | H39: 34 | I39: {=SUMPRODUCT(($E$5:E7) * (E39:$E$41))} -> 3.9855767e+10 | K39: =I39/$J$5 -> 0.014294058
B40: ago | C40: =GETPIVOTDATA("Sum of Orders TOTAL",'Aggregated Data'!$B$3,"Meses (Date)",8,"Trimestres (Date)",3,"Años (Date)",2024) -> 879063 | E40: =C40-$D$5 -> 41770.946 | F40: =E40^2 -> 1.7448119e+09 | H40: 35 | I40: {=SUMPRODUCT(($E$5:E6) * (E40:$E$41))} -> 12802981 | K40: =I40/$J$5 -> 4.5917207e-06
B41: sep | C41: =GETPIVOTDATA("Sum of Orders TOTAL",'Aggregated Data'!$B$3,"Meses (Date)",9,"Trimestres (Date)",3,"Años (Date)",2024) -> 930831 | E41: =C41-$D$5 -> 93538.946 | F41: =E41^2 -> 8.7495344e+09 | H41: 36 | I41: {=SUMPRODUCT(($E$5:E5) * (E41:$E$41))} -> -2.323606e+09 | K41: =I41/$J$5 -> -0.00083334889

Sheet Autocorrelation Black
A1: Date | B1: Orders | C1: Lag | D1: ACF Coefficient R
A2: 45562 | B2: =Table3[[#This Row],[Combined Daily order]] -> #VALUE! | C2: 0 | D2: 1 | F2: mean | G2: {=SUMPRODUCT(B$2:B$804-F$3,B2:B804-F$3)} -> #VALUE! | H2: {=SUMPRODUCT(B$2:B2-F$3,B$2:B2-F$3)} -> #VALUE! | I2: {=SUMPRODUCT(B2:B$804-F$3,B2:B$804-F$3)} -> #VALUE! | J2: =G2/I$2 -> #VALUE!
A3: 45561 | B3: =Table3[[#This Row],[Combined Daily order]] -> #VALUE! | C3: 1 | D3: {=SUMPRODUCT(OFFSET($B$2:$B$804,0,0,803-C3)-AVERAGE($B$2:$B$804),OFFSET($B$2:$B$804,C3,0,803-C3)-AVERAGE($B$2:$B$804))/DEVSQ($B$2:$B$804)} -> #VALUE! | F3: =AVERAGE(B2,B804) -> #VALUE! | G3: {=SUMPRODUCT(B$2:B$804-F$3,B3:B805-F$3)} -> #VALUE! | H3: {=SUMPRODUCT(B$2:B3-F$3,B$2:B3-F$3)} -> #VALUE! | I3: {=SUMPRODUCT(B3:B$804-F$3,B3:B$804-F$3)} -> #VALUE! | J3: =G3/I$2 -> #VALUE!
A4: 45560 | B4: =Table3[[#This Row],[Combined Daily order]] -> 25910 | C4: 2 | D4: {=SUMPRODUCT(OFFSET($B$2:$B$804,0,0,803-C4)-AVERAGE($B$2:$B$804),OFFSET($B$2:$B$804,C4,0,803-C4)-AVERAGE($B$2:$B$804))/DEVSQ($B$2:$B$804)} -> #VALUE! | G4: {=SUMPRODUCT(B$2:B$804-F$3,B4:B806-F$3)} -> #VALUE! | H4: {=SUMPRODUCT(B$2:B4-F$3,B$2:B4-F$3)} -> #VALUE! | I4: {=SUMPRODUCT(B4:B$804-F$3,B4:B$804-F$3)} -> #VALUE! | J4: =G4/I$2 -> #VALUE!
A5: 45559 | B5: =AVERAGE(B4,B6) -> 25989 | C5: 3 | D5: {=SUMPRODUCT(OFFSET($B$2:$B$804,0,0,803-C5)-AVERAGE($B$2:$B$804),OFFSET($B$2:$B$804,C5,0,803-C5)-AVERAGE($B$2:$B$804))/DEVSQ($B$2:$B$804)} -> #VALUE! | G5: {=SUMPRODUCT(B$2:B$804-F$3,B5:B807-F$3)} -> #VALUE! | H5: {=SUMPRODUCT(B$2:B5-F$3,B$2:B5-F$3)} -> #VALUE! | I5: {=SUMPRODUCT(B5:B$804-F$3,B5:B$804-F$3)} -> #VALUE! | J5: =G5/I$2 -> #VALUE!
A6: 45558 | B6: =Table3[[#This Row],[Combined Daily order]] -> 26068 | C6: 4 | D6: {=SUMPRODUCT(OFFSET($B$2:$B$804,0,0,803-C6)-AVERAGE($B$2:$B$804),OFFSET($B$2:$B$804,C6,0,803-C6)-AVERAGE($B$2:$B$804))/DEVSQ($B$2:$B$804)} -> #VALUE! | G6: {=SUMPRODUCT(B$2:B$804-F$3,B6:B808-F$3)} -> #VALUE! | H6: {=SUMPRODUCT(B$2:B6-F$3,B$2:B6-F$3)} -> #VALUE! | I6: {=SUMPRODUCT(B6:B$804-F$3,B6:B$804-F$3)} -> #VALUE! | J6: =G6/I$2 -> #VALUE!
A7: 45555 | B7: =Table3[[#This Row],[Combined Daily order]] -> 40865 | C7: 5 | D7: {=SUMPRODUCT(OFFSET($B$2:$B$804,0,0,803-C7)-AVERAGE($B$2:$B$804),OFFSET($B$2:$B$804,C7,0,803-C7)-AVERAGE($B$2:$B$804))/DEVSQ($B$2:$B$804)} -> #VALUE! | G7: {=SUMPRODUCT(B$2:B$804-F$3,B7:B809-F$3)} -> #VALUE! | H7: {=SUMPRODUCT(B$2:B7-F$3,B$2:B7-F$3)} -> #VALUE! | I7: {=SUMPRODUCT(B7:B$804-F$3,B7:B$804-F$3)} -> #VALUE! | J7: =G7/I$2 -> #VALUE!
A8: 45554 | B8: =Table3[[#This Row],[Combined Daily order]] -> 27032 | C8: 6 | D8: {=SUMPRODUCT(OFFSET($B$2:$B$804,0,0,803-C8)-AVERAGE($B$2:$B$804),OFFSET($B$2:$B$804,C8,0,803-C8)-AVERAGE($B$2:$B$804))/DEVSQ($B$2:$B$804)} -> #VALUE! | G8: {=SUMPRODUCT(B$2:B$804-F$3,B8:B810-F$3)} -> #VALUE! | H8: {=SUMPRODUCT(B$2:B8-F$3,B$2:B8-F$3)} -> #VALUE! | I8: {=SUMPRODUCT(B8:B$804-F$3,B8:B$804-F$3)} -> #VALUE! | J8: =G8/I$2 -> #VALUE!
A9: 45553 | B9: =Table3[[#This Row],[Combined Daily order]] -> 25465 | C9: 7 | D9: {=SUMPRODUCT(OFFSET($B$2:$B$804,0,0,803-C9)-AVERAGE($B$2:$B$804),OFFSET($B$2:$B$804,C9,0,803-C9)-AVERAGE($B$2:$B$804))/DEVSQ($B$2:$B$804)} -> #VALUE! | G9: {=SUMPRODUCT(B$2:B$804-F$3,B9:B811-F$3)} -> #VALUE! | H9: {=SUMPRODUCT(B$2:B9-F$3,B$2:B9-F$3)} -> #VALUE! | I9: {=SUMPRODUCT(B9:B$804-F$3,B9:B$804-F$3)} -> #VALUE! | J9: =G9/I$2 -> #VALUE!
A10: 45552 | B10: =Table3[[#This Row],[Combined Daily order]] -> 36114 | C10: 8 | D10: {=SUMPRODUCT(OFFSET($B$2:$B$804,0,0,803-C10)-AVERAGE($B$2:$B$804),OFFSET($B$2:$B$804,C10,0,803-C10)-AVERAGE($B$2:$B$804))/DEVSQ($B$2:$B$804)} -> #VALUE! | G10: {=SUMPRODUCT(B$2:B$804-F$3,B10:B812-F$3)} -> #VALUE! | H10: {=SUMPRODUCT(B$2:B10-F$3,B$2:B10-F$3)} -> #VALUE! | I10: {=SUMPRODUCT(B10:B$804-F$3,B10:B$804-F$3)} -> #VALUE! | J10: =G10/I$2 -> #VALUE!
A11: 45551 | B11: =Table3[[#This Row],[Combined Daily order]] -> 25049 | C11: 9 | D11: {=SUMPRODUCT(OFFSET($B$2:$B$804,0,0,803-C11)-AVERAGE($B$2:$B$804),OFFSET($B$2:$B$804,C11,0,803-C11)-AVERAGE($B$2:$B$804))/DEVSQ($B$2:$B$804)} -> #VALUE! | G11: {=SUMPRODUCT(B$2:B$804-F$3,B11:B813-F$3)} -> #VALUE! | H11: {=SUMPRODUCT(B$2:B11-F$3,B$2:B11-F$3)} -> #VALUE! | I11: {=SUMPRODUCT(B11:B$804-F$3,B11:B$804-F$3)} -> #VALUE! | J11: =G11/I$2 -> #VALUE!
A12: 45548 | B12: =Table3[[#This Row],[Combined Daily order]] -> 36767 | C12: 10 | D12: {=SUMPRODUCT(OFFSET($B$2:$B$804,0,0,803-C12)-AVERAGE($B$2:$B$804),OFFSET($B$2:$B$804,C12,0,803-C12)-AVERAGE($B$2:$B$804))/DEVSQ($B$2:$B$804)} -> #VALUE! | G12: {=SUMPRODUCT(B$2:B$804-F$3,B12:B814-F$3)} -> #VALUE! | H12: {=SUMPRODUCT(B$2:B12-F$3,B$2:B12-F$3)} -> #VALUE! | I12: {=SUMPRODUCT(B12:B$804-F$3,B12:B$804-F$3)} -> #VALUE! | J12: =G12/I$2 -> #VALUE!
A13: 45547 | B13: =Table3[[#This Row],[Combined Daily order]] -> 27301 | C13: 11 | D13: {=SUMPRODUCT(OFFSET($B$2:$B$804,0,0,803-C13)-AVERAGE($B$2:$B$804),OFFSET($B$2:$B$804,C13,0,803-C13)-AVERAGE($B$2:$B$804))/DEVSQ($B$2:$B$804)} -> #VALUE! | G13: {=SUMPRODUCT(B$2:B$804-F$3,B13:B815-F$3)} -> #VALUE! | H13: {=SUMPRODUCT(B$2:B13-F$3,B$2:B13-F$3)} -> #VALUE! | I13: {=SUMPRODUCT(B13:B$804-F$3,B13:B$804-F$3)} -> #VALUE! | J13: =G13/I$2 -> #VALUE!
A14: 45546 | B14: =Table3[[#This Row],[Combined Daily order]] -> 35320 | C14: 12 | D14: {=SUMPRODUCT(OFFSET($B$2:$B$804,0,0,803-C14)-AVERAGE($B$2:$B$804),OFFSET($B$2:$B$804,C14,0,803-C14)-AVERAGE($B$2:$B$804))/DEVSQ($B$2:$B$804)} -> #VALUE! | G14: {=SUMPRODUCT(B$2:B$804-F$3,B14:B816-F$3)} -> #VALUE! | H14: {=SUMPRODUCT(B$2:B14-F$3,B$2:B14-F$3)} -> #VALUE! | I14: {=SUMPRODUCT(B14:B$804-F$3,B14:B$804-F$3)} -> #VALUE! | J14: =G14/I$2 -> #VALUE!
A15: 45545 | B15: =Table3[[#This Row],[Combined Daily order]] -> 25240 | C15: 13 | D15: {=SUMPRODUCT(OFFSET($B$2:$B$804,0,0,803-C15)-AVERAGE($B$2:$B$804),OFFSET($B$2:$B$804,C15,0,803-C15)-AVERAGE($B$2:$B$804))/DEVSQ($B$2:$B$804)} -> #VALUE! | G15: {=SUMPRODUCT(B$2:B$804-F$3,B15:B817-F$3)} -> #VALUE! | H15: {=SUMPRODUCT(B$2:B15-F$3,B$2:B15-F$3)} -> #VALUE! | I15: {=SUMPRODUCT(B15:B$804-F$3,B15:B$804-F$3)} -> #VALUE! | J15: =G15/I$2 -> #VALUE!
A16: 45544 | B16: =Table3[[#This Row],[Combined Daily order]] -> 39060 | C16: 14 | D16: {=SUMPRODUCT(OFFSET($B$2:$B$804,0,0,803-C16)-AVERAGE($B$2:$B$804),OFFSET($B$2:$B$804,C16,0,803-C16)-AVERAGE($B$2:$B$804))/DEVSQ($B$2:$B$804)} -> #VALUE! | G16: {=SUMPRODUCT(B$2:B$804-F$3,B16:B818-F$3)} -> #VALUE! | H16: {=SUMPRODUCT(B$2:B16-F$3,B$2:B16-F$3)} -> #VALUE! | I16: {=SUMPRODUCT(B16:B$804-F$3,B16:B$804-F$3)} -> #VALUE! | J16: =G16/I$2 -> #VALUE!
A17: 45541 | B17: =AVERAGE(B16,B18) -> 32905.5 | C17: 15 | D17: {=SUMPRODUCT(OFFSET($B$2:$B$804,0,0,803-C17)-AVERAGE($B$2:$B$804),OFFSET($B$2:$B$804,C17,0,803-C17)-AVERAGE($B$2:$B$804))/DEVSQ($B$2:$B$804)} -> #VALUE! | G17: {=SUMPRODUCT(B$2:B$804-F$3,B17:B819-F$3)} -> #VALUE! | H17: {=SUMPRODUCT(B$2:B17-F$3,B$2:B17-F$3)} -> #VALUE! | I17: {=SUMPRODUCT(B17:B$804-F$3,B17:B$804-F$3)} -> #VALUE! | J17: =G17/I$2 -> #VALUE!
A18: 45540 | B18: =Table3[[#This Row],[Combined Daily order]] -> 26751 | C18: 16 | D18: {=SUMPRODUCT(OFFSET($B$2:$B$804,0,0,803-C18)-AVERAGE($B$2:$B$804),OFFSET($B$2:$B$804,C18,0,803-C18)-AVERAGE($B$2:$B$804))/DEVSQ($B$2:$B$804)} -> #VALUE! | G18: {=SUMPRODUCT(B$2:B$804-F$3,B18:B820-F$3)} -> #VALUE! | H18: {=SUMPRODUCT(B$2:B18-F$3,B$2:B18-F$3)} -> #VALUE! | I18: {=SUMPRODUCT(B18:B$804-F$3,B18:B$804-F$3)} -> #VALUE! | J18: =G18/I$2 -> #VALUE!
A19: 45539 | B19: =Table3[[#This Row],[Combined Daily order]] -> 42169 | C19: 17 | D19: {=SUMPRODUCT(OFFSET($B$2:$B$804,0,0,803-C19)-AVERAGE($B$2:$B$804),OFFSET($B$2:$B$804,C19,0,803-C19)-AVERAGE($B$2:$B$804))/DEVSQ($B$2:$B$804)} -> #VALUE! | G19: {=SUMPRODUCT(B$2:B$804-F$3,B19:B821-F$3)} -> #VALUE! | H19: {=SUMPRODUCT(B$2:B19-F$3,B$2:B19-F$3)} -> #VALUE! | I19: {=SUMPRODUCT(B19:B$804-F$3,B19:B$804-F$3)} -> #VALUE! | J19: =G19/I$2 -> #VALUE!
A20: 45538 | B20: =Table3[[#This Row],[Combined Daily order]] -> 24206 | C20: 18 | D20: {=SUMPRODUCT(OFFSET($B$2:$B$804,0,0,803-C20)-AVERAGE($B$2:$B$804),OFFSET($B$2:$B$804,C20,0,803-C20)-AVERAGE($B$2:$B$804))/DEVSQ($B$2:$B$804)} -> #VALUE! | G20: {=SUMPRODUCT(B$2:B$804-F$3,B20:B822-F$3)} -> #VALUE! | H20: {=SUMPRODUCT(B$2:B20-F$3,B$2:B20-F$3)} -> #VALUE! | I20: {=SUMPRODUCT(B20:B$804-F$3,B20:B$804-F$3)} -> #VALUE! | J20: =G20/I$2 -> #VALUE!
A21: 45537 | B21: =Table3[[#This Row],[Combined Daily order]] -> 39550 | C21: 19 | D21: {=SUMPRODUCT(OFFSET($B$2:$B$804,0,0,803-C21)-AVERAGE($B$2:$B$804),OFFSET($B$2:$B$804,C21,0,803-C21)-AVERAGE($B$2:$B$804))/DEVSQ($B$2:$B$804)} -> #VALUE! | G21: {=SUMPRODUCT(B$2:B$804-F$3,B21:B823-F$3)} -> #VALUE! | H21: {=SUMPRODUCT(B$2:B21-F$3,B$2:B21-F$3)} -> #VALUE! | I21: {=SUMPRODUCT(B21:B$804-F$3,B21:B$804-F$3)} -> #VALUE! | J21: =G21/I$2 -> #VALUE!
A22: 45534 | B22: =Table3[[#This Row],[Combined Daily order]] -> 24805 | C22: 20 | D22: {=SUMPRODUCT(OFFSET($B$2:$B$804,0,0,803-C22)-AVERAGE($B$2:$B$804),OFFSET($B$2:$B$804,C22,0,803-C22)-AVERAGE($B$2:$B$804))/DEVSQ($B$2:$B$804)} -> #VALUE! | G22: {=SUMPRODUCT(B$2:B$804-F$3,B22:B824-F$3)} -> #VALUE! | H22: {=SUMPRODUCT(B$2:B22-F$3,B$2:B22-F$3)} -> #VALUE! | I22: {=SUMPRODUCT(B22:B$804-F$3,B22:B$804-F$3)} -> #VALUE! | J22: =G22/I$2 -> #VALUE!
A23: 45533 | B23: =Table3[[#This Row],[Combined Daily order]] -> 38326 | C23: 21 | D23: {=SUMPRODUCT(OFFSET($B$2:$B$804,0,0,803-C23)-AVERAGE($B$2:$B$804),OFFSET($B$2:$B$804,C23,0,803-C23)-AVERAGE($B$2:$B$804))/DEVSQ($B$2:$B$804)} -> #VALUE! | G23: {=SUMPRODUCT(B$2:B$804-F$3,B23:B825-F$3)} -> #VALUE! | H23: {=SUMPRODUCT(B$2:B23-F$3,B$2:B23-F$3)} -> #VALUE! | I23: {=SUMPRODUCT(B23:B$804-F$3,B23:B$804-F$3)} -> #VALUE! | J23: =G23/I$2 -> #VALUE!
A24: 45532 | B24: =Table3[[#This Row],[Combined Daily order]] -> 23906 | C24: 22 | D24: {=SUMPRODUCT(OFFSET($B$2:$B$804,0,0,803-C24)-AVERAGE($B$2:$B$804),OFFSET($B$2:$B$804,C24,0,803-C24)-AVERAGE($B$2:$B$804))/DEVSQ($B$2:$B$804)} -> #VALUE! | G24: {=SUMPRODUCT(B$2:B$804-F$3,B24:B826-F$3)} -> #VALUE! | H24: {=SUMPRODUCT(B$2:B24-F$3,B$2:B24-F$3)} -> #VALUE! | I24: {=SUMPRODUCT(B24:B$804-F$3,B24:B$804-F$3)} -> #VALUE! | J24: =G24/I$2 -> #VALUE!
A25: 45531 | B25: =Table3[[#This Row],[Combined Daily order]] -> 35106 | C25: 23 | D25: {=SUMPRODUCT(OFFSET($B$2:$B$804,0,0,803-C25)-AVERAGE($B$2:$B$804),OFFSET($B$2:$B$804,C25,0,803-C25)-AVERAGE($B$2:$B$804))/DEVSQ($B$2:$B$804)} -> #VALUE! | G25: {=SUMPRODUCT(B$2:B$804-F$3,B25:B827-F$3)} -> #VALUE! | H25: {=SUMPRODUCT(B$2:B25-F$3,B$2:B25-F$3)} -> #VALUE! | I25: {=SUMPRODUCT(B25:B$804-F$3,B25:B$804-F$3)} -> #VALUE! | J25: =G25/I$2 -> #VALUE!
A26: 45530 | B26: =Table3[[#This Row],[Combined Daily order]] -> 22341 | C26: 24 | D26: {=SUMPRODUCT(OFFSET($B$2:$B$804,0,0,803-C26)-AVERAGE($B$2:$B$804),OFFSET($B$2:$B$804,C26,0,803-C26)-AVERAGE($B$2:$B$804))/DEVSQ($B$2:$B$804)} -> #VALUE! | G26: {=SUMPRODUCT(B$2:B$804-F$3,B26:B828-F$3)} -> #VALUE! | H26: {=SUMPRODUCT(B$2:B26-F$3,B$2:B26-F$3)} -> #VALUE! | I26: {=SUMPRODUCT(B26:B$804-F$3,B26:B$804-F$3)} -> #VALUE! | J26: =G26/I$2 -> #VALUE!
A27: 45527 | B27: =Table3[[#This Row],[Combined Daily order]] -> 36157 | C27: 25 | D27: {=SUMPRODUCT(OFFSET($B$2:$B$804,0,0,803-C27)-AVERAGE($B$2:$B$804),OFFSET($B$2:$B$804,C27,0,803-C27)-AVERAGE($B$2:$B$804))/DEVSQ($B$2:$B$804)} -> #VALUE! | G27: {=SUMPRODUCT(B$2:B$804-F$3,B27:B829-F$3)} -> #VALUE! | H27: {=SUMPRODUCT(B$2:B27-F$3,B$2:B27-F$3)} -> #VALUE! | I27: {=SUMPRODUCT(B27:B$804-F$3,B27:B$804-F$3)} -> #VALUE! | J27: =G27/I$2 -> #VALUE!
A28: 45526 | B28: =Table3[[#This Row],[Combined Daily order]] -> 24171 | C28: 26 | D28: {=SUMPRODUCT(OFFSET($B$2:$B$804,0,0,803-C28)-AVERAGE($B$2:$B$804),OFFSET($B$2:$B$804,C28,0,803-C28)-AVERAGE($B$2:$B$804))/DEVSQ($B$2:$B$804)} -> #VALUE! | G28: {=SUMPRODUCT(B$2:B$804-F$3,B28:B830-F$3)} -> #VALUE! | H28: {=SUMPRODUCT(B$2:B28-F$3,B$2:B28-F$3)} -> #VALUE! | I28: {=SUMPRODUCT(B28:B$804-F$3,B28:B$804-F$3)} -> #VALUE! | J28: =G28/I$2 -> #VALUE!
A29: 45525 | B29: =Table3[[#This Row],[Combined Daily order]] -> 33437 | C29: 27 | D29: {=SUMPRODUCT(OFFSET($B$2:$B$804,0,0,803-C29)-AVERAGE($B$2:$B$804),OFFSET($B$2:$B$804,C29,0,803-C29)-AVERAGE($B$2:$B$804))/DEVSQ($B$2:$B$804)} -> #VALUE! | G29: {=SUMPRODUCT(B$2:B$804-F$3,B29:B831-F$3)} -> #VALUE! | H29: {=SUMPRODUCT(B$2:B29-F$3,B$2:B29-F$3)} -> #VALUE! | I29: {=SUMPRODUCT(B29:B$804-F$3,B29:B$804-F$3)} -> #VALUE! | J29: =G29/I$2 -> #VALUE!
... A191: 45299 | B191: =Table3[[#This Row],[Combined Daily order]] -> 21954 | C191: 189 | D191: {=SUMPRODUCT(OFFSET($B$2:$B$804,0,0,803-C191)-AVERAGE($B$2:$B$804),OFFSET($B$2:$B$804,C191,0,803-C191)-AVERAGE($B$2:$B$804))/DEVSQ($B$2:$B$804)} -> #VALUE! | G191: {=SUMPRODUCT(B$2:B$804-F$3,B191:B993-F$3)} -> #VALUE! | H191: {=SUMPRODUCT(B$2:B191-F$3,B$2:B191-F$3)} -> #VALUE! | I191: {=SUMPRODUCT(B191:B$804-F$3,B191:B$804-F$3)} -> #VALUE! | J191: =G191/I$2 -> #VALUE!
A192: 45296 | B192: =AVERAGE(B191,B193) -> 22252.5 | C192: 190 | D192: {=SUMPRODUCT(OFFSET($B$2:$B$804,0,0,803-C192)-AVERAGE($B$2:$B$804),OFFSET($B$2:$B$804,C192,0,803-C192)-AVERAGE($B$2:$B$804))/DEVSQ($B$2:$B$804)} -> #VALUE! | G192: {=SUMPRODUCT(B$2:B$804-F$3,B192:B994-F$3)} -> #VALUE! | H192: {=SUMPRODUCT(B$2:B192-F$3,B$2:B192-F$3)} -> #VALUE! | I192: {=SUMPRODUCT(B192:B$804-F$3,B192:B$804-F$3)} -> #VALUE! | J192: =G192/I$2 -> #VALUE!
A193: 45295 | B193: =Table3[[#This Row],[Combined Daily order]] -> 22551 | C193: 191 | D193: {=SUMPRODUCT(OFFSET($B$2:$B$804,0,0,803-C193)-AVERAGE($B$2:$B$804),OFFSET($B$2:$B$804,C193,0,803-C193)-AVERAGE($B$2:$B$804))/DEVSQ($B$2:$B$804)} -> #VALUE! | G193: {=SUMPRODUCT(B$2:B$804-F$3,B193:B995-F$3)} -> #VALUE! | H193: {=SUMPRODUCT(B$2:B193-F$3,B$2:B193-F$3)} -> #VALUE! | I193: {=SUMPRODUCT(B193:B$804-F$3,B193:B$804-F$3)} -> #VALUE! | J193: =G193/I$2 -> #VALUE!
A194: 45294 | B194: =AVERAGE(B193,B195) -> 24096 | C194: 192 | D194: {=SUMPRODUCT(OFFSET($B$2:$B$804,0,0,803-C194)-AVERAGE($B$2:$B$804),OFFSET($B$2:$B$804,C194,0,803-C194)-AVERAGE($B$2:$B$804))/DEVSQ($B$2:$B$804)} -> #VALUE! | G194: {=SUMPRODUCT(B$2:B$804-F$3,B194:B996-F$3)} -> #VALUE! | H194: {=SUMPRODUCT(B$2:B194-F$3,B$2:B194-F$3)} -> #VALUE! | I194: {=SUMPRODUCT(B194:B$804-F$3,B194:B$804-F$3)} -> #VALUE! | J194: =G194/I$2 -> #VALUE!
A195: 45293 | B195: =Table3[[#This Row],[Combined Daily order]] -> 25641 | C195: 193 | D195: {=SUMPRODUCT(OFFSET($B$2:$B$804,0,0,803-C195)-AVERAGE($B$2:$B$804),OFFSET($B$2:$B$804,C195,0,803-C195)-AVERAGE($B$2:$B$804))/DEVSQ($B$2:$B$804)} -> #VALUE! | G195: {=SUMPRODUCT(B$2:B$804-F$3,B195:B997-F$3)} -> #VALUE! | H195: {=SUMPRODUCT(B$2:B195-F$3,B$2:B195-F$3)} -> #VALUE! | I195: {=SUMPRODUCT(B195:B$804-F$3,B195:B$804-F$3)} -> #VALUE! | J195: =G195/I$2 -> #VALUE!
A196: 45292 | B196: =AVERAGE(B195,B197) -> 27051 | C196: 194 | D196: {=SUMPRODUCT(OFFSET($B$2:$B$804,0,0,803-C196)-AVERAGE($B$2:$B$804),OFFSET($B$2:$B$804,C196,0,803-C196)-AVERAGE($B$2:$B$804))/DEVSQ($B$2:$B$804)} -> #VALUE! | G196: {=SUMPRODUCT(B$2:B$804-F$3,B196:B998-F$3)} -> #VALUE! | H196: {=SUMPRODUCT(B$2:B196-F$3,B$2:B196-F$3)} -> #VALUE! | I196: {=SUMPRODUCT(B196:B$804-F$3,B196:B$804-F$3)} -> #VALUE! | J196: =G196/I$2 -> #VALUE!
A197: 45289 | B197: =Table3[[#This Row],[Combined Daily order]] -> 28461 | C197: 195 | D197: {=SUMPRODUCT(OFFSET($B$2:$B$804,0,0,803-C197)-AVERAGE($B$2:$B$804),OFFSET($B$2:$B$804,C197,0,803-C197)-AVERAGE($B$2:$B$804))/DEVSQ($B$2:$B$804)} -> #VALUE! | G197: {=SUMPRODUCT(B$2:B$804-F$3,B197:B999-F$3)} -> #VALUE! | H197: {=SUMPRODUCT(B$2:B197-F$3,B$2:B197-F$3)} -> #VALUE! | I197: {=SUMPRODUCT(B197:B$804-F$3,B197:B$804-F$3)} -> #VALUE! | J197: =G197/I$2 -> #VALUE!
A198: 45288 | B198: =Table3[[#This Row],[Combined Daily order]] -> 42191 | C198: 196 | D198: {=SUMPRODUCT(OFFSET($B$2:$B$804,0,0,803-C198)-AVERAGE($B$2:$B$804),OFFSET($B$2:$B$804,C198,0,803-C198)-AVERAGE($B$2:$B$804))/DEVSQ($B$2:$B$804)} -> #VALUE! | G198: {=SUMPRODUCT(B$2:B$804-F$3,B198:B1000-F$3)} -> #VALUE! | H198: {=SUMPRODUCT(B$2:B198-F$3,B$2:B198-F$3)} -> #VALUE! | I198: {=SUMPRODUCT(B198:B$804-F$3,B198:B$804-F$3)} -> #VALUE! | J198: =G198/I$2 -> #VALUE!
A199: 45287 | B199: =Table3[[#This Row],[Combined Daily order]] -> 32667 | C199: 197 | D199: {=SUMPRODUCT(OFFSET($B$2:$B$804,0,0,803-C199)-AVERAGE($B$2:$B$804),OFFSET($B$2:$B$804,C199,0,803-C199)-AVERAGE($B$2:$B$804))/DEVSQ($B$2:$B$804)} -> #VALUE! | G199: {=SUMPRODUCT(B$2:B$804-F$3,B199:B1001-F$3)} -> #VALUE! | H199: {=SUMPRODUCT(B$2:B199-F$3,B$2:B199-F$3)} -> #VALUE! | I199: {=SUMPRODUCT(B199:B$804-F$3,B199:B$804-F$3)} -> #VALUE! | J199: =G199/I$2 -> #VALUE!
A200: 45286 | B200: =Table3[[#This Row],[Combined Daily order]] -> 46651 | C200: 198 | D200: {=SUMPRODUCT(OFFSET($B$2:$B$804,0,0,803-C200)-AVERAGE($B$2:$B$804),OFFSET($B$2:$B$804,C200,0,803-C200)-AVERAGE($B$2:$B$804))/DEVSQ($B$2:$B$804)} -> #VALUE! | G200: {=SUMPRODUCT(B$2:B$804-F$3,B200:B1002-F$3)} -> #VALUE! | H200: {=SUMPRODUCT(B$2:B200-F$3,B$2:B200-F$3)} -> #VALUE! | I200: {=SUMPRODUCT(B200:B$804-F$3,B200:B$804-F$3)} -> #VALUE! | J200: =G200/I$2 -> #VALUE!
A201: 45285 | B201: =Table3[[#This Row],[Combined Daily order]] -> 33123 | C201: 199 | D201: {=SUMPRODUCT(OFFSET($B$2:$B$804,0,0,803-C201)-AVERAGE($B$2:$B$804),OFFSET($B$2:$B$804,C201,0,803-C201)-AVERAGE($B$2:$B$804))/DEVSQ($B$2:$B$804)} -> #VALUE! | G201: {=SUMPRODUCT(B$2:B$804-F$3,B201:B1003-F$3)} -> #VALUE! | H201: {=SUMPRODUCT(B$2:B201-F$3,B$2:B201-F$3)} -> #VALUE! | I201: {=SUMPRODUCT(B201:B$804-F$3,B201:B$804-F$3)} -> #VALUE! | J201: =G201/I$2 -> #VALUE!
A202: 45282 | B202: =Table3[[#This Row],[Combined Daily order]] -> 52401 | C202: 200 | D202: {=SUMPRODUCT(OFFSET($B$2:$B$804,0,0,803-C202)-AVERAGE($B$2:$B$804),OFFSET($B$2:$B$804,C202,0,803-C202)-AVERAGE($B$2:$B$804))/DEVSQ($B$2:$B$804)} -> #VALUE! | G202: {=SUMPRODUCT(B$2:B$804-F$3,B202:B1004-F$3)} -> #VALUE! | H202: {=SUMPRODUCT(B$2:B202-F$3,B$2:B202-F$3)} -> #VALUE! | I202: {=SUMPRODUCT(B202:B$804-F$3,B202:B$804-F$3)} -> #VALUE! | J202: =G202/I$2 -> #VALUE!
A203: 45281 | B203: =Table3[[#This Row],[Combined Daily order]] -> 34112 | C203: 201 | D203: {=SUMPRODUCT(OFFSET($B$2:$B$804,0,0,803-C203)-AVERAGE($B$2:$B$804),OFFSET($B$2:$B$804,C203,0,803-C203)-AVERAGE($B$2:$B$804))/DEVSQ($B$2:$B$804)} -> #VALUE! | G203: {=SUMPRODUCT(B$2:B$804-F$3,B203:B1005-F$3)} -> #VALUE! | H203: {=SUMPRODUCT(B$2:B203-F$3,B$2:B203-F$3)} -> #VALUE! | I203: {=SUMPRODUCT(B203:B$804-F$3,B203:B$804-F$3)} -> #VALUE! | J203: =G203/I$2 -> #VALUE!
A204: 45280 | B204: =Table3[[#This Row],[Combined Daily order]] -> 58062 | C204: 202 | D204: {=SUMPRODUCT(OFFSET($B$2:$B$804,0,0,803-C204)-AVERAGE($B$2:$B$804),OFFSET($B$2:$B$804,C204,0,803-C204)-AVERAGE($B$2:$B$804))/DEVSQ($B$2:$B$804)} -> #VALUE! | G204: {=SUMPRODUCT(B$2:B$804-F$3,B204:B1006-F$3)} -> #VALUE! | H204: {=SUMPRODUCT(B$2:B204-F$3,B$2:B204-F$3)} -> #VALUE! | I204: {=SUMPRODUCT(B204:B$804-F$3,B204:B$804-F$3)} -> #VALUE! | J204: =G204/I$2 -> #VALUE!
A205: 45279 | B205: =Table3[[#This Row],[Combined Daily order]] -> 35552 | C205: 203 | D205: {=SUMPRODUCT(OFFSET($B$2:$B$804,0,0,803-C205)-AVERAGE($B$2:$B$804),OFFSET($B$2:$B$804,C205,0,803-C205)-AVERAGE($B$2:$B$804))/DEVSQ($B$2:$B$804)} -> #VALUE! | G205: {=SUMPRODUCT(B$2:B$804-F$3,B205:B1007-F$3)} -> #VALUE! | H205: {=SUMPRODUCT(B$2:B205-F$3,B$2:B205-F$3)} -> #VALUE! | I205: {=SUMPRODUCT(B205:B$804-F$3,B205:B$804-F$3)} -> #VALUE! | J205: =G205/I$2 -> #VALUE!
A206: 45278 | B206: =Table3[[#This Row],[Combined Daily order]] -> 59942 | C206: 204 | D206: {=SUMPRODUCT(OFFSET($B$2:$B$804,0,0,803-C206)-AVERAGE($B$2:$B$804),OFFSET($B$2:$B$804,C206,0,803-C206)-AVERAGE($B$2:$B$804))/DEVSQ($B$2:$B$804)} -> #VALUE! | G206: {=SUMPRODUCT(B$2:B$804-F$3,B206:B1008-F$3)} -> #VALUE! | H206: {=SUMPRODUCT(B$2:B206-F$3,B$2:B206-F$3)} -> #VALUE! | I206: {=SUMPRODUCT(B206:B$804-F$3,B206:B$804-F$3)} -> #VALUE! | J206: =G206/I$2 -> #VALUE!
A207: 45275 | B207: =Table3[[#This Row],[Combined Daily order]] -> 40854 | C207: 205 | D207: {=SUMPRODUCT(OFFSET($B$2:$B$804,0,0,803-C207)-AVERAGE($B$2:$B$804),OFFSET($B$2:$B$804,C207,0,803-C207)-AVERAGE($B$2:$B$804))/DEVSQ($B$2:$B$804)} -> #VALUE! | G207: {=SUMPRODUCT(B$2:B$804-F$3,B207:B1009-F$3)} -> #VALUE! | H207: {=SUMPRODUCT(B$2:B207-F$3,B$2:B207-F$3)} -> #VALUE! | I207: {=SUMPRODUCT(B207:B$804-F$3,B207:B$804-F$3)} -> #VALUE! | J207: =G207/I$2 -> #VALUE!
A208: 45274 | B208: =AVERAGE(B207,B209) -> 44006.5 | C208: 206 | D208: {=SUMPRODUCT(OFFSET($B$2:$B$804,0,0,803-C208)-AVERAGE($B$2:$B$804),OFFSET($B$2:$B$804,C208,0,803-C208)-AVERAGE($B$2:$B$804))/DEVSQ($B$2:$B$804)} -> #VALUE! | G208: {=SUMPRODUCT(B$2:B$804-F$3,B208:B1010-F$3)} -> #VALUE! | H208: {=SUMPRODUCT(B$2:B208-F$3,B$2:B208-F$3)} -> #VALUE! | I208: {=SUMPRODUCT(B208:B$804-F$3,B208:B$804-F$3)} -> #VALUE! | J208: =G208/I$2 -> #VALUE!
A209: 45273 | B209: =Table3[[#This Row],[Combined Daily order]] -> 47159 | C209: 207 | D209: {=SUMPRODUCT(OFFSET($B$2:$B$804,0,0,803-C209)-AVERAGE($B$2:$B$804),OFFSET($B$2:$B$804,C209,0,803-C209)-AVERAGE($B$2:$B$804))/DEVSQ($B$2:$B$804)} -> #VALUE! | G209: {=SUMPRODUCT(B$2:B$804-F$3,B209:B1011-F$3)} -> #VALUE! | H209: {=SUMPRODUCT(B$2:B209-F$3,B$2:B209-F$3)} -> #VALUE! | I209: {=SUMPRODUCT(B209:B$804-F$3,B209:B$804-F$3)} -> #VALUE! | J209: =G209/I$2 -> #VALUE!
A210: 45272 | B210: =Table3[[#This Row],[Combined Daily order]] -> 68328 | C210: 208 | D210: {=SUMPRODUCT(OFFSET($B$2:$B$804,0,0,803-C210)-AVERAGE($B$2:$B$804),OFFSET($B$2:$B$804,C210,0,803-C210)-AVERAGE($B$2:$B$804))/DEVSQ($B$2:$B$804)} -> #VALUE! | G210: {=SUMPRODUCT(B$2:B$804-F$3,B210:B1012-F$3)} -> #VALUE! | H210: {=SUMPRODUCT(B$2:B210-F$3,B$2:B210-F$3)} -> #VALUE! | I210: {=SUMPRODUCT(B210:B$804-F$3,B210:B$804-F$3)} -> #VALUE! | J210: =G210/I$2 -> #VALUE!
A211: 45271 | B211: =Table3[[#This Row],[Combined Daily order]] -> 44155 | C211: 209 | D211: {=SUMPRODUCT(OFFSET($B$2:$B$804,0,0,803-C211)-AVERAGE($B$2:$B$804),OFFSET($B$2:$B$804,C211,0,803-C211)-AVERAGE($B$2:$B$804))/DEVSQ($B$2:$B$804)} -> #VALUE! | G211: {=SUMPRODUCT(B$2:B$804-F$3,B211:B1013-F$3)} -> #VALUE! | H211: {=SUMPRODUCT(B$2:B211-F$3,B$2:B211-F$3)} -> #VALUE! | I211: {=SUMPRODUCT(B211:B$804-F$3,B211:B$804-F$3)} -> #VALUE! | J211: =G211/I$2 -> #VALUE!
A212: 45268 | B212: =Table3[[#This Row],[Combined Daily order]] -> 57283 | C212: 210 | D212: {=SUMPRODUCT(OFFSET($B$2:$B$804,0,0,803-C212)-AVERAGE($B$2:$B$804),OFFSET($B$2:$B$804,C212,0,803-C212)-AVERAGE($B$2:$B$804))/DEVSQ($B$2:$B$804)} -> #VALUE! | G212: {=SUMPRODUCT(B$2:B$804-F$3,B212:B1014-F$3)} -> #VALUE! | H212: {=SUMPRODUCT(B$2:B212-F$3,B$2:B212-F$3)} -> #VALUE! | I212: {=SUMPRODUCT(B212:B$804-F$3,B212:B$804-F$3)} -> #VALUE! | J212: =G212/I$2 -> #VALUE!
A213: 45267 | B213: =Table3[[#This Row],[Combined Daily order]] -> 44001 | C213: 211 | D213: {=SUMPRODUCT(OFFSET($B$2:$B$804,0,0,803-C213)-AVERAGE($B$2:$B$804),OFFSET($B$2:$B$804,C213,0,803-C213)-AVERAGE($B$2:$B$804))/DEVSQ($B$2:$B$804)} -> #VALUE! | G213: {=SUMPRODUCT(B$2:B$804-F$3,B213:B1015-F$3)} -> #VALUE! | H213: {=SUMPRODUCT(B$2:B213-F$3,B$2:B213-F$3)} -> #VALUE! | I213: {=SUMPRODUCT(B213:B$804-F$3,B213:B$804-F$3)} -> #VALUE! | J213: =G213/I$2 -> #VALUE!
A214: 45266 | B214: =Table3[[#This Row],[Combined Daily order]] -> 63744 | C214: 212 | D214: {=SUMPRODUCT(OFFSET($B$2:$B$804,0,0,803-C214)-AVERAGE($B$2:$B$804),OFFSET($B$2:$B$804,C214,0,803-C214)-AVERAGE($B$2:$B$804))/DEVSQ($B$2:$B$804)} -> #VALUE! | G214: {=SUMPRODUCT(B$2:B$804-F$3,B214:B1016-F$3)} -> #VALUE! | H214: {=SUMPRODUCT(B$2:B214-F$3,B$2:B214-F$3)} -> #VALUE! | I214: {=SUMPRODUCT(B214:B$804-F$3,B214:B$804-F$3)} -> #VALUE! | J214: =G214/I$2 -> #VALUE!
A215: 45265 | B215: =Table3[[#This Row],[Combined Daily order]] -> 38632 | C215: 213 | D215: {=SUMPRODUCT(OFFSET($B$2:$B$804,0,0,803-C215)-AVERAGE($B$2:$B$804),OFFSET($B$2:$B$804,C215,0,803-C215)-AVERAGE($B$2:$B$804))/DEVSQ($B$2:$B$804)} -> #VALUE! | G215: {=SUMPRODUCT(B$2:B$804-F$3,B215:B1017-F$3)} -> #VALUE! | H215: {=SUMPRODUCT(B$2:B215-F$3,B$2:B215-F$3)} -> #VALUE! | I215: {=SUMPRODUCT(B215:B$804-F$3,B215:B$804-F$3)} -> #VALUE! | J215: =G215/I$2 -> #VALUE!
A216: 45264 | B216: =Table3[[#This Row],[Combined Daily order]] -> 60173 | C216: 214 | D216: {=SUMPRODUCT(OFFSET($B$2:$B$804,0,0,803-C216)-AVERAGE($B$2:$B$804),OFFSET($B$2:$B$804,C216,0,803-C216)-AVERAGE($B$2:$B$804))/DEVSQ($B$2:$B$804)} -> #VALUE! | G216: {=SUMPRODUCT(B$2:B$804-F$3,B216:B1018-F$3)} -> #VALUE! | H216: {=SUMPRODUCT(B$2:B216-F$3,B$2:B216-F$3)} -> #VALUE! | I216: {=SUMPRODUCT(B216:B$804-F$3,B216:B$804-F$3)} -> #VALUE! | J216: =G216/I$2 -> #VALUE!
A217: 45261 | B217: =Table3[[#This Row],[Combined Daily order]] -> 41855 | C217: 215 | D217: {=SUMPRODUCT(OFFSET($B$2:$B$804,0,0,803-C217)-AVERAGE($B$2:$B$804),OFFSET($B$2:$B$804,C217,0,803-C217)-AVERAGE($B$2:$B$804))/DEVSQ($B$2:$B$804)} -> #VALUE! | G217: {=SUMPRODUCT(B$2:B$804-F$3,B217:B1019-F$3)} -> #VALUE! | H217: {=SUMPRODUCT(B$2:B217-F$3,B$2:B217-F$3)} -> #VALUE! | I217: {=SUMPRODUCT(B217:B$804-F$3,B217:B$804-F$3)} -> #VALUE! | J217: =G217/I$2 -> #VALUE!
A218: 45260 | B218: =Table3[[#This Row],[Combined Daily order]] -> 61216 | C218: 216 | D218: {=SUMPRODUCT(OFFSET($B$2:$B$804,0,0,803-C218)-AVERAGE($B$2:$B$804),OFFSET($B$2:$B$804,C218,0,803-C218)-AVERAGE($B$2:$B$804))/DEVSQ($B$2:$B$804)} -> #VALUE! | G218: {=SUMPRODUCT(B$2:B$804-F$3,B218:B1020-F$3)} -> #VALUE! | H218: {=SUMPRODUCT(B$2:B218-F$3,B$2:B218-F$3)} -> #VALUE! | I218: {=SUMPRODUCT(B218:B$804-F$3,B218:B$804-F$3)} -> #VALUE! | J218: =G218/I$2 -> #VALUE!
A219: 45259 | B219: =Table3[[#This Row],[Combined Daily order]] -> 41329 | C219: 217 | D219: {=SUMPRODUCT(OFFSET($B$2:$B$804,0,0,803-C219)-AVERAGE($B$2:$B$804),OFFSET($B$2:$B$804,C219,0,803-C219)-AVERAGE($B$2:$B$804))/DEVSQ($B$2:$B$804)} -> #VALUE! | G219: {=SUMPRODUCT(B$2:B$804-F$3,B219:B1021-F$3)} -> #VALUE! | H219: {=SUMPRODUCT(B$2:B219-F$3,B$2:B219-F$3)} -> #VALUE! | I219: {=SUMPRODUCT(B219:B$804-F$3,B219:B$804-F$3)} -> #VALUE! | J219: =G219/I$2 -> #VALUE!
A220: 45258 | B220: =Table3[[#This Row],[Combined Daily order]] -> 62400 | C220: 218 | D220: {=SUMPRODUCT(OFFSET($B$2:$B$804,0,0,803-C220)-AVERAGE($B$2:$B$804),OFFSET($B$2:$B$804,C220,0,803-C220)-AVERAGE($B$2:$B$804))/DEVSQ($B$2:$B$804)} -> #VALUE! | G220: {=SUMPRODUCT(B$2:B$804-F$3,B220:B1022-F$3)} -> #VALUE! | H220: {=SUMPRODUCT(B$2:B220-F$3,B$2:B220-F$3)} -> #VALUE! | I220: {=SUMPRODUCT(B220:B$804-F$3,B220:B$804-F$3)} -> #VALUE! | J220: =G220/I$2 -> #VALUE!
... A451: 44935 | B451: =Table3[[#This Row],[Combined Daily order]] -> 18397 | C451: 449 | D451: {=SUMPRODUCT(OFFSET($B$2:$B$804,0,0,803-C451)-AVERAGE($B$2:$B$804),OFFSET($B$2:$B$804,C451,0,803-C451)-AVERAGE($B$2:$B$804))/DEVSQ($B$2:$B$804)} -> #VALUE! | G451: {=SUMPRODUCT(B$2:B$804-F$3,B451:B1253-F$3)} -> #VALUE! | H451: {=SUMPRODUCT(B$2:B451-F$3,B$2:B451-F$3)} -> #VALUE! | I451: {=SUMPRODUCT(B451:B$804-F$3,B451:B$804-F$3)} -> #VALUE! | J451: =G451/I$2 -> #VALUE!
A452: 44932 | B452: =AVERAGE(B451,B453) -> 18623.5 | C452: 450 | D452: {=SUMPRODUCT(OFFSET($B$2:$B$804,0,0,803-C452)-AVERAGE($B$2:$B$804),OFFSET($B$2:$B$804,C452,0,803-C452)-AVERAGE($B$2:$B$804))/DEVSQ($B$2:$B$804)} -> #VALUE! | G452: {=SUMPRODUCT(B$2:B$804-F$3,B452:B1254-F$3)} -> #VALUE! | H452: {=SUMPRODUCT(B$2:B452-F$3,B$2:B452-F$3)} -> #VALUE! | I452: {=SUMPRODUCT(B452:B$804-F$3,B452:B$804-F$3)} -> #VALUE! | J452: =G452/I$2 -> #VALUE!
A453: 44931 | B453: =Table3[[#This Row],[Combined Daily order]] -> 18850 | C453: 451 | D453: {=SUMPRODUCT(OFFSET($B$2:$B$804,0,0,803-C453)-AVERAGE($B$2:$B$804),OFFSET($B$2:$B$804,C453,0,803-C453)-AVERAGE($B$2:$B$804))/DEVSQ($B$2:$B$804)} -> #VALUE! | G453: {=SUMPRODUCT(B$2:B$804-F$3,B453:B1255-F$3)} -> #VALUE! | H453: {=SUMPRODUCT(B$2:B453-F$3,B$2:B453-F$3)} -> #VALUE! | I453: {=SUMPRODUCT(B453:B$804-F$3,B453:B$804-F$3)} -> #VALUE! | J453: =G453/I$2 -> #VALUE!
A454: 44930 | B454: =AVERAGE(B453,B455) -> 21071 | C454: 452 | D454: {=SUMPRODUCT(OFFSET($B$2:$B$804,0,0,803-C454)-AVERAGE($B$2:$B$804),OFFSET($B$2:$B$804,C454,0,803-C454)-AVERAGE($B$2:$B$804))/DEVSQ($B$2:$B$804)} -> #VALUE! | G454: {=SUMPRODUCT(B$2:B$804-F$3,B454:B1256-F$3)} -> #VALUE! | H454: {=SUMPRODUCT(B$2:B454-F$3,B$2:B454-F$3)} -> #VALUE! | I454: {=SUMPRODUCT(B454:B$804-F$3,B454:B$804-F$3)} -> #VALUE! | J454: =G454/I$2 -> #VALUE!
